Workbook
Name UPDATE: 'Data Sheet'!$E$1

Sheet Financials>

Sheet HistoricalFS
B2: ="Historical Financial Statement - "&'Data Sheet'!B1 -> Historical Financial Statement - HINDUSTAN UNILEVER LTD
B3: Years | C3: ='Data Sheet'!B16 -> 42825 | D3: ='Data Sheet'!C16 -> 43190 | E3: ='Data Sheet'!D16 -> 43555 | F3: ='Data Sheet'!E16 -> 43921 | G3: ='Data Sheet'!F16 -> 44286 | H3: ='Data Sheet'!G16 -> 44651 | I3: ='Data Sheet'!H16 -> 45016 | J3: ='Data Sheet'!I16 -> 45382 | K3: ='Data Sheet'!J16 -> 45747
A5: # | B5: Income Statement
B6: Sales | C6: =IFERROR('Data Sheet'!B17,0) -> 33162 | D6: =IFERROR('Data Sheet'!C17,0) -> 35545 | E6: =IFERROR('Data Sheet'!D17,0) -> 39310 | F6: =IFERROR('Data Sheet'!E17,0) -> 39783 | G6: =IFERROR('Data Sheet'!F17,0) -> 47028 | H6: =IFERROR('Data Sheet'!G17,0) -> 52446 | I6: =IFERROR('Data Sheet'!H17,0) -> 60580 | J6: =IFERROR('Data Sheet'!I17,0) -> 61896 | K6: =IFERROR('Data Sheet'!J17,0) -> 63121
B7: Sales Growth | C7: - | D7: =D6/C6-1 -> 0.071859357 | E7: =E6/D6-1 -> 0.10592207 | F7: =F6/E6-1 -> 0.012032562 | G7: =G6/F6-1 -> 0.18211296 | H7: =H6/G6-1 -> 0.11520796 | I7: =I6/H6-1 -> 0.15509286 | J7: =J6/I6-1 -> 0.021723341 | K7: =K6/J6-1 -> 0.019791263
B9: COGS | C9: =IFERROR(SUM('Data Sheet'!B18,'Data Sheet'!B20:B22)-1*'Data Sheet'!B19,"-") -> 18675 | D9: =IFERROR(SUM('Data Sheet'!C18,'Data Sheet'!C20:C22)-1*'Data Sheet'!C19,"-") -> 19314 | E9: =IFERROR(SUM('Data Sheet'!D18,'Data Sheet'!D20:D22)-1*'Data Sheet'!D19,"-") -> 21081 | F9: =IFERROR(SUM('Data Sheet'!E18,'Data Sheet'!E20:E22)-1*'Data Sheet'!E19,"-") -> 20614 | G9: =IFERROR(SUM('Data Sheet'!F18,'Data Sheet'!F20:F22)-1*'Data Sheet'!F19,"-") -> 25301 | H9: =IFERROR(SUM('Data Sheet'!G18,'Data Sheet'!G20:G22)-1*'Data Sheet'!G19,"-") -> 29066 | I9: =IFERROR(SUM('Data Sheet'!H18,'Data Sheet'!H20:H22)-1*'Data Sheet'!H19,"-") -> 35381 | J9: =IFERROR(SUM('Data Sheet'!I18,'Data Sheet'!I20:I22)-1*'Data Sheet'!I19,"-") -> 33651 | K9: =IFERROR(SUM('Data Sheet'!J18,'Data Sheet'!J20:J22)-1*'Data Sheet'!J19,"-") -> 34529
B10: COGS as % Sales | C10: =C9/C6 -> 0.56314456 | D10: =D9/D6 -> 0.54336756 | E10: =E9/E6 -> 0.53627576 | F10: =F9/F6 -> 0.51816102 | G10: =G9/G6 -> 0.53799864 | H10: =H9/H6 -> 0.55420814 | I10: =I9/I6 -> 0.58403764 | J10: =J9/J6 -> 0.54367003 | K10: =K9/K6 -> 0.54702872
B12: Gross Profit | C12: =C6-C9 -> 14487 | D12: =D6-D9 -> 16231 | E12: =E6-E9 -> 18229 | F12: =F6-F9 -> 19169 | G12: =G6-G9 -> 21727 | H12: =H6-H9 -> 23380 | I12: =I6-I9 -> 25199 | J12: =J6-J9 -> 28245 | K12: =K6-K9 -> 28592
B13: Gross Margin | C13: =C12/C6 -> 0.43685544 | D13: =D12/D6 -> 0.45663244 | E13: =E12/E6 -> 0.46372424 | F13: =F12/F6 -> 0.48183898 | G13: =G12/G6 -> 0.46200136 | H13: =H12/H6 -> 0.44579186 | I13: =I12/I6 -> 0.41596236 | J13: =J12/J6 -> 0.45632997 | K13: =K12/K6 -> 0.45297128
B15: Selling & General Expenses | C15: =IFERROR(SUM('Data Sheet'!B23:B24),0) -> 8159 | D15: =IFERROR(SUM('Data Sheet'!C23:C24),0) -> 8732 | E15: =IFERROR(SUM('Data Sheet'!D23:D24),0) -> 9349 | F15: =IFERROR(SUM('Data Sheet'!E23:E24),0) -> 9308 | G15: =IFERROR(SUM('Data Sheet'!F23:F24),0) -> 10101 | H15: =IFERROR(SUM('Data Sheet'!G23:G24),0) -> 10523 | I15: =IFERROR(SUM('Data Sheet'!H23:H24),0) -> 11052 | J15: =IFERROR(SUM('Data Sheet'!I23:I24),0) -> 13586 | K15: =IFERROR(SUM('Data Sheet'!J23:J24),0) -> 13749
B16: S&G as % Sales | C16: =C15/C9 -> 0.43689424 | D16: =D15/D9 -> 0.45210728 | E16: =E15/E9 -> 0.44347991 | F16: =F15/F9 -> 0.45153779 | G16: =G15/G9 -> 0.39923323 | H16: =H15/H9 -> 0.36203812 | I16: =I15/I9 -> 0.31237105 | J16: =J15/J9 -> 0.40373243 | K16: =K15/K9 -> 0.39818703
B18: EBITDA | C18: =C12-C15 -> 6328 | D18: =D12-D15 -> 7499 | E18: =E12-E15 -> 8880 | F18: =F12-F15 -> 9861 | G18: =G12-G15 -> 11626 | H18: =H12-H15 -> 12857 | I18: =I12-I15 -> 14147 | J18: =J12-J15 -> 14659 | K18: =K12-K15 -> 14843
B19: EBITDA as % Sales | C19: =C18/C6 -> 0.19082082 | D19: =D18/D6 -> 0.21097201 | E19: =E18/E6 -> 0.22589672 | F19: =F18/F6 -> 0.24786969 | G19: =G18/G6 -> 0.24721443 | H19: =H18/H6 -> 0.24514739 | I19: =I18/I6 -> 0.23352592 | J19: =J18/J6 -> 0.23683275 | K19: =K18/K6 -> 0.23515153
B21: Depreciation | C21: =IFERROR('Data Sheet'!B26,0) -> 432 | D21: =IFERROR('Data Sheet'!C26,0) -> 520 | E21: =IFERROR('Data Sheet'!D26,0) -> 565 | F21: =IFERROR('Data Sheet'!E26,0) -> 1002 | G21: =IFERROR('Data Sheet'!F26,0) -> 1074 | H21: =IFERROR('Data Sheet'!G26,0) -> 1091 | I21: =IFERROR('Data Sheet'!H26,0) -> 1137 | J21: =IFERROR('Data Sheet'!I26,0) -> 1216 | K21: =IFERROR('Data Sheet'!J26,0) -> 1355
B22: Depreciation as % Sales | C22: =C21/C6 -> 0.013026959 | D22: =D21/D6 -> 0.014629343 | E22: =E21/E6 -> 0.014372933 | F22: =F21/F6 -> 0.025186638 | G22: =G21/G6 -> 0.022837459 | H22: =H21/H6 -> 0.020802349 | I22: =I21/I6 -> 0.01876857 | J22: =J21/J6 -> 0.019645858 | K22: =K21/K6 -> 0.021466707
B24: EBIT | C24: =C18-C21 -> 5896 | D24: =D18-D21 -> 6979 | E24: =E18-E21 -> 8315 | F24: =F18-F21 -> 8859 | G24: =G18-G21 -> 10552 | H24: =H18-H21 -> 11766 | I24: =I18-I21 -> 13010 | J24: =J18-J21 -> 13443 | K24: =K18-K21 -> 13488
B25: EBITDA as % Sales | C25: =C24/C6 -> 0.17779386 | D25: =D24/D6 -> 0.19634266 | E25: =E24/E6 -> 0.21152379 | F25: =F24/F6 -> 0.22268306 | G25: =G24/G6 -> 0.22437697 | H25: =H24/H6 -> 0.22434504 | I25: =I24/I6 -> 0.21475735 | J25: =J24/J6 -> 0.21718689 | K25: =K24/K6 -> 0.21368483
B27: Interest | C27: =IFERROR('Data Sheet'!B27,0) -> 35 | D27: =IFERROR('Data Sheet'!C27,0) -> 26 | E27: =IFERROR('Data Sheet'!D27,0) -> 33 | F27: =IFERROR('Data Sheet'!E27,0) -> 118 | G27: =IFERROR('Data Sheet'!F27,0) -> 117 | H27: =IFERROR('Data Sheet'!G27,0) -> 106 | I27: =IFERROR('Data Sheet'!H27,0) -> 114 | J27: =IFERROR('Data Sheet'!I27,0) -> 334 | K27: =IFERROR('Data Sheet'!J27,0) -> 395
B28: Interest as % Sales | C28: =C27/C6 -> 0.0010554249 | D28: =D27/D6 -> 0.00073146715 | E28: =E27/E6 -> 0.00083948105 | F28: =F27/F6 -> 0.002966091 | G28: =G27/G6 -> 0.0024878796 | H28: =H27/H6 -> 0.0020211265 | I28: =I27/I6 -> 0.0018818092 | J28: =J27/J6 -> 0.0053961484 | K28: =K27/K6 -> 0.0062578223
B30: EBT | C30: =C24-C27 -> 5861 | D30: =D24-D27 -> 6953 | E30: =E24-E27 -> 8282 | F30: =F24-F27 -> 8741 | G30: =G24-G27 -> 10435 | H30: =H24-H27 -> 11660 | I30: =I24-I27 -> 12896 | J30: =J24-J27 -> 13109 | K30: =K24-K27 -> 13093
B31: EBT as % Sales | C31: =C30/C6 -> 0.17673844 | D31: =D30/D6 -> 0.1956112 | E31: =E30/E6 -> 0.2106843 | F31: =F30/F6 -> 0.21971696 | G31: =G30/G6 -> 0.22188909 | H31: =H30/H6 -> 0.22232391 | I31: =I30/I6 -> 0.21287554 | J31: =J30/J6 -> 0.21179075 | K31: =K30/K6 -> 0.20742701
B33: Tax | C33: =IFERROR('Data Sheet'!B29,0) -> 1977 | D33: =IFERROR('Data Sheet'!C29,0) -> 2079 | E33: =IFERROR('Data Sheet'!D29,0) -> 2544 | F33: =IFERROR('Data Sheet'!E29,0) -> 2409 | G33: =IFERROR('Data Sheet'!F29,0) -> 2606 | H33: =IFERROR('Data Sheet'!G29,0) -> 2987 | I33: =IFERROR('Data Sheet'!H29,0) -> 3201 | J33: =IFERROR('Data Sheet'!I29,0) -> 3644 | K33: =IFERROR('Data Sheet'!J29,0) -> 3744
B34: Effective Tax Rate | C34: =C33/C30 -> 0.33731445 | D34: =D33/D30 -> 0.29900762 | E34: =E33/E30 -> 0.30717218 | F34: =F33/F30 -> 0.27559776 | G34: =G33/G30 -> 0.24973646 | H34: =H33/H30 -> 0.25617496 | I34: =I33/I30 -> 0.2482165 | J34: =J33/J30 -> 0.27797696 | K34: =K33/K30 -> 0.28595433
B36: Net Profit | C36: =C30-C33 -> 3884 | D36: =D30-D33 -> 4874 | E36: =E30-E33 -> 5738 | F36: =F30-F33 -> 6332 | G36: =G30-G33 -> 7829 | H36: =H30-H33 -> 8673 | I36: =I30-I33 -> 9695 | J36: =J30-J33 -> 9465 | K36: =K30-K33 -> 9349
B37: Net Margins | C37: =C36/C6 -> 0.11712201 | D37: =D36/D6 -> 0.13712196 | E37: =E36/E6 -> 0.14596795 | F37: =F36/F6 -> 0.15916346 | G37: =G36/G6 -> 0.16647529 | H37: =H36/H6 -> 0.16537009 | I37: =I36/I6 -> 0.16003632 | J37: =J36/J6 -> 0.1529178 | K37: =K36/K6 -> 0.14811236
B39: No of Equity Shares | C39: =IFERROR('Data Sheet'!B93,0) -> 216.43 | D39: =IFERROR('Data Sheet'!C93,0) -> 216.45 | E39: =IFERROR('Data Sheet'!D93,0) -> 216.47 | F39: =IFERROR('Data Sheet'!E93,0) -> 216.48 | G39: =IFERROR('Data Sheet'!F93,0) -> 234.96 | H39: =IFERROR('Data Sheet'!G93,0) -> 234.96 | I39: =IFERROR('Data Sheet'!H93,0) -> 234.96 | J39: =IFERROR('Data Sheet'!I93,0) -> 234.96 | K39: =IFERROR('Data Sheet'!J93,0) -> 234.96
B41: Earnings Per Share | C41: =IFERROR(C36/C39,0) -> 17.945756 | D41: =IFERROR(D36/D39,0) -> 22.517903 | E41: =IFERROR(E36/E39,0) -> 26.507137 | F41: =IFERROR(F36/F39,0) -> 29.249815 | G41: =IFERROR(G36/G39,0) -> 33.320565 | H41: =IFERROR(H36/H39,0) -> 36.912666 | I41: =IFERROR(I36/I39,0) -> 41.262343 | J41: =IFERROR(J36/J39,0) -> 40.283453 | K41: =IFERROR(K36/K39,0) -> 39.789751
B42: Earnings Per Share Growth | C42: - | D42: =D41/C41-1 -> 0.25477591 | E42: =E41/D41-1 -> 0.17715836 | F42: =F41/E41-1 -> 0.10346941 | G42: =G41/F41-1 -> 0.13917182 | H42: =H41/G41-1 -> 0.10780432 | I42: =I41/H41-1 -> 0.11783697 | J42: =J41/I41-1 -> -0.023723569 | K42: =K41/J41-1 -> -0.012255679
B44: Dividends Per Share | C44: =IFERROR('Data Sheet'!B31/'Data Sheet'!B93,0) -> 16.966225 | D44: =IFERROR('Data Sheet'!C31/'Data Sheet'!C93,0) -> 19.95842 | E44: =IFERROR('Data Sheet'!D31/'Data Sheet'!D93,0) -> 21.952234 | F44: =IFERROR('Data Sheet'!E31/'Data Sheet'!E93,0) -> 24.944568 | G44: =IFERROR('Data Sheet'!F31/'Data Sheet'!F93,0) -> 40.506895 | H44: =IFERROR('Data Sheet'!G31/'Data Sheet'!G93,0) -> 34.005788 | I44: =IFERROR('Data Sheet'!H31/'Data Sheet'!H93,0) -> 39.006639 | J44: =IFERROR('Data Sheet'!I31/'Data Sheet'!I93,0) -> 42.00715 | K44: =IFERROR('Data Sheet'!J31/'Data Sheet'!J93,0) -> 53.009023
B45: Dividends Payout Ratio | C45: =C44/C41 -> 0.9454171 | D45: =D44/D41 -> 0.88633566 | E45: =E44/E41 -> 0.82816312 | F45: =F44/F41 -> 0.85281112 | G45: =G44/G41 -> 1.2156725 | H45: =H44/H41 -> 0.92124986 | I45: =I44/I41 -> 0.94533265 | J45: =J44/J41 -> 1.0427892 | K45: =K44/K41 -> 1.332228
B47: Retained Earnings | C47: =IFERROR(IF(C41>C44,1-C45,0),0) -> 0.054582904 | D47: =IFERROR(IF(D41>D44,1-D45,0),0) -> 0.11366434 | E47: =IFERROR(IF(E41>E44,1-E45,0),0) -> 0.17183688 | F47: =IFERROR(IF(F41>F44,1-F45,0),0) -> 0.14718888 | G47: =IFERROR(IF(G41>G44,1-G45,0),0) -> 0 | H47: =IFERROR(IF(H41>H44,1-H45,0),0) -> 0.078750144 | I47: =IFERROR(IF(I41>I44,1-I45,0),0) -> 0.054667354 | J47: =IFERROR(IF(J41>J44,1-J45,0),0) -> 0 | K47: =IFERROR(IF(K41>K44,1-K45,0),0) -> 0
A49: # | B49: Balance Sheet
B50: Equity Share Capital | C50: =IFERROR('Data Sheet'!B57,0) -> 216 | D50: =IFERROR('Data Sheet'!C57,0) -> 216 | E50: =IFERROR('Data Sheet'!D57,0) -> 216 | F50: =IFERROR('Data Sheet'!E57,0) -> 216 | G50: =IFERROR('Data Sheet'!F57,0) -> 235 | H50: =IFERROR('Data Sheet'!G57,0) -> 235 | I50: =IFERROR('Data Sheet'!H57,0) -> 235 | J50: =IFERROR('Data Sheet'!I57,0) -> 235 | K50: =IFERROR('Data Sheet'!J57,0) -> 235
B51: Reserves | C51: =IFERROR('Data Sheet'!B58,0) -> 6528 | D51: =IFERROR('Data Sheet'!C58,0) -> 7065 | E51: =IFERROR('Data Sheet'!D58,0) -> 7651 | F51: =IFERROR('Data Sheet'!E58,0) -> 8013 | G51: =IFERROR('Data Sheet'!F58,0) -> 47439 | H51: =IFERROR('Data Sheet'!G58,0) -> 48826 | I51: =IFERROR('Data Sheet'!H58,0) -> 50069 | J51: =IFERROR('Data Sheet'!I58,0) -> 50983 | K51: =IFERROR('Data Sheet'!J58,0) -> 49167
B52: Borrowings | C52: =IFERROR('Data Sheet'!B59,0) -> 277 | D52: =IFERROR('Data Sheet'!C59,0) -> 0 | E52: =IFERROR('Data Sheet'!D59,0) -> 99 | F52: =IFERROR('Data Sheet'!E59,0) -> 0 | G52: =IFERROR('Data Sheet'!F59,0) -> 0 | H52: =IFERROR('Data Sheet'!G59,0) -> 1043 | I52: =IFERROR('Data Sheet'!H59,0) -> 1219 | J52: =IFERROR('Data Sheet'!I59,0) -> 1484 | K52: =IFERROR('Data Sheet'!J59,0) -> 1648
B53: Other Liabilities | C53: =IFERROR('Data Sheet'!B60,0) -> 8685 | D53: =IFERROR('Data Sheet'!C60,0) -> 10581 | E53: =IFERROR('Data Sheet'!D60,0) -> 10663 | F53: =IFERROR('Data Sheet'!E60,0) -> 11924 | G53: =IFERROR('Data Sheet'!F60,0) -> 21066 | H53: =IFERROR('Data Sheet'!G60,0) -> 20402 | I53: =IFERROR('Data Sheet'!H60,0) -> 21554 | J53: =IFERROR('Data Sheet'!I60,0) -> 25787 | K53: =IFERROR('Data Sheet'!J60,0) -> 28813
B54: Total Liabilities | C54: =IFERROR('Data Sheet'!B61,0) -> 15706 | D54: =IFERROR('Data Sheet'!C61,0) -> 17862 | E54: =IFERROR('Data Sheet'!D61,0) -> 18629 | F54: =IFERROR('Data Sheet'!E61,0) -> 20153 | G54: =IFERROR('Data Sheet'!F61,0) -> 68740 | H54: =IFERROR('Data Sheet'!G61,0) -> 70506 | I54: =IFERROR('Data Sheet'!H61,0) -> 73077 | J54: =IFERROR('Data Sheet'!I61,0) -> 78489 | K54: =IFERROR('Data Sheet'!J61,0) -> 79863
B56: Fixed Assets Net Block | C56: =IFERROR('Data Sheet'!B62,0) -> 4419 | D56: =IFERROR('Data Sheet'!C62,0) -> 4528 | E56: =IFERROR('Data Sheet'!D62,0) -> 4715 | F56: =IFERROR('Data Sheet'!E62,0) -> 5479 | G56: =IFERROR('Data Sheet'!F62,0) -> 51443 | H56: =IFERROR('Data Sheet'!G62,0) -> 51473 | I56: =IFERROR('Data Sheet'!H62,0) -> 52678 | J56: =IFERROR('Data Sheet'!I62,0) -> 53744 | K56: =IFERROR('Data Sheet'!J62,0) -> 54335
B57: Capital Work in Progress | C57: =IFERROR('Data Sheet'!B63,0) -> 229 | D57: =IFERROR('Data Sheet'!C63,0) -> 461 | E57: =IFERROR('Data Sheet'!D63,0) -> 406 | F57: =IFERROR('Data Sheet'!E63,0) -> 597 | G57: =IFERROR('Data Sheet'!F63,0) -> 745 | H57: =IFERROR('Data Sheet'!G63,0) -> 1313 | I57: =IFERROR('Data Sheet'!H63,0) -> 1132 | J57: =IFERROR('Data Sheet'!I63,0) -> 1025 | K57: =IFERROR('Data Sheet'!J63,0) -> 1009
B58: Investments | C58: =IFERROR('Data Sheet'!B64,0) -> 3794 | D58: =IFERROR('Data Sheet'!C64,0) -> 2873 | E58: =IFERROR('Data Sheet'!D64,0) -> 2716 | F58: =IFERROR('Data Sheet'!E64,0) -> 1255 | G58: =IFERROR('Data Sheet'!F64,0) -> 2709 | H58: =IFERROR('Data Sheet'!G64,0) -> 3521 | I58: =IFERROR('Data Sheet'!H64,0) -> 2882 | J58: =IFERROR('Data Sheet'!I64,0) -> 4625 | K58: =IFERROR('Data Sheet'!J64,0) -> 3810
B59: Other Assets | C59: =IFERROR('Data Sheet'!B65-SUM('Data Sheet'!B67:B69),0) -> 1810 | D59: =IFERROR('Data Sheet'!C65-SUM('Data Sheet'!C67:C69),0) -> 2692 | E59: =IFERROR('Data Sheet'!D65-SUM('Data Sheet'!D67:D69),0) -> 2645 | F59: =IFERROR('Data Sheet'!E65-SUM('Data Sheet'!E67:E69),0) -> 3793 | G59: =IFERROR('Data Sheet'!F65-SUM('Data Sheet'!F67:F69),0) -> 4035 | H59: =IFERROR('Data Sheet'!G65-SUM('Data Sheet'!G67:G69),0) -> 4021 | I59: =IFERROR('Data Sheet'!H65-SUM('Data Sheet'!H67:H69),0) -> 4377 | J59: =IFERROR('Data Sheet'!I65-SUM('Data Sheet'!I67:I69),0) -> 4517 | K59: =IFERROR('Data Sheet'!J65-SUM('Data Sheet'!J67:J69),0) -> 4921
B60: Total Non-Current Assets | C60: =SUM(C56:C59) -> 10252 | D60: =SUM(D56:D59) -> 10554 | E60: =SUM(E56:E59) -> 10482 | F60: =SUM(F56:F59) -> 11124 | G60: =SUM(G56:G59) -> 58932 | H60: =SUM(H56:H59) -> 60328 | I60: =SUM(I56:I59) -> 61069 | J60: =SUM(J56:J59) -> 63911 | K60: =SUM(K56:K59) -> 64075
B62: Receivables | C62: =IFERROR('Data Sheet'!B67,0) -> 1085 | D62: =IFERROR('Data Sheet'!C67,0) -> 1310 | E62: =IFERROR('Data Sheet'!D67,0) -> 1816 | F62: =IFERROR('Data Sheet'!E67,0) -> 1149 | G62: =IFERROR('Data Sheet'!F67,0) -> 1758 | H62: =IFERROR('Data Sheet'!G67,0) -> 2236 | I62: =IFERROR('Data Sheet'!H67,0) -> 3079 | J62: =IFERROR('Data Sheet'!I67,0) -> 2997 | K62: =IFERROR('Data Sheet'!J67,0) -> 3819
B63: Inventory | C63: =IFERROR('Data Sheet'!B68,0) -> 2541 | D63: =IFERROR('Data Sheet'!C68,0) -> 2513 | E63: =IFERROR('Data Sheet'!D68,0) -> 2574 | F63: =IFERROR('Data Sheet'!E68,0) -> 2767 | G63: =IFERROR('Data Sheet'!F68,0) -> 3579 | H63: =IFERROR('Data Sheet'!G68,0) -> 4096 | I63: =IFERROR('Data Sheet'!H68,0) -> 4251 | J63: =IFERROR('Data Sheet'!I68,0) -> 4022 | K63: =IFERROR('Data Sheet'!J68,0) -> 4415
B64: Cash & Bank | C64: =IFERROR('Data Sheet'!B69,0) -> 1828 | D64: =IFERROR('Data Sheet'!C69,0) -> 3485 | E64: =IFERROR('Data Sheet'!D69,0) -> 3757 | F64: =IFERROR('Data Sheet'!E69,0) -> 5113 | G64: =IFERROR('Data Sheet'!F69,0) -> 4471 | H64: =IFERROR('Data Sheet'!G69,0) -> 3846 | I64: =IFERROR('Data Sheet'!H69,0) -> 4678 | J64: =IFERROR('Data Sheet'!I69,0) -> 7559 | K64: =IFERROR('Data Sheet'!J69,0) -> 7554
B65: Total Current Assets | C65: =SUM(C62:C64) -> 5454 | D65: =SUM(D62:D64) -> 7308 | E65: =SUM(E62:E64) -> 8147 | F65: =SUM(F62:F64) -> 9029 | G65: =SUM(G62:G64) -> 9808 | H65: =SUM(H62:H64) -> 10178 | I65: =SUM(I62:I64) -> 12008 | J65: =SUM(J62:J64) -> 14578 | K65: =SUM(K62:K64) -> 15788
B67: Total Assets | C67: =C65+C60 -> 15706 | D67: =D65+D60 -> 17862 | E67: =E65+E60 -> 18629 | F67: =F65+F60 -> 20153 | G67: =G65+G60 -> 68740 | H67: =H65+H60 -> 70506 | I67: =I65+I60 -> 73077 | J67: =J65+J60 -> 78489 | K67: =K65+K60 -> 79863
A69: # | B69: Cash Flow Statement
B70: Operating Activities
B71: Profit from operations | C71: =IFERROR('Cash Flow Data'!E4,0) -> 984 | D71: =IFERROR('Cash Flow Data'!F4,0) -> 1375 | E71: =IFERROR('Cash Flow Data'!G4,0) -> 1659 | F71: =IFERROR('Cash Flow Data'!H4,0) -> 2149 | G71: =IFERROR('Cash Flow Data'!I4,0) -> 1764 | H71: =IFERROR('Cash Flow Data'!J4,0) -> 2515 | I71: =IFERROR('Cash Flow Data'!K4,0) -> 3659 | J71: =IFERROR('Cash Flow Data'!L4,0) -> 4131 | K71: =IFERROR('Cash Flow Data'!M4,0) -> 4535
B72: Receivables | C72: =IFERROR('Cash Flow Data'!E5,0) -> 54 | D72: =IFERROR('Cash Flow Data'!F5,0) -> -13 | E72: =IFERROR('Cash Flow Data'!G5,0) -> -31 | F72: =IFERROR('Cash Flow Data'!H5,0) -> 45 | G72: =IFERROR('Cash Flow Data'!I5,0) -> -24 | H72: =IFERROR('Cash Flow Data'!J5,0) -> -23 | I72: =IFERROR('Cash Flow Data'!K5,0) -> 5 | J72: =IFERROR('Cash Flow Data'!L5,0) -> -104 | K72: =IFERROR('Cash Flow Data'!M5,0) -> 13
B73: Inventory | C73: =IFERROR('Cash Flow Data'!E6,0) -> -276 | D73: =IFERROR('Cash Flow Data'!F6,0) -> -212 | E73: =IFERROR('Cash Flow Data'!G6,0) -> -445 | F73: =IFERROR('Cash Flow Data'!H6,0) -> -339 | G73: =IFERROR('Cash Flow Data'!I6,0) -> -301 | H73: =IFERROR('Cash Flow Data'!J6,0) -> -494 | I73: =IFERROR('Cash Flow Data'!K6,0) -> -501 | J73: =IFERROR('Cash Flow Data'!L6,0) -> -684 | K73: =IFERROR('Cash Flow Data'!M6,0) -> -1117
B74: Payables | C74: =IFERROR('Cash Flow Data'!E7,0) -> 0 | D74: =IFERROR('Cash Flow Data'!F7,0) -> 55 | E74: =IFERROR('Cash Flow Data'!G7,0) -> 146 | F74: =IFERROR('Cash Flow Data'!H7,0) -> -30 | G74: =IFERROR('Cash Flow Data'!I7,0) -> 145 | H74: =IFERROR('Cash Flow Data'!J7,0) -> 11 | I74: =IFERROR('Cash Flow Data'!K7,0) -> 165 | J74: =IFERROR('Cash Flow Data'!L7,0) -> 231 | K74: =IFERROR('Cash Flow Data'!M7,0) -> 86
B75: Loan & Advances | C75: =IFERROR('Cash Flow Data'!E8,0) -> 0 | D75: =IFERROR('Cash Flow Data'!F8,0) -> 0 | E75: =IFERROR('Cash Flow Data'!G8,0) -> 0 | F75: =IFERROR('Cash Flow Data'!H8,0) -> 0 | G75: =IFERROR('Cash Flow Data'!I8,0) -> 0 | H75: =IFERROR('Cash Flow Data'!J8,0) -> 0 | I75: =IFERROR('Cash Flow Data'!K8,0) -> 0 | J75: =IFERROR('Cash Flow Data'!L8,0) -> 0 | K75: =IFERROR('Cash Flow Data'!M8,0) -> 0
B76: Operating Investments | C76: =IFERROR('Cash Flow Data'!E9,0) -> -2 | D76: =IFERROR('Cash Flow Data'!F9,0) -> -62 | E76: =IFERROR('Cash Flow Data'!G9,0) -> 52 | F76: =IFERROR('Cash Flow Data'!H9,0) -> 2 | G76: =IFERROR('Cash Flow Data'!I9,0) -> 12 | H76: =IFERROR('Cash Flow Data'!J9,0) -> -3 | I76: =IFERROR('Cash Flow Data'!K9,0) -> 0 | J76: =IFERROR('Cash Flow Data'!L9,0) -> 0 | K76: =IFERROR('Cash Flow Data'!M9,0) -> 0
B77: Other WC Items | C77: =IFERROR('Cash Flow Data'!E10,0) -> -46 | D77: =IFERROR('Cash Flow Data'!F10,0) -> -11 | E77: =IFERROR('Cash Flow Data'!G10,0) -> -72 | F77: =IFERROR('Cash Flow Data'!H10,0) -> -54 | G77: =IFERROR('Cash Flow Data'!I10,0) -> 41 | H77: =IFERROR('Cash Flow Data'!J10,0) -> -73 | I77: =IFERROR('Cash Flow Data'!K10,0) -> 12 | J77: =IFERROR('Cash Flow Data'!L10,0) -> -87 | K77: =IFERROR('Cash Flow Data'!M10,0) -> -94
B78: Working capital changes | C78: =IFERROR('Cash Flow Data'!E11,0) -> -270 | D78: =IFERROR('Cash Flow Data'!F11,0) -> -243 | E78: =IFERROR('Cash Flow Data'!G11,0) -> -351 | F78: =IFERROR('Cash Flow Data'!H11,0) -> -376 | G78: =IFERROR('Cash Flow Data'!I11,0) -> -127 | H78: =IFERROR('Cash Flow Data'!J11,0) -> -582 | I78: =IFERROR('Cash Flow Data'!K11,0) -> -320 | J78: =IFERROR('Cash Flow Data'!L11,0) -> -644 | K78: =IFERROR('Cash Flow Data'!M11,0) -> -1113
B79: Direct taxes | C79: =IFERROR('Cash Flow Data'!E12,0) -> -258 | D79: =IFERROR('Cash Flow Data'!F12,0) -> -403 | E79: =IFERROR('Cash Flow Data'!G12,0) -> -502 | F79: =IFERROR('Cash Flow Data'!H12,0) -> -492 | G79: =IFERROR('Cash Flow Data'!I12,0) -> -262 | H79: =IFERROR('Cash Flow Data'!J12,0) -> -560 | I79: =IFERROR('Cash Flow Data'!K12,0) -> -709 | J79: =IFERROR('Cash Flow Data'!L12,0) -> -742 | K79: =IFERROR('Cash Flow Data'!M12,0) -> -959
B80: Cash From Operating Activities | C80: =IFERROR(SUM(C71,C78,C79),0) -> 456 | D80: =IFERROR(SUM(D71,D78,D79),0) -> 729 | E80: =IFERROR(SUM(E71,E78,E79),0) -> 806 | F80: =IFERROR(SUM(F71,F78,F79),0) -> 1281 | G80: =IFERROR(SUM(G71,G78,G79),0) -> 1375 | H80: =IFERROR(SUM(H71,H78,H79),0) -> 1373 | I80: =IFERROR(SUM(I71,I78,I79),0) -> 2630 | J80: =IFERROR(SUM(J71,J78,J79),0) -> 2745 | K80: =IFERROR(SUM(K71,K78,K79),0) -> 2463
B82: Investing Activities
B83: Fixed assets purchased | C83: =IFERROR('Cash Flow Data'!E14,0) -> -645 | D83: =IFERROR('Cash Flow Data'!F14,0) -> -916 | E83: =IFERROR('Cash Flow Data'!G14,0) -> -1417 | F83: =IFERROR('Cash Flow Data'!H14,0) -> -1712 | G83: =IFERROR('Cash Flow Data'!I14,0) -> -2029 | H83: =IFERROR('Cash Flow Data'!J14,0) -> -2410 | I83: =IFERROR('Cash Flow Data'!K14,0) -> -2212 | J83: =IFERROR('Cash Flow Data'!L14,0) -> -2731 | K83: =IFERROR('Cash Flow Data'!M14,0) -> -3423
B84: Fixed assets sold | C84: =IFERROR('Cash Flow Data'!E15,0) -> 10 | D84: =IFERROR('Cash Flow Data'!F15,0) -> 7 | E84: =IFERROR('Cash Flow Data'!G15,0) -> 8 | F84: =IFERROR('Cash Flow Data'!H15,0) -> 6 | G84: =IFERROR('Cash Flow Data'!I15,0) -> 2 | H84: =IFERROR('Cash Flow Data'!J15,0) -> 21 | I84: =IFERROR('Cash Flow Data'!K15,0) -> 5 | J84: =IFERROR('Cash Flow Data'!L15,0) -> 9 | K84: =IFERROR('Cash Flow Data'!M15,0) -> 6
B85: Investments purchased | C85: =IFERROR('Cash Flow Data'!E16,0) -> 0 | D85: =IFERROR('Cash Flow Data'!F16,0) -> 0 | E85: =IFERROR('Cash Flow Data'!G16,0) -> 0 | F85: =IFERROR('Cash Flow Data'!H16,0) -> 0 | G85: =IFERROR('Cash Flow Data'!I16,0) -> 0 | H85: =IFERROR('Cash Flow Data'!J16,0) -> 0 | I85: =IFERROR('Cash Flow Data'!K16,0) -> -193 | J85: =IFERROR('Cash Flow Data'!L16,0) -> -4201 | K85: =IFERROR('Cash Flow Data'!M16,0) -> -4948
B86: Investments sold | C86: =IFERROR('Cash Flow Data'!E17,0) -> 0 | D86: =IFERROR('Cash Flow Data'!F17,0) -> 1376 | E86: =IFERROR('Cash Flow Data'!G17,0) -> 410 | F86: =IFERROR('Cash Flow Data'!H17,0) -> 232 | G86: =IFERROR('Cash Flow Data'!I17,0) -> 3 | H86: =IFERROR('Cash Flow Data'!J17,0) -> 4 | I86: =IFERROR('Cash Flow Data'!K17,0) -> 6 | J86: =IFERROR('Cash Flow Data'!L17,0) -> 4324 | K86: =IFERROR('Cash Flow Data'!M17,0) -> 5074
B87: Investment Income | C87: =IFERROR('Cash Flow Data'!E18,0) -> 8 | D87: =IFERROR('Cash Flow Data'!F18,0) -> 0 | E87: =IFERROR('Cash Flow Data'!G18,0) -> 0 | F87: =IFERROR('Cash Flow Data'!H18,0) -> 0 | G87: =IFERROR('Cash Flow Data'!I18,0) -> 0 | H87: =IFERROR('Cash Flow Data'!J18,0) -> 0 | I87: =IFERROR('Cash Flow Data'!K18,0) -> 0 | J87: =IFERROR('Cash Flow Data'!L18,0) -> 0 | K87: =IFERROR('Cash Flow Data'!M18,0) -> 0
B88: Interest received | C88: =IFERROR('Cash Flow Data'!E19,0) -> 1 | D88: =IFERROR('Cash Flow Data'!F19,0) -> 31 | E88: =IFERROR('Cash Flow Data'!G19,0) -> 36 | F88: =IFERROR('Cash Flow Data'!H19,0) -> 12 | G88: =IFERROR('Cash Flow Data'!I19,0) -> 129 | H88: =IFERROR('Cash Flow Data'!J19,0) -> 43 | I88: =IFERROR('Cash Flow Data'!K19,0) -> 39 | J88: =IFERROR('Cash Flow Data'!L19,0) -> 262 | K88: =IFERROR('Cash Flow Data'!M19,0) -> 103
B89: Dividends received | C89: =IFERROR('Cash Flow Data'!E20,0) -> 0 | D89: =IFERROR('Cash Flow Data'!F20,0) -> 0 | E89: =IFERROR('Cash Flow Data'!G20,0) -> 0 | F89: =IFERROR('Cash Flow Data'!H20,0) -> 0 | G89: =IFERROR('Cash Flow Data'!I20,0) -> 0 | H89: =IFERROR('Cash Flow Data'!J20,0) -> 0 | I89: =IFERROR('Cash Flow Data'!K20,0) -> 0 | J89: =IFERROR('Cash Flow Data'!L20,0) -> 0 | K89: =IFERROR('Cash Flow Data'!M20,0) -> 0
B90: Invest in subsidiaries | C90: =IFERROR('Cash Flow Data'!E21,0) -> -21 | D90: =IFERROR('Cash Flow Data'!F21,0) -> -49 | E90: =IFERROR('Cash Flow Data'!G21,0) -> 0 | F90: =IFERROR('Cash Flow Data'!H21,0) -> 0 | G90: =IFERROR('Cash Flow Data'!I21,0) -> 0 | H90: =IFERROR('Cash Flow Data'!J21,0) -> 0 | I90: =IFERROR('Cash Flow Data'!K21,0) -> 0 | J90: =IFERROR('Cash Flow Data'!L21,0) -> 0 | K90: =IFERROR('Cash Flow Data'!M21,0) -> 0
B91: Redemption & Cancellation of Shares | C91: =IFERROR('Cash Flow Data'!E22,0) -> 0 | D91: =IFERROR('Cash Flow Data'!F22,0) -> 8 | E91: =IFERROR('Cash Flow Data'!G22,0) -> 0 | F91: =IFERROR('Cash Flow Data'!H22,0) -> 0 | G91: =IFERROR('Cash Flow Data'!I22,0) -> 0 | H91: =IFERROR('Cash Flow Data'!J22,0) -> 0 | I91: =IFERROR('Cash Flow Data'!K22,0) -> 0 | J91: =IFERROR('Cash Flow Data'!L22,0) -> 0 | K91: =IFERROR('Cash Flow Data'!M22,0) -> 0
B92: Other investing items | C92: =IFERROR('Cash Flow Data'!E23,0) -> -1835 | D92: =IFERROR('Cash Flow Data'!F23,0) -> 7 | E92: =IFERROR('Cash Flow Data'!G23,0) -> 3 | F92: =IFERROR('Cash Flow Data'!H23,0) -> -3194 | G92: =IFERROR('Cash Flow Data'!I23,0) -> 786 | H92: =IFERROR('Cash Flow Data'!J23,0) -> 1054 | I92: =IFERROR('Cash Flow Data'!K23,0) -> 42 | J92: =IFERROR('Cash Flow Data'!L23,0) -> -131 | K92: =IFERROR('Cash Flow Data'!M23,0) -> 1004
B93: Cash From Investing Activities | C93: =IFERROR(SUM(C83:C92),0) -> -2482 | D93: =IFERROR(SUM(D83:D92),0) -> 464 | E93: =IFERROR(SUM(E83:E92),0) -> -960 | F93: =IFERROR(SUM(F83:F92),0) -> -4656 | G93: =IFERROR(SUM(G83:G92),0) -> -1109 | H93: =IFERROR(SUM(H83:H92),0) -> -1288 | I93: =IFERROR(SUM(I83:I92),0) -> -2313 | J93: =IFERROR(SUM(J83:J92),0) -> -2468 | K93: =IFERROR(SUM(K83:K92),0) -> -2184
B95: Financing Activities
B96: Proceeds from shares | C96: =IFERROR('Cash Flow Data'!E25,0) -> 1841 | D96: =IFERROR('Cash Flow Data'!F25,0) -> 0 | E96: =IFERROR('Cash Flow Data'!G25,0) -> 0 | F96: =IFERROR('Cash Flow Data'!H25,0) -> 110 | G96: =IFERROR('Cash Flow Data'!I25,0) -> 0 | H96: =IFERROR('Cash Flow Data'!J25,0) -> 0 | I96: =IFERROR('Cash Flow Data'!K25,0) -> 15 | J96: =IFERROR('Cash Flow Data'!L25,0) -> 75 | K96: =IFERROR('Cash Flow Data'!M25,0) -> 0
B97: Proceeds from debentures | C97: =IFERROR('Cash Flow Data'!E26,0) -> 250 | D97: =IFERROR('Cash Flow Data'!F26,0) -> 0 | E97: =IFERROR('Cash Flow Data'!G26,0) -> 0 | F97: =IFERROR('Cash Flow Data'!H26,0) -> 300 | G97: =IFERROR('Cash Flow Data'!I26,0) -> 0 | H97: =IFERROR('Cash Flow Data'!J26,0) -> 0 | I97: =IFERROR('Cash Flow Data'!K26,0) -> 0 | J97: =IFERROR('Cash Flow Data'!L26,0) -> 0 | K97: =IFERROR('Cash Flow Data'!M26,0) -> 0
B98: Redemption of debentures | C98: =IFERROR('Cash Flow Data'!E27,0) -> 0 | D98: =IFERROR('Cash Flow Data'!F27,0) -> -384 | E98: =IFERROR('Cash Flow Data'!G27,0) -> -170 | F98: =IFERROR('Cash Flow Data'!H27,0) -> -512 | G98: =IFERROR('Cash Flow Data'!I27,0) -> -34 | H98: =IFERROR('Cash Flow Data'!J27,0) -> 0 | I98: =IFERROR('Cash Flow Data'!K27,0) -> 0 | J98: =IFERROR('Cash Flow Data'!L27,0) -> 0 | K98: =IFERROR('Cash Flow Data'!M27,0) -> 0
B99: Proceeds from borrowings | C99: =IFERROR('Cash Flow Data'!E28,0) -> 260 | D99: =IFERROR('Cash Flow Data'!F28,0) -> 0 | E99: =IFERROR('Cash Flow Data'!G28,0) -> 992 | F99: =IFERROR('Cash Flow Data'!H28,0) -> 1100 | G99: =IFERROR('Cash Flow Data'!I28,0) -> 200 | H99: =IFERROR('Cash Flow Data'!J28,0) -> 248 | I99: =IFERROR('Cash Flow Data'!K28,0) -> 0 | J99: =IFERROR('Cash Flow Data'!L28,0) -> 0 | K99: =IFERROR('Cash Flow Data'!M28,0) -> 0
B100: Repayment of borrowings | C100: =IFERROR('Cash Flow Data'!E29,0) -> -155 | D100: =IFERROR('Cash Flow Data'!F29,0) -> -695 | E100: =IFERROR('Cash Flow Data'!G29,0) -> -562 | F100: =IFERROR('Cash Flow Data'!H29,0) -> -1550 | G100: =IFERROR('Cash Flow Data'!I29,0) -> -204 | H100: =IFERROR('Cash Flow Data'!J29,0) -> -248 | I100: =IFERROR('Cash Flow Data'!K29,0) -> 0 | J100: =IFERROR('Cash Flow Data'!L29,0) -> 0 | K100: =IFERROR('Cash Flow Data'!M29,0) -> 0
B101: Interest paid fin | C101: =IFERROR('Cash Flow Data'!E30,0) -> -120 | D101: =IFERROR('Cash Flow Data'!F30,0) -> -80 | E101: =IFERROR('Cash Flow Data'!G30,0) -> -51 | F101: =IFERROR('Cash Flow Data'!H30,0) -> -68 | G101: =IFERROR('Cash Flow Data'!I30,0) -> -44 | H101: =IFERROR('Cash Flow Data'!J30,0) -> -54 | I101: =IFERROR('Cash Flow Data'!K30,0) -> -67 | J101: =IFERROR('Cash Flow Data'!L30,0) -> -58 | K101: =IFERROR('Cash Flow Data'!M30,0) -> -69
B102: Dividends paid | C102: =IFERROR('Cash Flow Data'!E31,0) -> 0 | D102: =IFERROR('Cash Flow Data'!F31,0) -> 0 | E102: =IFERROR('Cash Flow Data'!G31,0) -> 0 | F102: =IFERROR('Cash Flow Data'!H31,0) -> -100 | G102: =IFERROR('Cash Flow Data'!I31,0) -> -98 | H102: =IFERROR('Cash Flow Data'!J31,0) -> -125 | I102: =IFERROR('Cash Flow Data'!K31,0) -> -153 | J102: =IFERROR('Cash Flow Data'!L31,0) -> -164 | K102: =IFERROR('Cash Flow Data'!M31,0) -> -190
B103: Financial liabilities | C103: =IFERROR('Cash Flow Data'!E32,0) -> 0 | D103: =IFERROR('Cash Flow Data'!F32,0) -> 0 | E103: =IFERROR('Cash Flow Data'!G32,0) -> 0 | F103: =IFERROR('Cash Flow Data'!H32,0) -> 0 | G103: =IFERROR('Cash Flow Data'!I32,0) -> 0 | H103: =IFERROR('Cash Flow Data'!J32,0) -> 0 | I103: =IFERROR('Cash Flow Data'!K32,0) -> 1 | J103: =IFERROR('Cash Flow Data'!L32,0) -> 0 | K103: =IFERROR('Cash Flow Data'!M32,0) -> 0
B104: Other financing items | C104: =IFERROR('Cash Flow Data'!E33,0) -> -50 | D104: =IFERROR('Cash Flow Data'!F33,0) -> 0 | E104: =IFERROR('Cash Flow Data'!G33,0) -> 0 | F104: =IFERROR('Cash Flow Data'!H33,0) -> 4077 | G104: =IFERROR('Cash Flow Data'!I33,0) -> 0 | H104: =IFERROR('Cash Flow Data'!J33,0) -> 0 | I104: =IFERROR('Cash Flow Data'!K33,0) -> 0 | J104: =IFERROR('Cash Flow Data'!L33,0) -> 0 | K104: =IFERROR('Cash Flow Data'!M33,0) -> 0
B105: Cash From Investing Activities | C105: =IFERROR(SUM(C96:C104),0) -> 2026 | D105: =IFERROR(SUM(D96:D104),0) -> -1159 | E105: =IFERROR(SUM(E96:E104),0) -> 209 | F105: =IFERROR(SUM(F96:F104),0) -> 3357 | G105: =IFERROR(SUM(G96:G104),0) -> -180 | H105: =IFERROR(SUM(H96:H104),0) -> -179 | I105: =IFERROR(SUM(I96:I104),0) -> -204 | J105: =IFERROR(SUM(J96:J104),0) -> -147 | K105: =IFERROR(SUM(K96:K104),0) -> -259
B107: Net Cash Flow | C107: =SUM(C105,C93,C80) -> 0 | D107: =SUM(D105,D93,D80) -> 34 | E107: =SUM(E105,E93,E80) -> 55 | F107: =SUM(F105,F93,F80) -> -18 | G107: =SUM(G105,G93,G80) -> 86 | H107: =SUM(H105,H93,H80) -> -94 | I107: =SUM(I105,I93,I80) -> 113 | J107: =SUM(J105,J93,J80) -> 130 | K107: =SUM(K105,K93,K80) -> 20
B109: Notes : 1. March 2026 audited report is yet to be released as of the day of preparation of this model. All calculations are done by taking March 2025 as the latest financial year

Sheet Common Size Statement
B2: ="Common Size Statement - "&'Data Sheet'!B1 -> Common Size Statement - HINDUSTAN UNILEVER LTD
B3: Years | C3: ='Data Sheet'!B16 -> 42825 | D3: ='Data Sheet'!C16 -> 43190 | E3: ='Data Sheet'!D16 -> 43555 | F3: ='Data Sheet'!E16 -> 43921 | G3: ='Data Sheet'!F16 -> 44286 | H3: ='Data Sheet'!G16 -> 44651 | I3: ='Data Sheet'!H16 -> 45016 | J3: ='Data Sheet'!I16 -> 45382 | K3: ='Data Sheet'!J16 -> 45747 | L3: ='Data Sheet'!#REF! -> #REF! | M3: LTM
A5: # | B5: Income Statement
B6: Sales | C6: =IFERROR(HistoricalFS!C6/HistoricalFS!C6,0) -> 1 | D6: =IFERROR(HistoricalFS!D6/HistoricalFS!D6,0) -> 1 | E6: =IFERROR(HistoricalFS!E6/HistoricalFS!E6,0) -> 1 | F6: =IFERROR(HistoricalFS!F6/HistoricalFS!F6,0) -> 1 | G6: =IFERROR(HistoricalFS!G6/HistoricalFS!G6,0) -> 1 | H6: =IFERROR(HistoricalFS!H6/HistoricalFS!H6,0) -> 1 | I6: =IFERROR(HistoricalFS!I6/HistoricalFS!I6,0) -> 1 | J6: =IFERROR(HistoricalFS!J6/HistoricalFS!J6,0) -> 1 | K6: =IFERROR(HistoricalFS!K6/HistoricalFS!K6,0) -> 1 | L6: =IFERROR(HistoricalFS!#REF!/HistoricalFS!#REF!,0) -> 0 | M6: =IFERROR(HistoricalFS!#REF!/HistoricalFS!#REF!,0) -> 0
B7: COGS | C7: =IFERROR(HistoricalFS!C10,0) -> 0.56314456 | D7: =IFERROR(HistoricalFS!D10,0) -> 0.54336756 | E7: =IFERROR(HistoricalFS!E10,0) -> 0.53627576 | F7: =IFERROR(HistoricalFS!F10,0) -> 0.51816102 | G7: =IFERROR(HistoricalFS!G10,0) -> 0.53799864 | H7: =IFERROR(HistoricalFS!H10,0) -> 0.55420814 | I7: =IFERROR(HistoricalFS!I10,0) -> 0.58403764 | J7: =IFERROR(HistoricalFS!J10,0) -> 0.54367003 | K7: =IFERROR(HistoricalFS!K10,0) -> 0.54702872 | L7: =IFERROR(HistoricalFS!#REF!,0) -> 0 | M7: =IFERROR(HistoricalFS!#REF!,0) -> 0
B8: Gross Profit | C8: =IFERROR(HistoricalFS!C12/HistoricalFS!C6,0) -> 0.43685544 | D8: =IFERROR(HistoricalFS!D12/HistoricalFS!D6,0) -> 0.45663244 | E8: =IFERROR(HistoricalFS!E12/HistoricalFS!E6,0) -> 0.46372424 | F8: =IFERROR(HistoricalFS!F12/HistoricalFS!F6,0) -> 0.48183898 | G8: =IFERROR(HistoricalFS!G12/HistoricalFS!G6,0) -> 0.46200136 | H8: =IFERROR(HistoricalFS!H12/HistoricalFS!H6,0) -> 0.44579186 | I8: =IFERROR(HistoricalFS!I12/HistoricalFS!I6,0) -> 0.41596236 | J8: =IFERROR(HistoricalFS!J12/HistoricalFS!J6,0) -> 0.45632997 | K8: =IFERROR(HistoricalFS!K12/HistoricalFS!K6,0) -> 0.45297128 | L8: =IFERROR(HistoricalFS!#REF!/HistoricalFS!#REF!,0) -> 0 | M8: =IFERROR(HistoricalFS!#REF!/HistoricalFS!#REF!,0) -> 0
B9: Selling &General Expense | C9: =IFERROR(HistoricalFS!C16,0) -> 0.43689424 | D9: =IFERROR(HistoricalFS!D16,0) -> 0.45210728 | E9: =IFERROR(HistoricalFS!E16,0) -> 0.44347991 | F9: =IFERROR(HistoricalFS!F16,0) -> 0.45153779 | G9: =IFERROR(HistoricalFS!G16,0) -> 0.39923323 | H9: =IFERROR(HistoricalFS!H16,0) -> 0.36203812 | I9: =IFERROR(HistoricalFS!I16,0) -> 0.31237105 | J9: =IFERROR(HistoricalFS!J16,0) -> 0.40373243 | K9: =IFERROR(HistoricalFS!K16,0) -> 0.39818703 | L9: =IFERROR(HistoricalFS!#REF!,0) -> 0 | M9: =IFERROR(HistoricalFS!#REF!,0) -> 0
B10: EBITDA | C10: =IFERROR(HistoricalFS!C19,0) -> 0.19082082 | D10: =IFERROR(HistoricalFS!D19,0) -> 0.21097201 | E10: =IFERROR(HistoricalFS!E19,0) -> 0.22589672 | F10: =IFERROR(HistoricalFS!F19,0) -> 0.24786969 | G10: =IFERROR(HistoricalFS!G19,0) -> 0.24721443 | H10: =IFERROR(HistoricalFS!H19,0) -> 0.24514739 | I10: =IFERROR(HistoricalFS!I19,0) -> 0.23352592 | J10: =IFERROR(HistoricalFS!J19,0) -> 0.23683275 | K10: =IFERROR(HistoricalFS!K19,0) -> 0.23515153 | L10: =IFERROR(HistoricalFS!#REF!,0) -> 0 | M10: =IFERROR(HistoricalFS!#REF!,0) -> 0
B11: Depreciation & Amortisation | C11: =IFERROR(HistoricalFS!C22,0) -> 0.013026959 | D11: =IFERROR(HistoricalFS!D22,0) -> 0.014629343 | E11: =IFERROR(HistoricalFS!E22,0) -> 0.014372933 | F11: =IFERROR(HistoricalFS!F22,0) -> 0.025186638 | G11: =IFERROR(HistoricalFS!G22,0) -> 0.022837459 | H11: =IFERROR(HistoricalFS!H22,0) -> 0.020802349 | I11: =IFERROR(HistoricalFS!I22,0) -> 0.01876857 | J11: =IFERROR(HistoricalFS!J22,0) -> 0.019645858 | K11: =IFERROR(HistoricalFS!K22,0) -> 0.021466707 | L11: =IFERROR(HistoricalFS!#REF!,0) -> 0 | M11: =IFERROR(HistoricalFS!#REF!,0) -> 0
B12: EBIT | C12: =IFERROR((HistoricalFS!C30+HistoricalFS!C27)/HistoricalFS!C6,0) -> 0.17779386 | D12: =IFERROR((HistoricalFS!D30+HistoricalFS!D27)/HistoricalFS!D6,0) -> 0.19634266 | E12: =IFERROR((HistoricalFS!E30+HistoricalFS!E27)/HistoricalFS!E6,0) -> 0.21152379 | F12: =IFERROR((HistoricalFS!F30+HistoricalFS!F27)/HistoricalFS!F6,0) -> 0.22268306 | G12: =IFERROR((HistoricalFS!G30+HistoricalFS!G27)/HistoricalFS!G6,0) -> 0.22437697 | H12: =IFERROR((HistoricalFS!H30+HistoricalFS!H27)/HistoricalFS!H6,0) -> 0.22434504 | I12: =IFERROR((HistoricalFS!I30+HistoricalFS!I27)/HistoricalFS!I6,0) -> 0.21475735 | J12: =IFERROR((HistoricalFS!J30+HistoricalFS!J27)/HistoricalFS!J6,0) -> 0.21718689 | K12: =IFERROR((HistoricalFS!K30+HistoricalFS!K27)/HistoricalFS!K6,0) -> 0.21368483 | L12: =IFERROR((HistoricalFS!#REF!+HistoricalFS!#REF!)/HistoricalFS!#REF!,0) -> 0 | M12: =IFERROR((HistoricalFS!#REF!+HistoricalFS!#REF!)/HistoricalFS!#REF!,0) -> 0
B13: Interest | C13: =IFERROR(HistoricalFS!C28,0) -> 0.0010554249 | D13: =IFERROR(HistoricalFS!D28,0) -> 0.00073146715 | E13: =IFERROR(HistoricalFS!E28,0) -> 0.00083948105 | F13: =IFERROR(HistoricalFS!F28,0) -> 0.002966091 | G13: =IFERROR(HistoricalFS!G28,0) -> 0.0024878796 | H13: =IFERROR(HistoricalFS!H28,0) -> 0.0020211265 | I13: =IFERROR(HistoricalFS!I28,0) -> 0.0018818092 | J13: =IFERROR(HistoricalFS!J28,0) -> 0.0053961484 | K13: =IFERROR(HistoricalFS!K28,0) -> 0.0062578223 | L13: =IFERROR(HistoricalFS!#REF!,0) -> 0 | M13: =IFERROR(HistoricalFS!#REF!,0) -> 0
B14: EBT | C14: =IFERROR(HistoricalFS!C31,0) -> 0.17673844 | D14: =IFERROR(HistoricalFS!D31,0) -> 0.1956112 | E14: =IFERROR(HistoricalFS!E31,0) -> 0.2106843 | F14: =IFERROR(HistoricalFS!F31,0) -> 0.21971696 | G14: =IFERROR(HistoricalFS!G31,0) -> 0.22188909 | H14: =IFERROR(HistoricalFS!H31,0) -> 0.22232391 | I14: =IFERROR(HistoricalFS!I31,0) -> 0.21287554 | J14: =IFERROR(HistoricalFS!J31,0) -> 0.21179075 | K14: =IFERROR(HistoricalFS!K31,0) -> 0.20742701 | L14: =IFERROR(HistoricalFS!#REF!,0) -> 0 | M14: =IFERROR(HistoricalFS!#REF!,0) -> 0
B15: Tax | C15: =IFERROR(HistoricalFS!C33/HistoricalFS!C9,0) -> 0.10586345 | D15: =IFERROR(HistoricalFS!D33/HistoricalFS!D9,0) -> 0.10764212 | E15: =IFERROR(HistoricalFS!E33/HistoricalFS!E9,0) -> 0.12067739 | F15: =IFERROR(HistoricalFS!F33/HistoricalFS!F9,0) -> 0.11686233 | G15: =IFERROR(HistoricalFS!G33/HistoricalFS!G9,0) -> 0.10299988 | H15: =IFERROR(HistoricalFS!H33/HistoricalFS!H9,0) -> 0.10276612 | I15: =IFERROR(HistoricalFS!I33/HistoricalFS!I9,0) -> 0.090472287 | J15: =IFERROR(HistoricalFS!J33/HistoricalFS!J9,0) -> 0.10828802 | K15: =IFERROR(HistoricalFS!K33/HistoricalFS!K9,0) -> 0.10843059 | L15: =IFERROR(HistoricalFS!#REF!/HistoricalFS!#REF!,0) -> 0 | M15: =IFERROR(HistoricalFS!#REF!/HistoricalFS!#REF!,0) -> 0
B16: Net Profit | C16: =IFERROR(HistoricalFS!C36/HistoricalFS!C6,0) -> 0.11712201 | D16: =IFERROR(HistoricalFS!D36/HistoricalFS!D6,0) -> 0.13712196 | E16: =IFERROR(HistoricalFS!E36/HistoricalFS!E6,0) -> 0.14596795 | F16: =IFERROR(HistoricalFS!F36/HistoricalFS!F6,0) -> 0.15916346 | G16: =IFERROR(HistoricalFS!G36/HistoricalFS!G6,0) -> 0.16647529 | H16: =IFERROR(HistoricalFS!H36/HistoricalFS!H6,0) -> 0.16537009 | I16: =IFERROR(HistoricalFS!I36/HistoricalFS!I6,0) -> 0.16003632 | J16: =IFERROR(HistoricalFS!J36/HistoricalFS!J6,0) -> 0.1529178 | K16: =IFERROR(HistoricalFS!K36/HistoricalFS!K6,0) -> 0.14811236 | L16: =IFERROR(HistoricalFS!#REF!/HistoricalFS!#REF!,0) -> 0 | M16: =IFERROR(HistoricalFS!#REF!/HistoricalFS!#REF!,0) -> 0
A19: # | B19: Balance Sheet
B20: Equity Share Capital | C20: =IFERROR(HistoricalFS!C50/HistoricalFS!C$54,0) -> 0.013752706 | D20: =IFERROR(HistoricalFS!D50/HistoricalFS!D$54,0) -> 0.012092711 | E20: =IFERROR(HistoricalFS!E50/HistoricalFS!E$54,0) -> 0.011594825 | F20: =IFERROR(HistoricalFS!F50/HistoricalFS!F$54,0) -> 0.010718007 | G20: =IFERROR(HistoricalFS!G50/HistoricalFS!G$54,0) -> 0.0034186791 | H20: =IFERROR(HistoricalFS!H50/HistoricalFS!H$54,0) -> 0.0033330497 | I20: =IFERROR(HistoricalFS!I50/HistoricalFS!I$54,0) -> 0.0032157861 | J20: =IFERROR(HistoricalFS!J50/HistoricalFS!J$54,0) -> 0.0029940501 | K20: =IFERROR(HistoricalFS!K50/HistoricalFS!K$54,0) -> 0.0029425391 | L20: =IFERROR(HistoricalFS!#REF!/HistoricalFS!#REF!,0) -> 0
B21: Reserves | C21: =IFERROR(HistoricalFS!C51/HistoricalFS!C$54,0) -> 0.41563734 | D21: =IFERROR(HistoricalFS!D51/HistoricalFS!D$54,0) -> 0.39553242 | E21: =IFERROR(HistoricalFS!E51/HistoricalFS!E$54,0) -> 0.41070374 | F21: =IFERROR(HistoricalFS!F51/HistoricalFS!F$54,0) -> 0.3976083 | G21: =IFERROR(HistoricalFS!G51/HistoricalFS!G$54,0) -> 0.6901222 | H21: =IFERROR(HistoricalFS!H51/HistoricalFS!H$54,0) -> 0.69250844 | I21: =IFERROR(HistoricalFS!I51/HistoricalFS!I$54,0) -> 0.68515402 | J21: =IFERROR(HistoricalFS!J51/HistoricalFS!J$54,0) -> 0.64955599 | K21: =IFERROR(HistoricalFS!K51/HistoricalFS!K$54,0) -> 0.61564179 | L21: =IFERROR(HistoricalFS!#REF!/HistoricalFS!#REF!,0) -> 0
B22: Borrowings | C22: =IFERROR(HistoricalFS!C52/HistoricalFS!C$54,0) -> 0.017636572 | D22: =IFERROR(HistoricalFS!D52/HistoricalFS!D$54,0) -> 0 | E22: =IFERROR(HistoricalFS!E52/HistoricalFS!E$54,0) -> 0.0053142949 | F22: =IFERROR(HistoricalFS!F52/HistoricalFS!F$54,0) -> 0 | G22: =IFERROR(HistoricalFS!G52/HistoricalFS!G$54,0) -> 0 | H22: =IFERROR(HistoricalFS!H52/HistoricalFS!H$54,0) -> 0.014793067 | I22: =IFERROR(HistoricalFS!I52/HistoricalFS!I$54,0) -> 0.016681035 | J22: =IFERROR(HistoricalFS!J52/HistoricalFS!J$54,0) -> 0.018907108 | K22: =IFERROR(HistoricalFS!K52/HistoricalFS!K$54,0) -> 0.020635338 | L22: =IFERROR(HistoricalFS!#REF!/HistoricalFS!#REF!,0) -> 0
B23: Other Liabilities | C23: =IFERROR(HistoricalFS!C53/HistoricalFS!C$54,0) -> 0.55297339 | D23: =IFERROR(HistoricalFS!D53/HistoricalFS!D$54,0) -> 0.59237487 | E23: =IFERROR(HistoricalFS!E53/HistoricalFS!E$54,0) -> 0.57238714 | F23: =IFERROR(HistoricalFS!F53/HistoricalFS!F$54,0) -> 0.5916737 | G23: =IFERROR(HistoricalFS!G53/HistoricalFS!G$54,0) -> 0.30645912 | H23: =IFERROR(HistoricalFS!H53/HistoricalFS!H$54,0) -> 0.28936544 | I23: =IFERROR(HistoricalFS!I53/HistoricalFS!I$54,0) -> 0.29494916 | J23: =IFERROR(HistoricalFS!J53/HistoricalFS!J$54,0) -> 0.32854285 | K23: =IFERROR(HistoricalFS!K53/HistoricalFS!K$54,0) -> 0.36078034 | L23: =IFERROR(HistoricalFS!#REF!/HistoricalFS!#REF!,0) -> 0
B24: Total Liabilities | C24: =IFERROR(HistoricalFS!C54/HistoricalFS!C$54,0) -> 1 | D24: =IFERROR(HistoricalFS!D54/HistoricalFS!D$54,0) -> 1 | E24: =IFERROR(HistoricalFS!E54/HistoricalFS!E$54,0) -> 1 | F24: =IFERROR(HistoricalFS!F54/HistoricalFS!F$54,0) -> 1 | G24: =IFERROR(HistoricalFS!G54/HistoricalFS!G$54,0) -> 1 | H24: =IFERROR(HistoricalFS!H54/HistoricalFS!H$54,0) -> 1 | I24: =IFERROR(HistoricalFS!I54/HistoricalFS!I$54,0) -> 1 | J24: =IFERROR(HistoricalFS!J54/HistoricalFS!J$54,0) -> 1 | K24: =IFERROR(HistoricalFS!K54/HistoricalFS!K$54,0) -> 1 | L24: =IFERROR(HistoricalFS!#REF!/HistoricalFS!#REF!,0) -> 0
B26: Fixed Assets Net Block | C26: =IFERROR(HistoricalFS!C56/HistoricalFS!C$67,0) -> 0.28135744 | D26: =IFERROR(HistoricalFS!D56/HistoricalFS!D$67,0) -> 0.25349905 | E26: =IFERROR(HistoricalFS!E56/HistoricalFS!E$67,0) -> 0.25310001 | F26: =IFERROR(HistoricalFS!F56/HistoricalFS!F$67,0) -> 0.27187019 | G26: =IFERROR(HistoricalFS!G56/HistoricalFS!G$67,0) -> 0.74837067 | H26: =IFERROR(HistoricalFS!H56/HistoricalFS!H$67,0) -> 0.73005134 | I26: =IFERROR(HistoricalFS!I56/HistoricalFS!I$67,0) -> 0.72085608 | J26: =IFERROR(HistoricalFS!J56/HistoricalFS!J$67,0) -> 0.68473289 | K26: =IFERROR(HistoricalFS!K56/HistoricalFS!K$67,0) -> 0.6803526 | L26: =IFERROR(HistoricalFS!#REF!/HistoricalFS!#REF!,0) -> 0
B27: Capital Work in Progress | C27: =IFERROR(HistoricalFS!C57/HistoricalFS!C$67,0) -> 0.014580415 | D27: =IFERROR(HistoricalFS!D57/HistoricalFS!D$67,0) -> 0.02580898 | E27: =IFERROR(HistoricalFS!E57/HistoricalFS!E$67,0) -> 0.021793977 | F27: =IFERROR(HistoricalFS!F57/HistoricalFS!F$67,0) -> 0.029623381 | G27: =IFERROR(HistoricalFS!G57/HistoricalFS!G$67,0) -> 0.01083794 | H27: =IFERROR(HistoricalFS!H57/HistoricalFS!H$67,0) -> 0.018622529 | I27: =IFERROR(HistoricalFS!I57/HistoricalFS!I$67,0) -> 0.01549051 | J27: =IFERROR(HistoricalFS!J57/HistoricalFS!J$67,0) -> 0.013059155 | K27: =IFERROR(HistoricalFS!K57/HistoricalFS!K$67,0) -> 0.012634136 | L27: =IFERROR(HistoricalFS!#REF!/HistoricalFS!#REF!,0) -> 0
B28: Investments | C28: =IFERROR(HistoricalFS!C58/HistoricalFS!C$67,0) -> 0.24156373 | D28: =IFERROR(HistoricalFS!D58/HistoricalFS!D$67,0) -> 0.16084425 | E28: =IFERROR(HistoricalFS!E58/HistoricalFS!E$67,0) -> 0.14579419 | F28: =IFERROR(HistoricalFS!F58/HistoricalFS!F$67,0) -> 0.062273607 | G28: =IFERROR(HistoricalFS!G58/HistoricalFS!G$67,0) -> 0.039409369 | H28: =IFERROR(HistoricalFS!H58/HistoricalFS!H$67,0) -> 0.049939012 | I28: =IFERROR(HistoricalFS!I58/HistoricalFS!I$67,0) -> 0.039437853 | J28: =IFERROR(HistoricalFS!J58/HistoricalFS!J$67,0) -> 0.058925455 | K28: =IFERROR(HistoricalFS!K58/HistoricalFS!K$67,0) -> 0.047706698 | L28: =IFERROR(HistoricalFS!#REF!/HistoricalFS!#REF!,0) -> 0
B29: Other Assets | C29: =IFERROR(HistoricalFS!C59/HistoricalFS!C$67,0) -> 0.11524258 | D29: =IFERROR(HistoricalFS!D59/HistoricalFS!D$67,0) -> 0.15071101 | E29: =IFERROR(HistoricalFS!E59/HistoricalFS!E$67,0) -> 0.14198293 | F29: =IFERROR(HistoricalFS!F59/HistoricalFS!F$67,0) -> 0.18821019 | G29: =IFERROR(HistoricalFS!G59/HistoricalFS!G$67,0) -> 0.058699447 | H29: =IFERROR(HistoricalFS!H59/HistoricalFS!H$67,0) -> 0.057030607 | I29: =IFERROR(HistoricalFS!I59/HistoricalFS!I$67,0) -> 0.059895726 | J29: =IFERROR(HistoricalFS!J59/HistoricalFS!J$67,0) -> 0.057549466 | K29: =IFERROR(HistoricalFS!K59/HistoricalFS!K$67,0) -> 0.061618021 | L29: =IFERROR(HistoricalFS!#REF!/HistoricalFS!#REF!,0) -> 0
B30: Total Non-Current Assets | C30: =IFERROR(HistoricalFS!C60/HistoricalFS!C$67,0) -> 0.65274417 | D30: =IFERROR(HistoricalFS!D60/HistoricalFS!D$67,0) -> 0.59086329 | E30: =IFERROR(HistoricalFS!E60/HistoricalFS!E$67,0) -> 0.5626711 | F30: =IFERROR(HistoricalFS!F60/HistoricalFS!F$67,0) -> 0.55197737 | G30: =IFERROR(HistoricalFS!G60/HistoricalFS!G$67,0) -> 0.85731743 | H30: =IFERROR(HistoricalFS!H60/HistoricalFS!H$67,0) -> 0.85564349 | I30: =IFERROR(HistoricalFS!I60/HistoricalFS!I$67,0) -> 0.83568017 | J30: =IFERROR(HistoricalFS!J60/HistoricalFS!J$67,0) -> 0.81426697 | K30: =IFERROR(HistoricalFS!K60/HistoricalFS!K$67,0) -> 0.80231146 | L30: =IFERROR(HistoricalFS!#REF!/HistoricalFS!#REF!,0) -> 0
B32: Receivables | C32: =IFERROR(HistoricalFS!C62/HistoricalFS!C$67,0) -> 0.06908188 | D32: =IFERROR(HistoricalFS!D62/HistoricalFS!D$67,0) -> 0.073340052 | E32: =IFERROR(HistoricalFS!E62/HistoricalFS!E$67,0) -> 0.09748242 | F32: =IFERROR(HistoricalFS!F62/HistoricalFS!F$67,0) -> 0.057013844 | G32: =IFERROR(HistoricalFS!G62/HistoricalFS!G$67,0) -> 0.025574629 | H32: =IFERROR(HistoricalFS!H62/HistoricalFS!H$67,0) -> 0.031713613 | I32: =IFERROR(HistoricalFS!I62/HistoricalFS!I$67,0) -> 0.04213364 | J32: =IFERROR(HistoricalFS!J62/HistoricalFS!J$67,0) -> 0.038183695 | K32: =IFERROR(HistoricalFS!K62/HistoricalFS!K$67,0) -> 0.047819391 | L32: =IFERROR(HistoricalFS!#REF!/HistoricalFS!#REF!,0) -> 0
B33: Inventory | C33: =IFERROR(HistoricalFS!C63/HistoricalFS!C$67,0) -> 0.1617853 | D33: =IFERROR(HistoricalFS!D63/HistoricalFS!D$67,0) -> 0.14068973 | E33: =IFERROR(HistoricalFS!E63/HistoricalFS!E$67,0) -> 0.13817167 | F33: =IFERROR(HistoricalFS!F63/HistoricalFS!F$67,0) -> 0.13729966 | G33: =IFERROR(HistoricalFS!G63/HistoricalFS!G$67,0) -> 0.052065755 | H33: =IFERROR(HistoricalFS!H63/HistoricalFS!H$67,0) -> 0.058094347 | I33: =IFERROR(HistoricalFS!I63/HistoricalFS!I$67,0) -> 0.058171518 | J33: =IFERROR(HistoricalFS!J63/HistoricalFS!J$67,0) -> 0.051242849 | K33: =IFERROR(HistoricalFS!K63/HistoricalFS!K$67,0) -> 0.055282171 | L33: =IFERROR(HistoricalFS!#REF!/HistoricalFS!#REF!,0) -> 0
B34: Cash & Bank | C34: =IFERROR(HistoricalFS!C64/HistoricalFS!C$67,0) -> 0.11638864 | D34: =IFERROR(HistoricalFS!D64/HistoricalFS!D$67,0) -> 0.19510693 | E34: =IFERROR(HistoricalFS!E64/HistoricalFS!E$67,0) -> 0.20167481 | F34: =IFERROR(HistoricalFS!F64/HistoricalFS!F$67,0) -> 0.25370913 | G34: =IFERROR(HistoricalFS!G64/HistoricalFS!G$67,0) -> 0.065042188 | H34: =IFERROR(HistoricalFS!H64/HistoricalFS!H$67,0) -> 0.054548549 | I34: =IFERROR(HistoricalFS!I64/HistoricalFS!I$67,0) -> 0.064014669 | J34: =IFERROR(HistoricalFS!J64/HistoricalFS!J$67,0) -> 0.096306489 | K34: =IFERROR(HistoricalFS!K64/HistoricalFS!K$67,0) -> 0.09458698 | L34: =IFERROR(HistoricalFS!#REF!/HistoricalFS!#REF!,0) -> 0
B35: Total Current Assets | C35: =IFERROR(HistoricalFS!C65/HistoricalFS!C$67,0) -> 0.34725583 | D35: =IFERROR(HistoricalFS!D65/HistoricalFS!D$67,0) -> 0.40913671 | E35: =IFERROR(HistoricalFS!E65/HistoricalFS!E$67,0) -> 0.4373289 | F35: =IFERROR(HistoricalFS!F65/HistoricalFS!F$67,0) -> 0.44802263 | G35: =IFERROR(HistoricalFS!G65/HistoricalFS!G$67,0) -> 0.14268257 | H35: =IFERROR(HistoricalFS!H65/HistoricalFS!H$67,0) -> 0.14435651 | I35: =IFERROR(HistoricalFS!I65/HistoricalFS!I$67,0) -> 0.16431983 | J35: =IFERROR(HistoricalFS!J65/HistoricalFS!J$67,0) -> 0.18573303 | K35: =IFERROR(HistoricalFS!K65/HistoricalFS!K$67,0) -> 0.19768854 | L35: =IFERROR(HistoricalFS!#REF!/HistoricalFS!#REF!,0) -> 0
B37: Total Assets | C37: =IFERROR(HistoricalFS!C67/HistoricalFS!C$67,0) -> 1 | D37: =IFERROR(HistoricalFS!D67/HistoricalFS!D$67,0) -> 1 | E37: =IFERROR(HistoricalFS!E67/HistoricalFS!E$67,0) -> 1 | F37: =IFERROR(HistoricalFS!F67/HistoricalFS!F$67,0) -> 1 | G37: =IFERROR(HistoricalFS!G67/HistoricalFS!G$67,0) -> 1 | H37: =IFERROR(HistoricalFS!H67/HistoricalFS!H$67,0) -> 1 | I37: =IFERROR(HistoricalFS!I67/HistoricalFS!I$67,0) -> 1 | J37: =IFERROR(HistoricalFS!J67/HistoricalFS!J$67,0) -> 1 | K37: =IFERROR(HistoricalFS!K67/HistoricalFS!K$67,0) -> 1 | L37: =IFERROR(HistoricalFS!#REF!/HistoricalFS!#REF!,0) -> 0

Sheet Ratio Analysis
B2: ="Ratio Analysis - "&'Data Sheet'!B1 -> Ratio Analysis - HINDUSTAN UNILEVER LTD
B3: Years | C3: ='Data Sheet'!B16 -> 42825 | D3: ='Data Sheet'!C16 -> 43190 | E3: ='Data Sheet'!D16 -> 43555 | F3: ='Data Sheet'!E16 -> 43921 | G3: ='Data Sheet'!F16 -> 44286 | H3: ='Data Sheet'!G16 -> 44651 | I3: ='Data Sheet'!H16 -> 45016 | J3: ='Data Sheet'!I16 -> 45382 | K3: ='Data Sheet'!J16 -> 45747 | L3: ='Data Sheet'!#REF! -> #REF! | M3: Trends | N3: Mean | O3: Median
B5: SalesGrowth | C5: =IFERROR(HistoricalFS!C7,0) -> - | D5: =IFERROR(HistoricalFS!D7,0) -> 0.071859357 | E5: =IFERROR(HistoricalFS!E7,0) -> 0.10592207 | F5: =IFERROR(HistoricalFS!F7,0) -> 0.012032562 | G5: =IFERROR(HistoricalFS!G7,0) -> 0.18211296 | H5: =IFERROR(HistoricalFS!H7,0) -> 0.11520796 | I5: =IFERROR(HistoricalFS!I7,0) -> 0.15509286 | J5: =IFERROR(HistoricalFS!J7,0) -> 0.021723341 | K5: =IFERROR(HistoricalFS!K7,0) -> 0.019791263 | L5: =IFERROR(HistoricalFS!#REF!,0) -> 0 | N5: =IFERROR(AVERAGE(D5:L5),0) -> 0.075971375 | O5: =IFERROR(MEDIAN(D5:L5),0) -> 0.071859357
B6: EBITDA Growth | C6: - | D6: =IFERROR(HistoricalFS!D18/HistoricalFS!C18-1,0) -> 0.18505057 | E6: =IFERROR(HistoricalFS!E18/HistoricalFS!D18-1,0) -> 0.18415789 | F6: =IFERROR(HistoricalFS!F18/HistoricalFS!E18-1,0) -> 0.11047297 | G6: =IFERROR(HistoricalFS!G18/HistoricalFS!F18-1,0) -> 0.17898793 | H6: =IFERROR(HistoricalFS!H18/HistoricalFS!G18-1,0) -> 0.10588336 | I6: =IFERROR(HistoricalFS!I18/HistoricalFS!H18-1,0) -> 0.10033445 | J6: =IFERROR(HistoricalFS!J18/HistoricalFS!I18-1,0) -> 0.036191419 | K6: =IFERROR(HistoricalFS!K18/HistoricalFS!J18-1,0) -> 0.012552016 | L6: =IFERROR(HistoricalFS!#REF!/HistoricalFS!K18-1,0) -> 0 | N6: =IFERROR(AVERAGE(D6:L6),0) -> 0.10151451 | O6: =IFERROR(MEDIAN(D6:L6),0) -> 0.10588336
B7: EBIT Growth | C7: - | D7: =IFERROR((HistoricalFS!D30+HistoricalFS!D27)/(HistoricalFS!C30+HistoricalFS!C27)-1,0) -> 0.18368385 | E7: =IFERROR((HistoricalFS!E30-HistoricalFS!E27)/(HistoricalFS!D30-HistoricalFS!D27)-1,0) -> 0.19084741 | F7: =IFERROR((HistoricalFS!F30-HistoricalFS!F27)/(HistoricalFS!E30-HistoricalFS!E27)-1,0) -> 0.045338829 | G7: =IFERROR((HistoricalFS!G30-HistoricalFS!G27)/(HistoricalFS!F30-HistoricalFS!F27)-1,0) -> 0.19656732 | H7: =IFERROR((HistoricalFS!H30-HistoricalFS!H27)/(HistoricalFS!G30-HistoricalFS!G27)-1,0) -> 0.11979066 | I7: =IFERROR((HistoricalFS!I30-HistoricalFS!I27)/(HistoricalFS!H30-HistoricalFS!H27)-1,0) -> 0.10628354 | J7: =IFERROR((HistoricalFS!J30-HistoricalFS!J27)/(HistoricalFS!I30-HistoricalFS!I27)-1,0) -> -0.00054764513 | K7: =IFERROR((HistoricalFS!K30-HistoricalFS!K27)/(HistoricalFS!J30-HistoricalFS!J27)-1,0) -> -0.0060273973 | L7: =IFERROR((HistoricalFS!#REF!-HistoricalFS!#REF!)/(HistoricalFS!K30-HistoricalFS!K27)-1,0) -> 0 | N7: =IFERROR(AVERAGE(D7:L7),0) -> 0.09288184 | O7: =IFERROR(MEDIAN(D7:L7),0) -> 0.10628354
B8: NetProfitGrowth | C8: - | D8: =IFERROR(HistoricalFS!D36/HistoricalFS!C36-1,0) -> 0.25489186 | E8: =IFERROR(HistoricalFS!E36/HistoricalFS!D36-1,0) -> 0.17726713 | F8: =IFERROR(HistoricalFS!F36/HistoricalFS!E36-1,0) -> 0.10352039 | G8: =IFERROR(HistoricalFS!G36/HistoricalFS!F36-1,0) -> 0.23641819 | H8: =IFERROR(HistoricalFS!H36/HistoricalFS!G36-1,0) -> 0.10780432 | I8: =IFERROR(HistoricalFS!I36/HistoricalFS!H36-1,0) -> 0.11783697 | J8: =IFERROR(HistoricalFS!J36/HistoricalFS!I36-1,0) -> -0.023723569 | K8: =IFERROR(HistoricalFS!K36/HistoricalFS!J36-1,0) -> -0.012255679 | L8: =IFERROR(HistoricalFS!#REF!/HistoricalFS!K36-1,0) -> 0 | N8: =IFERROR(AVERAGE(D8:L8),0) -> 0.10686218 | O8: =IFERROR(MEDIAN(D8:L8),0) -> 0.10780432
B9: Dividend Growth | C9: - | D9: =IFERROR(HistoricalFS!D44/HistoricalFS!C44-1,0) -> 0.17636188 | E9: =IFERROR(HistoricalFS!E44/HistoricalFS!D44-1,0) -> 0.099898369 | F9: =IFERROR(HistoricalFS!F44/HistoricalFS!E44-1,0) -> 0.13631114 | G9: =IFERROR(HistoricalFS!G44/HistoricalFS!F44-1,0) -> 0.6238764 | H9: =IFERROR(HistoricalFS!H44/HistoricalFS!G44-1,0) -> -0.16049383 | I9: =IFERROR(HistoricalFS!I44/HistoricalFS!H44-1,0) -> 0.14705882 | J9: =IFERROR(HistoricalFS!J44/HistoricalFS!I44-1,0) -> 0.076923077 | K9: =IFERROR(HistoricalFS!K44/HistoricalFS!J44-1,0) -> 0.26190476 | L9: =IFERROR(HistoricalFS!#REF!/HistoricalFS!K44-1,0) -> 0 | N9: =IFERROR(AVERAGE(D9:L9),0) -> 0.15131563 | O9: =IFERROR(MEDIAN(D9:L9),0) -> 0.13631114
B11: Gross Margin | C11: =IFERROR(HistoricalFS!C13,0) -> 0.43685544 | D11: =IFERROR(HistoricalFS!D13,0) -> 0.45663244 | E11: =IFERROR(HistoricalFS!E13,0) -> 0.46372424 | F11: =IFERROR(HistoricalFS!F13,0) -> 0.48183898 | G11: =IFERROR(HistoricalFS!G13,0) -> 0.46200136 | H11: =IFERROR(HistoricalFS!H13,0) -> 0.44579186 | I11: =IFERROR(HistoricalFS!I13,0) -> 0.41596236 | J11: =IFERROR(HistoricalFS!J13,0) -> 0.45632997 | K11: =IFERROR(HistoricalFS!K13,0) -> 0.45297128 | L11: =IFERROR(HistoricalFS!#REF!,0) -> 0 | N11: =IFERROR(AVERAGE(C11:L11),0) -> 0.40721079 | O11: =IFERROR(MEDIAN(C11:L11),0) -> 0.45465063
B12: EBITDA Margin | C12: =IFERROR(HistoricalFS!C19,0) -> 0.19082082 | D12: =IFERROR(HistoricalFS!D19,0) -> 0.21097201 | E12: =IFERROR(HistoricalFS!E19,0) -> 0.22589672 | F12: =IFERROR(HistoricalFS!F19,0) -> 0.24786969 | G12: =IFERROR(HistoricalFS!G19,0) -> 0.24721443 | H12: =IFERROR(HistoricalFS!H19,0) -> 0.24514739 | I12: =IFERROR(HistoricalFS!I19,0) -> 0.23352592 | J12: =IFERROR(HistoricalFS!J19,0) -> 0.23683275 | K12: =IFERROR(HistoricalFS!K19,0) -> 0.23515153 | L12: =IFERROR(HistoricalFS!#REF!,0) -> 0 | N12: =IFERROR(AVERAGE(C12:L12),0) -> 0.20734313 | O12: =IFERROR(MEDIAN(C12:L12),0) -> 0.23433873
B13: EBIT Margin | C13: =IFERROR((HistoricalFS!C30+HistoricalFS!C27)/HistoricalFS!C6,0) -> 0.17779386 | D13: =IFERROR((HistoricalFS!D30+HistoricalFS!D27)/HistoricalFS!D6,0) -> 0.19634266 | E13: =IFERROR((HistoricalFS!E30+HistoricalFS!E27)/HistoricalFS!E6,0) -> 0.21152379 | F13: =IFERROR((HistoricalFS!F30+HistoricalFS!F27)/HistoricalFS!F6,0) -> 0.22268306 | G13: =IFERROR((HistoricalFS!G30+HistoricalFS!G27)/HistoricalFS!G6,0) -> 0.22437697 | H13: =IFERROR((HistoricalFS!H30+HistoricalFS!H27)/HistoricalFS!H6,0) -> 0.22434504 | I13: =IFERROR((HistoricalFS!I30+HistoricalFS!I27)/HistoricalFS!I6,0) -> 0.21475735 | J13: =IFERROR((HistoricalFS!J30+HistoricalFS!J27)/HistoricalFS!J6,0) -> 0.21718689 | K13: =IFERROR((HistoricalFS!K30+HistoricalFS!K27)/HistoricalFS!K6,0) -> 0.21368483 | L13: =IFERROR((HistoricalFS!#REF!+HistoricalFS!#REF!)/HistoricalFS!#REF!,0) -> 0 | N13: =IFERROR(AVERAGE(C13:L13),0) -> 0.19026944 | O13: =IFERROR(MEDIAN(C13:L13),0) -> 0.21422109
B14: EBT Margin | C14: =IFERROR(HistoricalFS!C31,0) -> 0.17673844 | D14: =IFERROR(HistoricalFS!D31,0) -> 0.1956112 | E14: =IFERROR(HistoricalFS!E31,0) -> 0.2106843 | F14: =IFERROR(HistoricalFS!F31,0) -> 0.21971696 | G14: =IFERROR(HistoricalFS!G31,0) -> 0.22188909 | H14: =IFERROR(HistoricalFS!H31,0) -> 0.22232391 | I14: =IFERROR(HistoricalFS!I31,0) -> 0.21287554 | J14: =IFERROR(HistoricalFS!J31,0) -> 0.21179075 | K14: =IFERROR(HistoricalFS!K31,0) -> 0.20742701 | L14: =IFERROR(HistoricalFS!#REF!,0) -> 0 | N14: =IFERROR(AVERAGE(C14:L14),0) -> 0.18790572 | O14: =IFERROR(MEDIAN(C14:L14),0) -> 0.21123753
B15: Net Profit Margin | C15: =IFERROR(HistoricalFS!C37,0) -> 0.11712201 | D15: =IFERROR(HistoricalFS!D37,0) -> 0.13712196 | E15: =IFERROR(HistoricalFS!E37,0) -> 0.14596795 | F15: =IFERROR(HistoricalFS!F37,0) -> 0.15916346 | G15: =IFERROR(HistoricalFS!G37,0) -> 0.16647529 | H15: =IFERROR(HistoricalFS!H37,0) -> 0.16537009 | I15: =IFERROR(HistoricalFS!I37,0) -> 0.16003632 | J15: =IFERROR(HistoricalFS!J37,0) -> 0.1529178 | K15: =IFERROR(HistoricalFS!K37,0) -> 0.14811236 | L15: =IFERROR(HistoricalFS!#REF!,0) -> 0 | N15: =IFERROR(AVERAGE(C15:L15),0) -> 0.13522872 | O15: =IFERROR(MEDIAN(C15:L15),0) -> 0.15051508
B17: SalesExpenses%Sales | C17: =IFERROR(HistoricalFS!C16,0) -> 0.43689424 | D17: =IFERROR(HistoricalFS!D16,0) -> 0.45210728 | E17: =IFERROR(HistoricalFS!E16,0) -> 0.44347991 | F17: =IFERROR(HistoricalFS!F16,0) -> 0.45153779 | G17: =IFERROR(HistoricalFS!G16,0) -> 0.39923323 | H17: =IFERROR(HistoricalFS!H16,0) -> 0.36203812 | I17: =IFERROR(HistoricalFS!I16,0) -> 0.31237105 | J17: =IFERROR(HistoricalFS!J16,0) -> 0.40373243 | K17: =IFERROR(HistoricalFS!K16,0) -> 0.39818703 | L17: =IFERROR(HistoricalFS!#REF!,0) -> 0 | N17: =IFERROR(AVERAGE(C17:L17),0) -> 0.36595811 | O17: =IFERROR(MEDIAN(C17:L17),0) -> 0.40148283
B18: Depreciation%Sales | C18: =IFERROR(HistoricalFS!C22,0) -> 0.013026959 | D18: =IFERROR(HistoricalFS!D22,0) -> 0.014629343 | E18: =IFERROR(HistoricalFS!E22,0) -> 0.014372933 | F18: =IFERROR(HistoricalFS!F22,0) -> 0.025186638 | G18: =IFERROR(HistoricalFS!G22,0) -> 0.022837459 | H18: =IFERROR(HistoricalFS!H22,0) -> 0.020802349 | I18: =IFERROR(HistoricalFS!I22,0) -> 0.01876857 | J18: =IFERROR(HistoricalFS!J22,0) -> 0.019645858 | K18: =IFERROR(HistoricalFS!K22,0) -> 0.021466707 | L18: =IFERROR(HistoricalFS!#REF!,0) -> 0 | N18: =IFERROR(AVERAGE(C18:L18),0) -> 0.017073681 | O18: =IFERROR(MEDIAN(C18:L18),0) -> 0.019207214
B19: OperatingIncome%Sales | C19: =C12 -> 0.19082082 | D19: =D12 -> 0.21097201 | E19: =E12 -> 0.22589672 | F19: =F12 -> 0.24786969 | G19: =G12 -> 0.24721443 | H19: =H12 -> 0.24514739 | I19: =I12 -> 0.23352592 | J19: =J12 -> 0.23683275 | ... L19: =L12 -> 0 | N19: =IFERROR(AVERAGE(C19:L19),0) -> 0.20734313 | O19: =IFERROR(MEDIAN(C19:L19),0) -> 0.23433873
B21: Return On Capital Employed | C21: =IFERROR((HistoricalFS!C30+HistoricalFS!C27)/(SUM(HistoricalFS!C50:C52)),0) -> 0.83976642 | D21: =IFERROR((HistoricalFS!D30+HistoricalFS!D27)/(SUM(HistoricalFS!D50:D52)),0) -> 0.95852218 | E21: =IFERROR((HistoricalFS!E30+HistoricalFS!E27)/(SUM(HistoricalFS!E50:E52)),0) -> 1.0438112 | F21: =IFERROR((HistoricalFS!F30+HistoricalFS!F27)/(SUM(HistoricalFS!F50:F52)),0) -> 1.0765585 | G21: =IFERROR((HistoricalFS!G30+HistoricalFS!G27)/(SUM(HistoricalFS!G50:G52)),0) -> 0.22133658 | H21: =IFERROR((HistoricalFS!H30+HistoricalFS!H27)/(SUM(HistoricalFS!H50:H52)),0) -> 0.23483155 | I21: =IFERROR((HistoricalFS!I30+HistoricalFS!I27)/(SUM(HistoricalFS!I50:I52)),0) -> 0.25250859 | J21: =IFERROR((HistoricalFS!J30+HistoricalFS!J27)/(SUM(HistoricalFS!J50:J52)),0) -> 0.25507571 | K21: =IFERROR((HistoricalFS!K30+HistoricalFS!K27)/(SUM(HistoricalFS!K50:K52)),0) -> 0.26421156 | L21: =IFERROR((HistoricalFS!#REF!+HistoricalFS!#REF!)/(SUM(HistoricalFS!#REF!)),0) -> 0 | N21: =IFERROR(AVERAGE(C21:L21),0) -> 0.51466223 | O21: =IFERROR(MEDIAN(C21:L21),0) -> 0.25964363
B22: Retained Earnings% | C22: =IFERROR(HistoricalFS!C47,0) -> 0.054582904 | D22: =IFERROR(HistoricalFS!D47,0) -> 0.11366434 | E22: =IFERROR(HistoricalFS!E47,0) -> 0.17183688 | F22: =IFERROR(HistoricalFS!F47,0) -> 0.14718888 | G22: =IFERROR(HistoricalFS!G47,0) -> 0 | H22: =IFERROR(HistoricalFS!H47,0) -> 0.078750144 | I22: =IFERROR(HistoricalFS!I47,0) -> 0.054667354 | J22: =IFERROR(HistoricalFS!J47,0) -> 0 | K22: =IFERROR(HistoricalFS!K47,0) -> 0 | L22: =IFERROR(HistoricalFS!#REF!,0) -> 0 | N22: =IFERROR(AVERAGE(C22:L22),0) -> 0.06206905 | O22: =IFERROR(MEDIAN(C22:L22),0) -> 0.054625129
B23: Return On Equity% | C23: =IFERROR(HistoricalFS!C36/(SUM(HistoricalFS!C50:C52)),0) -> 0.55319755 | D23: =IFERROR(HistoricalFS!D36/(SUM(HistoricalFS!D50:D52)),0) -> 0.66941354 | E23: =IFERROR(HistoricalFS!E36/(SUM(HistoricalFS!E50:E52)),0) -> 0.72031132 | F23: =IFERROR(HistoricalFS!F36/(SUM(HistoricalFS!F50:F52)),0) -> 0.76947381 | G23: =IFERROR(HistoricalFS!G36/(SUM(HistoricalFS!G50:G52)),0) -> 0.16421949 | H23: =IFERROR(HistoricalFS!H36/(SUM(HistoricalFS!H50:H52)),0) -> 0.17309995 | I23: =IFERROR(HistoricalFS!I36/(SUM(HistoricalFS!I50:I52)),0) -> 0.18816839 | J23: =IFERROR(HistoricalFS!J36/(SUM(HistoricalFS!J50:J52)),0) -> 0.1795947 | K23: =IFERROR(HistoricalFS!K36/(SUM(HistoricalFS!K50:K52)),0) -> 0.18313418 | L23: =IFERROR(HistoricalFS!#REF!/(SUM(HistoricalFS!#REF!)),0) -> 0 | N23: =IFERROR(AVERAGE(C23:L23),0) -> 0.36006129 | O23: =IFERROR(MEDIAN(C23:L23),0) -> 0.18565129
B24: Self Sustained Growth Rate | C24: =IFERROR(C22*C23,0) -> 0.030195129 | D24: =IFERROR(D22*D23,0) -> 0.076088449 | E24: =IFERROR(E22*E23,0) -> 0.12377605 | F24: =IFERROR(F22*F23,0) -> 0.11325799 | G24: =IFERROR(G22*G23,0) -> 0 | H24: =IFERROR(H22*H23,0) -> 0.013631646 | I24: =IFERROR(I22*I23,0) -> 0.010286668 | J24: =IFERROR(J22*J23,0) -> 0 | ... L24: =IFERROR(L22*L23,0) -> 0 | N24: =IFERROR(AVERAGE(C24:L24),0) -> 0.036723593 | O24: =IFERROR(MEDIAN(C24:L24),0) -> 0.011959157
B25: Interest Coverage Ratio | C25: =IFERROR((HistoricalFS!C30+HistoricalFS!C27)/HistoricalFS!C27,0) -> 168.45714 | D25: =IFERROR((HistoricalFS!D30+HistoricalFS!D27)/HistoricalFS!D27,0) -> 268.42308 | E25: =IFERROR((HistoricalFS!E30+HistoricalFS!E27)/HistoricalFS!E27,0) -> 251.9697 | F25: =IFERROR((HistoricalFS!F30+HistoricalFS!F27)/HistoricalFS!F27,0) -> 75.076271 | G25: =IFERROR((HistoricalFS!G30+HistoricalFS!G27)/HistoricalFS!G27,0) -> 90.188034 | H25: =IFERROR((HistoricalFS!H30+HistoricalFS!H27)/HistoricalFS!H27,0) -> 111 | I25: =IFERROR((HistoricalFS!I30+HistoricalFS!I27)/HistoricalFS!I27,0) -> 114.12281 | J25: =IFERROR((HistoricalFS!J30+HistoricalFS!J27)/HistoricalFS!J27,0) -> 40.248503 | K25: =IFERROR((HistoricalFS!K30+HistoricalFS!K27)/HistoricalFS!K27,0) -> 34.146835 | L25: =IFERROR((HistoricalFS!#REF!+HistoricalFS!#REF!)/HistoricalFS!#REF!,0) -> 0 | N25: =IFERROR(AVERAGE(C25:L25),0) -> 115.36324 | O25: =IFERROR(MEDIAN(C25:L25),0) -> 100.59402
B27: Debtor Turnover Ratio | C27: =IFERROR(HistoricalFS!C6/HistoricalFS!C62,0) -> 30.564055 | D27: =IFERROR(HistoricalFS!D6/HistoricalFS!D62,0) -> 27.133588 | E27: =IFERROR(HistoricalFS!E6/HistoricalFS!E62,0) -> 21.646476 | F27: =IFERROR(HistoricalFS!F6/HistoricalFS!F62,0) -> 34.624021 | G27: =IFERROR(HistoricalFS!G6/HistoricalFS!G62,0) -> 26.750853 | H27: =IFERROR(HistoricalFS!H6/HistoricalFS!H62,0) -> 23.455277 | I27: =IFERROR(HistoricalFS!I6/HistoricalFS!I62,0) -> 19.675219 | J27: =IFERROR(HistoricalFS!J6/HistoricalFS!J62,0) -> 20.652653 | K27: =IFERROR(HistoricalFS!K6/HistoricalFS!K62,0) -> 16.528149 | L27: =IFERROR(HistoricalFS!#REF!/HistoricalFS!#REF!,0) -> 0 | N27: =IFERROR(AVERAGE(C27:L27),0) -> 22.103029 | O27: =IFERROR(MEDIAN(C27:L27),0) -> 22.550877
B28: Creditor Turnover Ratio | C28: =IFERROR(HistoricalFS!C6/HistoricalFS!C53,0) -> 3.8183074 | D28: =IFERROR(HistoricalFS!D6/HistoricalFS!D53,0) -> 3.3593233 | E28: =IFERROR(HistoricalFS!E6/HistoricalFS!E53,0) -> 3.6865798 | F28: =IFERROR(HistoricalFS!F6/HistoricalFS!F53,0) -> 3.3363804 | G28: =IFERROR(HistoricalFS!G6/HistoricalFS!G53,0) -> 2.2324124 | H28: =IFERROR(HistoricalFS!H6/HistoricalFS!H53,0) -> 2.5706303 | I28: =IFERROR(HistoricalFS!I6/HistoricalFS!I53,0) -> 2.8106152 | J28: =IFERROR(HistoricalFS!J6/HistoricalFS!J53,0) -> 2.4002792 | K28: =IFERROR(HistoricalFS!K6/HistoricalFS!K53,0) -> 2.1907125 | L28: =IFERROR(HistoricalFS!#REF!/HistoricalFS!#REF!,0) -> 0 | N28: =IFERROR(AVERAGE(C28:L28),0) -> 2.6405241 | O28: =IFERROR(MEDIAN(C28:L28),0) -> 2.6906228
B29: Inventory Turnover | C29: =IFERROR(HistoricalFS!C6/HistoricalFS!C63,0) -> 13.050767 | D29: =IFERROR(HistoricalFS!D6/HistoricalFS!D63,0) -> 14.144449 | E29: =IFERROR(HistoricalFS!E6/HistoricalFS!E63,0) -> 15.27195 | F29: =IFERROR(HistoricalFS!F6/HistoricalFS!F63,0) -> 14.377665 | G29: =IFERROR(HistoricalFS!G6/HistoricalFS!G63,0) -> 13.139983 | H29: =IFERROR(HistoricalFS!H6/HistoricalFS!H63,0) -> 12.804199 | I29: =IFERROR(HistoricalFS!I6/HistoricalFS!I63,0) -> 14.250765 | J29: =IFERROR(HistoricalFS!J6/HistoricalFS!J63,0) -> 15.389359 | K29: =IFERROR(HistoricalFS!K6/HistoricalFS!K63,0) -> 14.296942 | L29: =IFERROR(HistoricalFS!#REF!/HistoricalFS!#REF!,0) -> 0 | N29: =IFERROR(AVERAGE(C29:L29),0) -> 12.672608 | O29: =IFERROR(MEDIAN(C29:L29),0) -> 14.197607
B30: Fixed Asset Turnover | C30: =IFERROR(HistoricalFS!C6/HistoricalFS!C56,0) -> 7.5044128 | E30: =IFERROR(HistoricalFS!E6/HistoricalFS!E56,0) -> 8.3372216 | F30: =IFERROR(HistoricalFS!F6/HistoricalFS!F56,0) -> 7.2609965 | G30: =IFERROR(HistoricalFS!G6/HistoricalFS!G56,0) -> 0.91417686 | H30: =IFERROR(HistoricalFS!H6/HistoricalFS!H56,0) -> 1.0189031 | I30: =IFERROR(HistoricalFS!I6/HistoricalFS!I56,0) -> 1.1500057 | J30: =IFERROR(HistoricalFS!J6/HistoricalFS!J56,0) -> 1.151682 | K30: =IFERROR(HistoricalFS!K6/HistoricalFS!K56,0) -> 1.1617006 | L30: =IFERROR(HistoricalFS!#REF!/HistoricalFS!#REF!,0) -> 0 | N30: =IFERROR(AVERAGE(C30:L30),0) -> 3.1665666 | O30: =IFERROR(MEDIAN(C30:L30),0) -> 1.151682
B31: Capital Turnover Ratio | C31: =IFERROR(HistoricalFS!C6/(SUM(HistoricalFS!C50:C51)),0) -> 4.9172598 | D31: =IFERROR(HistoricalFS!D6/(SUM(HistoricalFS!D50:D51)),0) -> 4.8818844 | E31: =IFERROR(HistoricalFS!E6/(SUM(HistoricalFS!E50:E51)),0) -> 4.9968222 | F31: =IFERROR(HistoricalFS!F6/(SUM(HistoricalFS!F50:F51)),0) -> 4.8344878 | G31: =IFERROR(HistoricalFS!G6/(SUM(HistoricalFS!G50:G51)),0) -> 0.98644964 | H31: =IFERROR(HistoricalFS!H6/(SUM(HistoricalFS!H50:H51)),0) -> 1.0689957 | I31: =IFERROR(HistoricalFS!I6/(SUM(HistoricalFS!I50:I51)),0) -> 1.204278 | J31: =IFERROR(HistoricalFS!J6/(SUM(HistoricalFS!J50:J51)),0) -> 1.2084814 | K31: =IFERROR(HistoricalFS!K6/(SUM(HistoricalFS!K50:K51)),0) -> 1.2777013 | L31: =IFERROR(HistoricalFS!#REF!/(SUM(HistoricalFS!#REF!)),0) -> 0 | N31: =IFERROR(AVERAGE(C31:L31),0) -> 2.537636 | O31: =IFERROR(MEDIAN(C31:L31),0) -> 1.2430914
B33: Debtor Days | C33: =IFERROR(365/C27,0) -> 11.942133 | D33: =IFERROR(365/D27,0) -> 13.451962 | E33: =IFERROR(365/E27,0) -> 16.861867 | F33: =IFERROR(365/F27,0) -> 10.541814 | G33: =IFERROR(365/G27,0) -> 13.644425 | H33: =IFERROR(365/H27,0) -> 15.56153 | I33: =IFERROR(365/I27,0) -> 18.551255 | J33: =IFERROR(365/J27,0) -> 17.673275 | ... L33: =IFERROR(365/L27,0) -> 0 | N33: =IFERROR(AVERAGE(C33:L33),0) -> 14.03118 | O33: =IFERROR(MEDIAN(C33:L33),0) -> 14.602977
B34: Payable Days | C34: =IFERROR(365/C28,0) -> 95.592093 | D34: =IFERROR(365/D28,0) -> 108.65283 | E34: =IFERROR(365/E28,0) -> 99.007759 | F34: =IFERROR(365/F28,0) -> 109.39999 | G34: =IFERROR(365/G28,0) -> 163.50026 | H34: =IFERROR(365/H28,0) -> 141.98852 | I34: =IFERROR(365/I28,0) -> 129.86481 | J34: =IFERROR(365/J28,0) -> 152.06564 | ... L34: =IFERROR(365/L28,0) -> 0 | N34: =IFERROR(AVERAGE(C34:L34),0) -> 116.66844 | O34: =IFERROR(MEDIAN(C34:L34),0) -> 119.6324
B35: Inventory Days | C35: =IFERROR(365/C29,0) -> 27.967704 | D35: =IFERROR(365/D29,0) -> 25.805177 | E35: =IFERROR(365/E29,0) -> 23.900025 | F35: =IFERROR(365/F29,0) -> 25.386597 | G35: =IFERROR(365/G29,0) -> 27.777813 | H35: =IFERROR(365/H29,0) -> 28.506273 | I35: =IFERROR(365/I29,0) -> 25.612661 | J35: =IFERROR(365/J29,0) -> 23.717688 | ... L35: =IFERROR(365/L29,0) -> 0 | N35: =IFERROR(AVERAGE(C35:L35),0) -> 23.420387 | O35: =IFERROR(MEDIAN(C35:L35),0) -> 25.571298
B36: Cash Conversion Cycle | C36: =SUM(C33,C35)-C34 -> -55.682257 | D36: =SUM(D33,D35)-D34 -> -69.395696 | E36: =SUM(E33,E35)-E34 -> -58.245866 | F36: =SUM(F33,F35)-F34 -> -73.471583 | G36: =SUM(G33,G35)-G34 -> -122.07802 | H36: =SUM(H33,H35)-H34 -> -97.920718 | I36: =SUM(I33,I35)-I34 -> -85.700891 | J36: =SUM(J33,J35)-J34 -> -110.67468 | ... L36: =SUM(L33,L35)-L34 -> 0 | N36: =IFERROR(AVERAGE(C36:L36),0) -> -79.21687 | O36: =IFERROR(MEDIAN(C36:L36),0) -> -79.586237
B38: CFO/Sales | C38: =IFERROR(HistoricalFS!C80/HistoricalFS!C6,0) -> 0.013750678 | D38: =IFERROR(HistoricalFS!D80/HistoricalFS!D6,0) -> 0.020509214 | E38: =IFERROR(HistoricalFS!E80/HistoricalFS!E6,0) -> 0.020503689 | F38: =IFERROR(HistoricalFS!F80/HistoricalFS!F6,0) -> 0.032199683 | G38: =IFERROR(HistoricalFS!G80/HistoricalFS!G6,0) -> 0.029237901 | H38: =IFERROR(HistoricalFS!H80/HistoricalFS!H6,0) -> 0.026179308 | I38: =IFERROR(HistoricalFS!I80/HistoricalFS!I6,0) -> 0.043413668 | J38: =IFERROR(HistoricalFS!J80/HistoricalFS!J6,0) -> 0.044348585 | K38: =IFERROR(HistoricalFS!K80/HistoricalFS!K6,0) -> 0.039020294 | L38: =IFERROR(HistoricalFS!#REF!/HistoricalFS!#REF!,0) -> 0 | N38: =IFERROR(AVERAGE(C38:L38),0) -> 0.026916302 | O38: =IFERROR(MEDIAN(C38:L38),0) -> 0.027708605
B39: CFO/Total Assets | C39: =IFERROR(HistoricalFS!C80/HistoricalFS!C67,0) -> 0.02903349 | D39: =IFERROR(HistoricalFS!D80/HistoricalFS!D67,0) -> 0.040812899 | E39: =IFERROR(HistoricalFS!E80/HistoricalFS!E67,0) -> 0.043265876 | F39: =IFERROR(HistoricalFS!F80/HistoricalFS!F67,0) -> 0.063563737 | G39: =IFERROR(HistoricalFS!G80/HistoricalFS!G67,0) -> 0.02000291 | H39: =IFERROR(HistoricalFS!H80/HistoricalFS!H67,0) -> 0.01947352 | I39: =IFERROR(HistoricalFS!I80/HistoricalFS!I67,0) -> 0.035989436 | J39: =IFERROR(HistoricalFS!J80/HistoricalFS!J67,0) -> 0.034973054 | K39: =IFERROR(HistoricalFS!K80/HistoricalFS!K67,0) -> 0.030840314 | L39: =IFERROR(HistoricalFS!#REF!/HistoricalFS!#REF!,0) -> 0 | N39: =IFERROR(AVERAGE(C39:L39),0) -> 0.031795524 | O39: =IFERROR(MEDIAN(C39:L39),0) -> 0.032906684
B40: CFO/Total Debt | C40: =IFERROR(HistoricalFS!C80/HistoricalFS!C52,0) -> 1.6462094 | D40: =IFERROR(HistoricalFS!D80/HistoricalFS!D52,0) -> 0 | E40: =IFERROR(HistoricalFS!E80/HistoricalFS!E52,0) -> 8.1414141 | F40: =IFERROR(HistoricalFS!F80/HistoricalFS!F52,0) -> 0 | G40: =IFERROR(HistoricalFS!G80/HistoricalFS!G52,0) -> 0 | H40: =IFERROR(HistoricalFS!H80/HistoricalFS!H52,0) -> 1.316395 | I40: =IFERROR(HistoricalFS!I80/HistoricalFS!I52,0) -> 2.1575062 | J40: =IFERROR(HistoricalFS!J80/HistoricalFS!J52,0) -> 1.8497305 | K40: =IFERROR(HistoricalFS!K80/HistoricalFS!K52,0) -> 1.4945388 | L40: =IFERROR(HistoricalFS!#REF!/HistoricalFS!#REF!,0) -> 0 | N40: =IFERROR(AVERAGE(C40:L40),0) -> 1.6605794 | O40: =IFERROR(MEDIAN(C40:L40),0) -> 1.4054669

Sheet Forecasting
B2: ='Data Sheet'!B1&" -"&" Sales Forecasting" -> HINDUSTAN UNILEVER LTD - Sales Forecasting | G2: ='Data Sheet'!B1&" -"&" EBITDA Forecasting" -> HINDUSTAN UNILEVER LTD - EBITDA Forecasting | L2: ='Data Sheet'!B1&" -"&" EBIT Forecasting" -> HINDUSTAN UNILEVER LTD - EBIT Forecasting | Q2: ='Data Sheet'!B1&" -"&" Depreciation Forecasting" -> HINDUSTAN UNILEVER LTD - Depreciation Forecasting
B3: Year Weight | C3: Year | D3: Sales | E3: Sales Growth | G3: Year Weight | H3: Year | I3: EBITDA | J3: EBITDA Growth | L3: Year Weight | M3: Year | N3: EBIT | O3: EBIT Growth | Q3: Year Weight | R3: Year | S3: D&A | T3: D&A as Sales% | U3: D&A Growth
B4: 1 | C4: {=TRANSPOSE('Data Sheet'!B16:J16)} -> 42825 | D4: {=TRANSPOSE('Data Sheet'!B17:J17)} -> 33162 | E4: - | G4: 1 | H4: 42825 | I4: {=TRANSPOSE(HistoricalFS!C18:K18)} -> 6328 | J4: - | L4: 1 | M4: 42825 | N4: {=TRANSPOSE(HistoricalFS!C24:K24)} -> 5896 | O4: - | Q4: 1 | R4: 42825 | S4: {=TRANSPOSE(HistoricalFS!C21:K21)} -> 432 | T4: {=TRANSPOSE(HistoricalFS!C22:K22)} -> 0.013026959 | U4: -
B5: 2 | C5: 43190 | D5: 35545 | E5: =(D5-D4)/D4 -> 0.071859357 | G5: 2 | H5: 43190 | I5: 7499 | J5: =(I5-I4)/I4 -> 0.18505057 | L5: 2 | M5: 43190 | N5: 6979 | O5: =(N5-N4)/N4 -> 0.18368385 | Q5: 2 | R5: 43190 | S5: 520 | T5: 0.014629343 | U5: =(S5-S4)/S4 -> 0.2037037
B6: 3 | C6: 43555 | D6: 39310 | E6: =(D6-D5)/D5 -> 0.10592207 | G6: 3 | H6: 43555 | I6: 8880 | J6: =(I6-I5)/I5 -> 0.18415789 | L6: 3 | M6: 43555 | N6: 8315 | O6: =(N6-N5)/N5 -> 0.19143144 | Q6: 3 | R6: 43555 | S6: 565 | T6: 0.014372933 | U6: =(S6-S5)/S5 -> 0.086538462
B7: 4 | C7: 43921 | D7: 39783 | E7: =(D7-D6)/D6 -> 0.012032562 | G7: 4 | H7: 43921 | I7: 9861 | J7: =(I7-I6)/I6 -> 0.11047297 | L7: 4 | M7: 43921 | N7: 8859 | O7: =(N7-N6)/N6 -> 0.065423933 | Q7: 4 | R7: 43921 | S7: 1002 | T7: 0.025186638 | U7: =(S7-S6)/S6 -> 0.77345133
B8: 5 | C8: 44286 | D8: 47028 | E8: =(D8-D7)/D7 -> 0.18211296 | G8: 5 | H8: 44286 | I8: 11626 | J8: =(I8-I7)/I7 -> 0.17898793 | L8: 5 | M8: 44286 | N8: 10552 | O8: =(N8-N7)/N7 -> 0.19110509 | Q8: 5 | R8: 44286 | S8: 1074 | T8: 0.022837459 | U8: =(S8-S7)/S7 -> 0.071856287
B9: 6 | C9: 44651 | D9: 52446 | E9: =(D9-D8)/D8 -> 0.11520796 | G9: 6 | H9: 44651 | I9: 12857 | J9: =(I9-I8)/I8 -> 0.10588336 | L9: 6 | M9: 44651 | N9: 11766 | O9: =(N9-N8)/N8 -> 0.11504928 | Q9: 6 | R9: 44651 | S9: 1091 | T9: 0.020802349 | U9: =(S9-S8)/S8 -> 0.015828678
B10: 7 | C10: 45016 | D10: 60580 | E10: =(D10-D9)/D9 -> 0.15509286 | G10: 7 | H10: 45016 | I10: 14147 | J10: =(I10-I9)/I9 -> 0.10033445 | L10: 7 | M10: 45016 | N10: 13010 | O10: =(N10-N9)/N9 -> 0.10572837 | Q10: 7 | R10: 45016 | S10: 1137 | T10: 0.01876857 | U10: =(S10-S9)/S9 -> 0.042163153
B11: 8 | C11: 45382 | D11: 61896 | E11: =(D11-D10)/D10 -> 0.021723341 | G11: 8 | H11: 45382 | I11: 14659 | J11: =(I11-I10)/I10 -> 0.036191419 | L11: 8 | M11: 45382 | N11: 13443 | O11: =(N11-N10)/N10 -> 0.033282091 | Q11: 8 | R11: 45382 | S11: 1216 | T11: 0.019645858 | U11: =(S11-S10)/S10 -> 0.069481091
B12: 9 | C12: 45747 | D12: 63121 | E12: =(D12-D11)/D11 -> 0.019791263 | G12: 9 | H12: 45747 | I12: 14843 | J12: =(I12-I11)/I11 -> 0.012552016 | L12: 9 | M12: 45747 | N12: 13488 | O12: =(N12-N11)/N11 -> 0.0033474671 | Q12: 9 | R12: 45747 | S12: 1355 | T12: 0.021466707 | U12: =(S12-S11)/S11 -> 0.11430921
B13: 10 | C13: 46082 | D13: =D12*(1+E13) -> 68170.68 | E13: 0.08 | G13: 10 | H13: 46082 | I13: =I12*(1+J13) -> 18331.105 | J13: 0.235 | L13: 10 | M13: 46082 | N13: =I13-S13 -> 16967.691 | O13: =(N13-N12)/N12 -> 0.25798424 | Q13: 10 | R13: 46082 | S13: =D13*T13 -> 1363.4136 | T13: 0.02 | U13: =(S13-S12)/S12 -> 0.0062092989
B14: 11 | C14: 46447 | D14: =D13*(1+E14) -> 74987.748 | E14: 0.1 | G14: 11 | H14: 46447 | I14: =I13*(1+J14) -> 22730.57 | J14: 0.24 | L14: 11 | M14: 46447 | N14: =I14-S14 -> 21230.815 | O14: =(N14-N13)/N13 -> 0.25124949 | Q14: 11 | R14: 46447 | S14: =D14*T14 -> 1499.755 | T14: 0.02 | U14: =(S14-S13)/S13 -> 0.1
B15: 12 | C15: 46813 | D15: =D14*(1+E15) -> 81736.645 | E15: 0.09 | G15: 12 | H15: 46813 | I15: =I14*(1+J15) -> 28185.907 | J15: 0.24 | L15: 12 | M15: 46813 | N15: =I15-S15 -> 26551.174 | O15: =(N15-N14)/N14 -> 0.25059607 | Q15: 12 | R15: 46813 | S15: =D15*T15 -> 1634.7329 | T15: 0.02 | U15: =(S15-S14)/S14 -> 0.09
B16: 13 | C16: 47178 | D16: =D15*(1+E16) -> 88275.577 | E16: 0.08 | G16: 13 | H16: 47178 | I16: =I15*(1+J16) -> 34809.595 | J16: 0.235 | L16: 13 | M16: 47178 | N16: =I16-S16 -> 33044.084 | O16: =(N16-N15)/N15 -> 0.24454322 | Q16: 13 | R16: 47178 | S16: =D16*T16 -> 1765.5115 | T16: 0.02 | U16: =(S16-S15)/S15 -> 0.08
B17: 14 | C17: 47543 | D17: =D16*(1+E17) -> 94454.867 | E17: 0.07 | G17: 14 | H17: 47543 | I17: =I16*(1+J17) -> 42989.85 | J17: 0.235 | L17: 14 | M17: 47543 | N17: =I17-S17 -> 41100.753 | O17: =(N17-N16)/N16 -> 0.24381578 | Q17: 14 | R17: 47543 | S17: =D17*T17 -> 1889.0973 | T17: 0.02 | U17: =(S17-S16)/S16 -> 0.07
B18: 15 | C18: 47908 | D18: =D17*(1+E18) -> 100122.16 | E18: 0.06 | G18: 15 | H18: 47908 | I18: =I17*(1+J18) -> 52877.516 | J18: 0.23 | L18: 15 | M18: 47908 | N18: =I18-S18 -> 50875.072 | O18: =(N18-N17)/N17 -> 0.23781364 | Q18: 15 | R18: 47908 | S18: =D18*T18 -> 2002.4432 | T18: 0.02 | U18: =(S18-S17)/S17 -> 0.06

Sheet DCF>
B1: Company | C1: Country | D1: Total Debt | E1: Total Equity | F1: Tax Rate
B2: Vishal Mega Mart | C2: India | D2: 1729 | E2: =4597+1804 -> 6401 | F2: 0.26
B3: V-Mart Retail | C3: India | D3: 783 | E3: 810 | F3: 0.26
B4: Shopper's Store | C4: India | D4: 3314 | E4: =55+266 -> 321 | F4: 0.26
B5: Electronics Mart | C5: India | D5: 1976 | E5: =385+1146 -> 1531 | F5: 0.26
B6: Patel Retail | C6: India | D6: 183 | E6: =25+110 -> 135 | F6: 0.26

Sheet DCF
B2: Calculation of PV of FCFF | E2: =HistoricalFS!K3 -> 45747 | F2: =E2+365 -> 46112 | G2: =F2+365 -> 46477 | H2: =G2+365 -> 46842 | I2: =H2+365 -> 47207 | J2: =I2+365 -> 47572
B4: Revenue | E4: =Forecasting!D12 -> 63121 | F4: =Forecasting!$D13 -> 68170.68 | G4: =Forecasting!$D14 -> 74987.748 | H4: =Forecasting!$D15 -> 81736.645 | I4: =Forecasting!$D16 -> 88275.577 | J4: =Forecasting!$D17 -> 94454.867
B5: EBITDA | E5: =Forecasting!I12 -> 14843 | F5: =Forecasting!I13 -> 18331.105 | G5: =Forecasting!I14 -> 22730.57 | H5: =Forecasting!I15 -> 28185.907 | I5: =Forecasting!I16 -> 34809.595 | J5: =Forecasting!I17 -> 42989.85
B6: EBIT | E6: =HistoricalFS!K24 -> 13488 | F6: =Forecasting!$N13 -> 16967.691 | G6: =Forecasting!$N14 -> 21230.815 | H6: =Forecasting!$N15 -> 26551.174 | I6: =Forecasting!$N16 -> 33044.084 | J6: =Forecasting!$N17 -> 41100.753
B7: Tax Rate | E7: =HistoricalFS!K33/HistoricalFS!K30 -> 0.28595433 | F7: 0.26 | G7: 0.26 | H7: 0.26 | I7: 0.26 | J7: 0.26
B8: EBIT (1-T) | E8: =E6*(1-E7) -> 9631.048 | F8: =F6*(1-F7) -> 12556.092 | G8: =G6*(1-G7) -> 15710.803 | H8: =H6*(1-H7) -> 19647.869 | I8: =I6*(1-I7) -> 24452.622 | J8: =J6*(1-J7) -> 30414.557
B9: Less : Reinvestment Rate | E9: 0.31830994 | F9: 0.31830994 | G9: 0.31830994 | H9: 0.31830994 | I9: 0.31830994 | J9: 0.31830994
B10: Free Cash Flow to the Firm | E10: =E8*(1-E9) -> 6565.3897 | F10: =F8*(1-F9) -> 8559.3628 | G10: =G8*(1-G9) -> 10709.898 | H10: =H8*(1-H9) -> 13393.757 | I10: =I8*(1-I9) -> 16669.109 | J10: =J8*(1-J9) -> 20733.301
B11: Mid Year Convention | F11: 0.5 | G11: =F11+1 -> 1.5 | H11: =G11+1 -> 2.5 | I11: =H11+1 -> 3.5 | J11: =I11+1 -> 4.5
B12: Discounting Factor | F12: =1/(1+$J$17)^F11 -> 0.93980509 | G12: =1/(1+$J$17)^G11 -> 0.83006743 | H12: =1/(1+$J$17)^H11 -> 0.73314345 | I12: =1/(1+$J$17)^I11 -> 0.64753693 | J12: =1/(1+$J$17)^J11 -> 0.57192638
B13: PV of FCFF | F13: =F10*F12 -> 8044.1328 | G13: =G10*G12 -> 8889.9379 | H13: =H10*H12 -> 9819.5451 | I13: =I10*I12 -> 10793.864 | J13: =J10*J12 -> 11857.922
B15: Expected Growth | E15: - | F15: 0.08 | G15: 0.1 | H15: 0.09 | I15: 0.08 | J15: 0.07
B16: Terminal Growth | J16: 0.06
B17: WACC | J17: =WACC!J40 -> 0.1322033
B20: Calculation of Terminal Value | F20: Sensitivity Table
F21: =D38 -> 900.2544 | G21: 0.11 | H21: 0.12 | I21: 0.1322 | J21: 0.14
B22: FCCF (n+1) | D22: =J10*(1+D15) -> 20733.301 | F22: 0.05 | G22: 1132.4401 | H22: 964.53985 | I22: 815.2555 | J22: 741.13878
B23: WACC | D23: =J17 -> 0.1322033 | F23: 0.055 | G23: 1216.0385 | H23: 1022.7733 | I23: 855.02239 | J23: 773.1227
B24: Terminal Growth Rate | D24: =J16 -> 0.06 | F24: 0.06 | G24: 1316.3565 | H24: 1090.7123 | I24: 900.29716 | J24: 809.10461
F25: 0.065 | G25: 1438.9674 | H25: 1171.0039 | I25: 952.30926 | J25: 849.88411
B26: Terminal Value | D26: =D22/(D23-D24) -> 287151.71
B29: Calculation of Equity Value
B31: PV of FCFF | D31: =SUM(F13:J13) -> 49405.401
B32: PV of Terminal Value | D32: {=D26*J12} -> 164229.64
B33: Value of Operating Assets | D33: =SUM(D31:D32) -> 213635.04
B34: Add : Cash | D34: =[1]HistoricalFS!L64 -> 303.78
B35: Less : Debt | D35: =SUM('[1]Raw FS'!L7:L9) -> 2425
B36: Value of Equity | D36: =D33+D34-D35 -> 211513.82
B37: No of Shares | D37: ='Data Sheet'!B6 -> 234.94894
B38: Equity Value Per Share | D38: =D36/D37 -> 900.2544
B40: Share Price | D40: ='Data Sheet'!B8 -> 2262
B41: Discount/Premium | D41: =D40/D38-1 -> 1.5126231
B45: Notes : 1. Base year reinvestment rate provides distortion in the FCFF. The company is spending a lot on new stores.

Sheet WACC
B2: Weighted Average Cost of Capital
B4: All figures are in INR unless stated otherwise
B6: Peer Comps
G7: Debt / | H7: Debt / | I7: Levered | J7: Unlevered
B8: Name of the Comp | C8: Country | D8: Total Debt | E8: Total Equity | F8: Tax Rate 1 | G8: Equity | H8: Capital | I8: Beta 2 | J8: Beta 3
B10: ='Beta - Comps'!C3 -> Hindustan Unilever | C10: India | D10: ='Beta - Comps'!F3 -> 1478 | E10: ='Beta - Comps'!E3 -> 530220.51 | F10: 0.23833333 | G10: =D10/E10 -> 0.0027875195 | H10: =D10/(D10+E10) -> 0.0027797708 | I10: ='Beta - Regression'!J10 -> 0.72661619 | J10: =I10/(1+(1-F10)*G10) -> 0.72507674
B11: ='Beta - Comps'!C4 -> Nestle India | C11: ='DCF>'!C2 -> India | D11: ='Beta - Comps'!F4 -> 444.16 | E11: ='Beta - Comps'!E4 -> 283655.02 | F11: 0.26 | G11: =D11/E11 -> 0.0015658457 | H11: =D11/(D11+E11) -> 0.0015633977 | I11: ='Beta - Regression'!J122 -> 0.82032057 | J11: =I11/(1+(1-F11)*G11) -> 0.81937114
B12: ='Beta - Comps'!C5 -> Marico | C12: ='DCF>'!C3 -> India | D12: ='Beta - Comps'!F5 -> 557 | E12: ='Beta - Comps'!E5 -> 107499.72 | F12: 0.222 | G12: =D12/E12 -> 0.0051814088 | H12: =D12/(D12+E12) -> 0.0051547002 | I12: ='Beta - Regression'!J233 -> 0.66091889 | J12: =I12/(1+(1-F12)*G12) -> 0.65826533
B13: ='Beta - Comps'!C6 -> Godrej Consumer | C13: ='DCF>'!C4 -> India | D13: ='Beta - Comps'!F6 -> 4415.81 | E13: ='Beta - Comps'!E6 -> 104677.93 | F13: 0.2125 | G13: =D13/E13 -> 0.042184728 | H13: =D13/(D13+E13) -> 0.040477208 | I13: ='Beta - Regression'!J343 -> 1.0104586 | J13: =I13/(1+(1-F13)*G13) -> 0.97797002
B14: ='Beta - Comps'!C7 -> Dabur India | C14: ='DCF>'!C6 -> India | D14: ='Beta - Comps'!F7 -> 1287.32 | E14: ='Beta - Comps'!E7 -> 83993.12 | F14: 0.22 | G14: =D14/E14 -> 0.015326493 | H14: =D14/(D14+E14) -> 0.015095138 | I14: ='Beta - Regression'!J453 -> 0.6920856 | J14: =I14/(1+(1-F14)*G14) -> 0.68390968
B15: ='Beta - Comps'!C8 -> Emami | C15: India | D15: ='Beta - Comps'!F8 -> 71.96 | E15: ='Beta - Comps'!E8 -> 18867.72 | F15: 0.11 | G15: =D15/E15 -> 0.0038139213 | H15: =D15/(D15+E15) -> 0.0037994306 | I15: ='Beta - Regression'!J564 -> 0.94271206 | J15: =I15/(1+(1-F15)*G15) -> 0.93952295
E17: Average | F17: =AVERAGE(F10:F15) -> 0.21047222 | G17: =AVERAGE(G10:G15) -> 0.011809986 | H17: =AVERAGE(H10:H15) -> 0.011478274 | I17: =AVERAGE(I10:I15) -> 0.80885199 | J17: =AVERAGE(J10:J15) -> 0.80068598
E18: Median | F18: =MEDIAN(F10:F15) -> 0.221 | G18: =MEDIAN(G10:G15) -> 0.0044976651 | H18: =MEDIAN(H10:H15) -> 0.0044770654 | I18: =MEDIAN(I10:I15) -> 0.77346838 | J18: =MEDIAN(J10:J15) -> 0.77222394
B20: Cost of Debt | F20: Cost of Equity
B22: Pre-Tax Cost of Debt | D22: 0.084 | F22: Risk Free Rate | J22: 0.06984
B23: Tax Rate | D23: =F10 -> 0.23833333 | F23: Equity Risk Premium | J23: =RM!F6 -> 0.081652308
B24: Post-Tax Cost of Debt | D24: =D22*(1-D23) -> 0.06398 | F24: Levered Beta 4 | J24: =I18 -> 0.77346838
F25: Cost of Equity | J25: =J22+(J23*J24) -> 0.13299548
B28: Capital Structure | G28: Levered Beta
D30: Current | E30: Target | G30: Comps Median Unlevered Beta | J30: =J18 -> 0.77222394
B31: Total Debt | C31: =D10 -> 1478 | D31: =C31/C33 -> 0.0027797708 | E31: =H17 -> 0.011478274 | G31: Target Debt/Equity | J31: =H17 -> 0.011478274
B32: Market Capitalization | C32: =E10 -> 530220.51 | D32: =C32/C33 -> 0.99722023 | E32: =E33-E31 -> 0.98852173 | G32: Tax Rate | J32: =F18 -> 0.221
B33: Total Capital | C33: =C32+C31 -> 531698.51 | D33: =D31+D32 -> 1 | E33: 1 | G33: Levered Beta | J33: =J30*(1+(1-J32)*J31) -> 0.77912884
B35: Debt/Equity | D35: =D31/D32 -> 0.0027875195 | E35: =E31/E32 -> 0.011611555 | G35: Weighted Average Cost of Capital
B37: Notes: | I37: Total Cost | J37: Total Weight
B38: 1. Tax Rate considered as marginal tax rate for the country | G38: Debt | I38: =D24 -> 0.06398 | J38: =E31 -> 0.011478274
B39: 2. Levered Beta is based on 5 year monthly data | G39: Equity | I39: =J25 -> 0.13299548 | J39: =E32 -> 0.98852173
B40: 3. Unlevered Beta = Levered Beta/(1+(1-Tax Rate)*Debt/Equity) | G40: Weighted Average Cost of Capital | J40: =SUMPRODUCT(I38:I39,J38:J39) -> 0.1322033
B41: 4. Levered Beta = Unlevered Beta*(1+(1-Tax Rate)*Debt/Equity)
A53: x`

Sheet Beta - Regression
B2: Regression Beta - 2 Year Weekly
B4: Hindustan Unilever Weekly Returns | F4: Nifty Weekly Returns | I4: Beta Drifting
B6: Date | C6: Closing Price | D6: Returns | F6: Closing Price | G6: Returns | I6: Levered Raw Beta | J6: =M7 -> 0.63548826 | L6: Beta 1 | M6: =SLOPE(D8:D112,G8:G112) -> 0.63548826
B7: 45425 | C7: 2236.9 | D7: - | F7: 22466.1 | G7: - | I7: Raw Beta Weight | J7: 0.75 | L7: Beta 2 | M7: =_xlfn.COVARIANCE.S(D8:D112,G8:G112)/_xlfn.VAR.S(G8:G112) -> 0.63548826
B8: 45432 | C8: 2277.17 | D8: =(C8-C7)/C7 -> 0.018002593 | F8: 22957.1 | G8: =(F8-F7)/F7 -> 0.021855151 | I8: Market Beta | J8: 1 | L8: Beta 3 | M8: SUMMARY OUTPUT
B9: 45439 | C9: 2238.72 | D9: =(C9-C8)/C8 -> -0.016884993 | F9: 22530.7 | G9: =(F9-F8)/F8 -> -0.018573775 | I9: Market Beta Weight | J9: 0.25
B10: 45446 | C10: 2477.82 | D10: =(C10-C9)/C9 -> 0.1068021 | F10: 23290.15 | G10: =(F10-F9)/F9 -> 0.033707342 | I10: Adjusted Beta | J10: =(J6*J7)+(J8*J9) -> 0.72661619 | M10: Regression Statistics
B11: 45453 | C11: 2383.58 | D11: =(C11-C10)/C10 -> -0.038033433 | F11: 23465.6 | G11: =(F11-F10)/F10 -> 0.0075332276 | M11: Multiple R | N11: 0.41174143
B12: 45460 | C12: 2369.48 | D12: =(C12-C11)/C11 -> -0.0059154717 | F12: 23501.1 | G12: =(F12-F11)/F11 -> 0.0015128529 | M12: R Square | N12: 0.169531
B13: 45467 | C13: 2400.3 | D13: =(C13-C12)/C12 -> 0.013007073 | F13: 24010.6 | G13: =(F13-F12)/F12 -> 0.021679836 | M13: Adjusted R Square | N13: 0.1614682
B14: 45474 | C14: 2472.07 | D14: =(C14-C13)/C13 -> 0.029900429 | F14: 24323.85 | G14: =(F14-F13)/F13 -> 0.013046321 | M14: Standard Error | N14: 0.026816858
B15: 45481 | C15: 2545.11 | D15: =(C15-C14)/C14 -> 0.029546089 | F15: 24502.15 | G15: =(F15-F14)/F14 -> 0.0073302541 | M15: Observations | N15: 105
B16: 45488 | C16: 2646.78 | D16: =(C16-C15)/C15 -> 0.039947193 | F16: 24530.9 | G16: =(F16-F15)/F15 -> 0.0011733664
B17: 45495 | C17: 2631.29 | D17: =(C17-C16)/C16 -> -0.0058523942 | F17: 24834.85 | G17: =(F17-F16)/F16 -> 0.012390495 | M17: ANOVA
B18: 45502 | C18: 2613.34 | D18: =(C18-C17)/C17 -> -0.006821749 | F18: 24717.7 | G18: =(F18-F17)/F17 -> -0.0047171616 | N18: df | O18: SS | P18: MS | Q18: F | R18: Significance F
B19: 45509 | C19: 2666.38 | D19: =(C19-C18)/C18 -> 0.020295867 | F19: 24367.5 | G19: =(F19-F18)/F18 -> -0.014167985 | M19: Regression | N19: 1 | O19: 0.015120937 | P19: 0.015120937 | Q19: 21.026304 | R19: 1.278363e-05
B20: 45516 | C20: 2667.4 | D20: =(C20-C19)/C19 -> 0.00038254112 | F20: 24541.15 | G20: =(F20-F19)/F19 -> 0.0071262953 | M20: Residual | N20: 103 | O20: 0.074071819 | P20: 0.00071914387
B21: 45523 | C21: 2732.77 | D21: =(C21-C20)/C20 -> 0.024507011 | F21: 24823.15 | G21: =(F21-F20)/F20 -> 0.011490904 | M21: Total | N21: 104 | O21: 0.089192756
B22: 45530 | C22: 2696.28 | D22: =(C22-C21)/C21 -> -0.013352752 | F22: 25235.9 | G22: =(F22-F21)/F21 -> 0.016627624
B23: 45537 | C23: 2755.43 | D23: =(C23-C22)/C22 -> 0.021937633 | F23: 24852.15 | G23: =(F23-F22)/F22 -> -0.015206511 | N23: Coefficients | O23: Standard Error | P23: t Stat | Q23: P-value | R23: Lower 95% | S23: Upper 95% | T23: Lower 95.0% | U23: Upper 95.0%
B24: 45544 | C24: 2846.67 | D24: =(C24-C23)/C23 -> 0.033112799 | F24: 25356.5 | G24: =(F24-F23)/F23 -> 0.020294019 | M24: Intercept | N24: 0.00018454123 | O24: 0.0026183603 | P24: 0.070479691 | Q24: 0.94394853 | R24: -0.0050083589 | S24: 0.0053774413 | T24: -0.0050083589 | U24: 0.0053774413
B25: 45551 | C25: 2890 | D25: =(C25-C24)/C24 -> 0.015221294 | F25: 25790.95 | G25: =(F25-F24)/F24 -> 0.017133674 | M25: X Variable 1 | N25: 0.63548826 | O25: 0.13858814 | P25: 4.5854448 | Q25: 1.278363e-05 | R25: 0.36063137 | S25: 0.91034514 | T25: 0.36063137 | U25: 0.91034514
B26: 45558 | C26: 2878.99 | D26: =(C26-C25)/C25 -> -0.0038096886 | F26: 26178.95 | G26: =(F26-F25)/F25 -> 0.015044037
B27: 45565 | C27: 2764.94 | D27: =(C27-C26)/C26 -> -0.039614587 | F27: 25014.6 | G27: =(F27-F26)/F26 -> -0.044476574
B28: 45572 | C28: 2701.32 | D28: =(C28-C27)/C27 -> -0.023009541 | F28: 24964.25 | G28: =(F28-F27)/F27 -> -0.0020128245
B29: 45579 | C29: 2637.17 | D29: =(C29-C28)/C28 -> -0.023747649 | F29: 24854.05 | G29: =(F29-F28)/F28 -> -0.0044143125
B30: 45586 | C30: 2453.68 | D30: =(C30-C29)/C29 -> -0.069578374 | F30: 24180.8 | G30: =(F30-F29)/F29 -> -0.027088141
B31: 45593 | C31: 2462.85 | D31: =(C31-C30)/C30 -> 0.0037372437 | F31: 24304.35 | G31: =(F31-F30)/F30 -> 0.0051094257
B32: 45600 | C32: 2433.93 | D32: =(C32-C31)/C31 -> -0.011742493 | F32: 24148.2 | G32: =(F32-F31)/F31 -> -0.0064247758
B33: 45607 | C33: 2345.9 | D33: =(C33-C32)/C32 -> -0.036167844 | F33: 23532.7 | G33: =(F33-F32)/F32 -> -0.025488442
B34: 45614 | C34: 2400.93 | D34: =(C34-C33)/C33 -> 0.023457948 | F34: 23907.25 | G34: =(F34-F33)/F33 -> 0.015916151
B35: 45621 | C35: 2450.91 | D35: =(C35-C34)/C34 -> 0.020816933 | F35: 24131.1 | G35: =(F35-F34)/F34 -> 0.0093632685
B36: 45628 | C36: 2438.78 | D36: =(C36-C35)/C35 -> -0.0049491821 | F36: 24677.8 | G36: =(F36-F35)/F35 -> 0.022655411
B37: 45635 | C37: 2346.78 | D37: =(C37-C36)/C36 -> -0.03772378 | F37: 24768.3 | G37: =(F37-F36)/F36 -> 0.0036672637
... B112: 46155 | C112: 2270.6 | D112: =(C112-C111)/C111 -> 0.0038019452 | F112: 23472.8 | G112: =(F112-F111)/F111 -> 0.0039885284
B116: Nestle Weekly Returns | F116: Nifty Weekly Returns | I116: Beta Drifting
B118: Date | C118: Closing Price | D118: Returns | F118: Closing Price | G118: Returns | I118: Levered Raw Beta | J118: =M119 -> 0.76042742 | L118: Beta 1 | M118: =SLOPE(D119:D224,G119:G224) -> 0.76042742
B119: 45425 | C119: 1227.05 | D119: - | F119: 22466.1 | G119: - | I119: Raw Beta Weight | J119: 0.75 | L119: Beta 2 | M119: =_xlfn.COVARIANCE.S(D120:D224,G120:G224)/_xlfn.VAR.S(G120:G224) -> 0.76042742
B120: 45432 | C120: 1209.09 | D120: =(C120-C119)/C119 -> -0.01463673 | F120: 22957.1 | G120: =(F120-F119)/F119 -> 0.021855151 | I120: Market Beta | J120: 1 | L120: Beta 3 | M120: SUMMARY OUTPUT
B121: 45439 | C121: 1153.8 | D121: =(C121-C120)/C120 -> -0.045728606 | F121: 22530.7 | G121: =(F121-F120)/F120 -> -0.018573775 | I121: Market Beta Weight | J121: 0.25
B122: 45446 | C122: 1226.09 | D122: =(C122-C121)/C121 -> 0.062653839 | F122: 23290.15 | G122: =(F122-F121)/F121 -> 0.033707342 | I122: Adjusted Beta | J122: =(J118*J119)+(J120*J121) -> 0.82032057 | M122: Regression Statistics
B123: 45453 | C123: 1245.71 | D123: =(C123-C122)/C122 -> 0.016002088 | F123: 23465.6 | G123: =(F123-F122)/F122 -> 0.0075332276 | M123: Multiple R | N123: 0.49497235
B124: 45460 | C124: 1224.11 | D124: =(C124-C123)/C123 -> -0.017339509 | F124: 23501.1 | G124: =(F124-F123)/F123 -> 0.0015128529 | M124: R Square | N124: 0.24499763
B125: 45467 | C125: 1250.2 | D125: =(C125-C124)/C124 -> 0.021313444 | F125: 24010.6 | G125: =(F125-F124)/F124 -> 0.021679836 | M125: Adjusted R Square | N125: 0.23766751
B126: 45474 | C126: 1261.22 | D126: =(C126-C125)/C125 -> 0.0088145897 | F126: 24323.85 | G126: =(F126-F125)/F125 -> 0.013046321 | M126: Standard Error | N126: 0.025451548
B127: 45481 | C127: 1278.3 | D127: =(C127-C126)/C126 -> 0.013542443 | F127: 24502.15 | G127: =(F127-F126)/F126 -> 0.0073302541 | M127: Observations | N127: 105
B128: 45488 | C128: 1272.83 | D128: =(C128-C127)/C127 -> -0.0042791207 | F128: 24530.9 | G128: =(F128-F127)/F127 -> 0.0011733664
B129: 45495 | C129: 1218.84 | D129: =(C129-C128)/C128 -> -0.042417291 | F129: 24834.85 | G129: =(F129-F128)/F128 -> 0.012390495 | M129: ANOVA
B130: 45502 | C130: 1227.79 | D130: =(C130-C129)/C129 -> 0.0073430475 | F130: 24717.7 | G130: =(F130-F129)/F129 -> -0.0047171616 | N130: df | O130: SS | P130: MS | Q130: F | R130: Significance F
B131: 45509 | C131: 1232.52 | D131: =(C131-C130)/C130 -> 0.0038524503 | F131: 24367.5 | G131: =(F131-F130)/F130 -> -0.014167985 | M131: Regression | N131: 1 | O131: 0.021651062 | P131: 0.021651062 | Q131: 33.423412 | R131: 7.9852041e-08
B132: 45516 | C132: 1242.73 | D132: =(C132-C131)/C131 -> 0.0082838412 | F132: 24541.15 | G132: =(F132-F131)/F131 -> 0.0071262953 | M132: Residual | N132: 103 | O132: 0.066721475 | P132: 0.00064778131
B133: 45523 | C133: 1244.57 | D133: =(C133-C132)/C132 -> 0.0014806112 | F133: 24823.15 | G133: =(F133-F132)/F132 -> 0.011490904 | M133: Total | N133: 104 | O133: 0.088372537
B134: 45530 | C134: 1230.57 | D134: =(C134-C133)/C133 -> -0.011248865 | F134: 25235.9 | G134: =(F134-F133)/F133 -> 0.016627624
B135: 45537 | C135: 1231.78 | D135: =(C135-C134)/C134 -> 0.00098328417 | F135: 24852.15 | G135: =(F135-F134)/F134 -> -0.015206511 | N135: Coefficients | O135: Standard Error | P135: t Stat | Q135: P-value | R135: Lower 95% | S135: Upper 95% | T135: Lower 95.0% | U135: Upper 95.0%
B136: 45544 | C136: 1245.65 | D136: =(C136-C135)/C135 -> 0.011260128 | F136: 25356.5 | G136: =(F136-F135)/F135 -> 0.020294019 | M136: Intercept | N136: 0.0016791484 | O136: 0.0024850534 | P136: 0.67569911 | Q136: 0.50074596 | R136: -0.0032493689 | S136: 0.0066076656 | T136: -0.0032493689 | U136: 0.0066076656
B137: 45551 | C137: 1328.4 | D137: =(C137-C136)/C136 -> 0.066431181 | F137: 25790.95 | G137: =(F137-F136)/F136 -> 0.017133674 | M137: X Variable 1 | N137: 0.76042742 | O137: 0.13153229 | P137: 5.7812985 | Q137: 7.9852041e-08 | R137: 0.49956415 | S137: 1.0212907 | T137: 0.49956415 | U137: 1.0212907
B138: 45558 | C138: 1351.11 | D138: =(C138-C137)/C137 -> 0.017095754 | F138: 26178.95 | G138: =(F138-F137)/F137 -> 0.015044037
B139: 45565 | C139: 1278.5 | D139: =(C139-C138)/C138 -> -0.053740998 | F139: 25014.6 | G139: =(F139-F138)/F138 -> -0.044476574
B140: 45572 | C140: 1236.01 | D140: =(C140-C139)/C139 -> -0.033234259 | F140: 24964.25 | G140: =(F140-F139)/F139 -> -0.0020128245
B141: 45579 | C141: 1156.51 | D141: =(C141-C140)/C140 -> -0.064319868 | F141: 24854.05 | G141: =(F141-F140)/F140 -> -0.0044143125
B142: 45586 | C142: 1112.45 | D142: =(C142-C141)/C141 -> -0.038097379 | F142: 24180.8 | G142: =(F142-F141)/F141 -> -0.027088141
B143: 45593 | C143: 1123.08 | D143: =(C143-C142)/C142 -> 0.0095554856 | F143: 24304.35 | G143: =(F143-F142)/F142 -> 0.0051094257
B144: 45600 | C144: 1129.65 | D144: =(C144-C143)/C143 -> 0.005849984 | F144: 24148.2 | G144: =(F144-F143)/F143 -> -0.0064247758
B145: 45607 | C145: 1074.12 | D145: =(C145-C144)/C144 -> -0.049156818 | F145: 23532.7 | G145: =(F145-F144)/F144 -> -0.025488442
B146: 45614 | C146: 1105.85 | D146: =(C146-C145)/C145 -> 0.029540461 | F146: 23907.25 | G146: =(F146-F145)/F145 -> 0.015916151
B147: 45621 | C147: 1099.63 | D147: =(C147-C146)/C146 -> -0.0056246326 | F147: 24131.1 | G147: =(F147-F146)/F146 -> 0.0093632685
B148: 45628 | C148: 1115.94 | D148: =(C148-C147)/C147 -> 0.014832262 | F148: 24677.8 | G148: =(F148-F147)/F147 -> 0.022655411
B149: 45635 | C149: 1108.91 | D149: =(C149-C148)/C148 -> -0.0062996218 | F149: 24768.3 | G149: =(F149-F148)/F148 -> 0.0036672637
... B224: 46155 | C224: 1468.9 | D224: =(C224-C223)/C223 -> 0.00020427618 | F224: 23472.8 | G224: =(F224-F223)/F223 -> 0.0039885284
B227: Marico Weekly Returns | F227: Nifty Weekly Returns | I227: Beta Drifting
B229: Date | C229: Closing Price | D229: Returns | F229: Closing Price | G229: Returns | I229: Levered Raw Beta | J229: =M229 -> 0.54789185 | L229: Beta 1 | M229: =SLOPE(D230:D335,G230:G335) -> 0.54789185
B230: 45425 | C230: 585.57 | D230: - | F230: 22466.1 | G230: - | I230: Raw Beta Weight | J230: 0.75 | L230: Beta 2 | M230: =_xlfn.COVARIANCE.S(D230:D335,G230:G335)/_xlfn.VAR.S(G230:G335) -> 0.54789185
B231: 45432 | C231: 594.88 | D231: =(C231-C230)/C230 -> 0.015899039 | F231: 22957.1 | G231: =(F231-F230)/F230 -> 0.021855151 | I231: Market Beta | J231: 1 | L231: Beta 3 | M231: SUMMARY OUTPUT
B232: 45439 | C232: 586.56 | D232: =(C232-C231)/C231 -> -0.013986014 | F232: 22530.7 | G232: =(F232-F231)/F231 -> -0.018573775 | I232: Market Beta Weight | J232: 0.25
B233: 45446 | C233: 643.14 | D233: =(C233-C232)/C232 -> 0.09646072 | F233: 23290.15 | G233: =(F233-F232)/F232 -> 0.033707342 | I233: Adjusted Beta | J233: =(J229*J230)+(J231*J232) -> 0.66091889 | M233: Regression Statistics
B234: 45453 | C234: 610 | D234: =(C234-C233)/C233 -> -0.051528439 | F234: 23465.6 | G234: =(F234-F233)/F233 -> 0.0075332276 | M234: Multiple R | N234: 0.35890977
B235: 45460 | C235: 600.59 | D235: =(C235-C234)/C234 -> -0.01542623 | F235: 23501.1 | G235: =(F235-F234)/F234 -> 0.0015128529 | M235: R Square | N235: 0.12881622
B236: 45467 | C236: 603.74 | D236: =(C236-C235)/C235 -> 0.0052448426 | F236: 24010.6 | G236: =(F236-F235)/F235 -> 0.021679836 | M236: Adjusted R Square | N236: 0.12035813
B237: 45474 | C237: 606.06 | D237: =(C237-C236)/C236 -> 0.0038427138 | F237: 24323.85 | G237: =(F237-F236)/F236 -> 0.013046321 | M237: Standard Error | N237: 0.026869749
B238: 45481 | C238: 640.28 | D238: =(C238-C237)/C237 -> 0.056463056 | F238: 24502.15 | G238: =(F238-F237)/F237 -> 0.0073302541 | M238: Observations | N238: 105
B239: 45488 | C239: 658.55 | D239: =(C239-C238)/C238 -> 0.028534391 | F239: 24530.9 | G239: =(F239-F238)/F238 -> 0.0011733664
B240: 45495 | C240: 669.49 | D240: =(C240-C239)/C239 -> 0.016612254 | F240: 24834.85 | G240: =(F240-F239)/F239 -> 0.012390495 | M240: ANOVA
B241: 45509 | C241: 643.14 | D241: =(C241-C240)/C240 -> -0.039358318 | F241: 24717.7 | G241: =(F241-F240)/F240 -> -0.0047171616 | N241: df | O241: SS | P241: MS | Q241: F | R241: Significance F
B242: 45509 | C242: 652.4 | D242: =(C242-C241)/C241 -> 0.014398109 | F242: 24367.5 | G242: =(F242-F241)/F241 -> -0.014167985 | M242: Regression | N242: 1 | O242: 0.010995759 | P242: 0.010995759 | Q242: 15.229933 | R242: 0.00017006257
B243: 45516 | C243: 651.07 | D243: =(C243-C242)/C242 -> -0.0020386266 | F243: 24541.15 | G243: =(F243-F242)/F242 -> 0.0071262953 | M243: Residual | N243: 103 | O243: 0.07436429 | P243: 0.0007219834
B244: 45523 | C244: 667.96 | D244: =(C244-C243)/C243 -> 0.025941911 | F244: 24823.15 | G244: =(F244-F243)/F243 -> 0.011490904 | M244: Total | N244: 104 | O244: 0.085360049
B245: 45530 | C245: 637.38 | D245: =(C245-C244)/C244 -> -0.045781185 | F245: 25235.9 | G245: =(F245-F244)/F244 -> 0.016627624
B246: 45537 | C246: 655.2 | D246: =(C246-C245)/C245 -> 0.027958204 | F246: 24852.15 | G246: =(F246-F245)/F245 -> -0.015206511 | N246: Coefficients | O246: Standard Error | P246: t Stat | Q246: P-value | R246: Lower 95% | S246: Upper 95% | T246: Lower 95.0% | U246: Upper 95.0%
B247: 45544 | C247: 671.65 | D247: =(C247-C246)/C246 -> 0.025106838 | F247: 25356.5 | G247: =(F247-F246)/F246 -> 0.020294019 | M247: Intercept | N247: 0.0034226526 | O247: 0.0026235245 | P247: 1.304601 | Q247: 0.19493621 | R247: -0.0017804894 | S247: 0.0086257947 | T247: -0.0017804894 | U247: 0.0086257947
B248: 45551 | C248: 698.29 | D248: =(C248-C247)/C247 -> 0.039663515 | F248: 25790.95 | G248: =(F248-F247)/F247 -> 0.017133674 | M248: X Variable 1 | N248: 0.5419145 | O248: 0.13886148 | P248: 3.9025547 | Q248: 0.00017006257 | R248: 0.26651552 | S248: 0.81731349 | T248: 0.26651552 | U248: 0.81731349
B249: 45558 | C249: 681.99 | D249: =(C249-C248)/C248 -> -0.023342737 | F249: 26178.95 | G249: =(F249-F248)/F248 -> 0.015044037
B250: 45565 | C250: 679.78 | D250: =(C250-C249)/C249 -> -0.0032405167 | F250: 25014.6 | G250: =(F250-F249)/F249 -> -0.044476574
B251: 45572 | C251: 675.15 | D251: =(C251-C250)/C250 -> -0.0068110271 | F251: 24964.25 | G251: =(F251-F250)/F250 -> -0.0020128245
B252: 45579 | C252: 659.19 | D252: =(C252-C251)/C251 -> -0.023639191 | F252: 24854.05 | G252: =(F252-F251)/F251 -> -0.0044143125
B253: 45586 | C253: 630.43 | D253: =(C253-C252)/C252 -> -0.043629303 | F253: 24180.8 | G253: =(F253-F252)/F252 -> -0.027088141
B254: 45593 | C254: 636.2 | D254: =(C254-C253)/C253 -> 0.0091524832 | F254: 24304.35 | G254: =(F254-F253)/F253 -> 0.0051094257
B255: 45600 | C255: 620.34 | D255: =(C255-C254)/C254 -> -0.024929268 | F255: 24148.2 | G255: =(F255-F254)/F254 -> -0.0064247758
B256: 45607 | C256: 583.31 | D256: =(C256-C255)/C255 -> -0.059693072 | F256: 23532.7 | G256: =(F256-F255)/F255 -> -0.025488442
B257: 45614 | C257: 590.1 | D257: =(C257-C256)/C256 -> 0.011640466 | F257: 23907.25 | G257: =(F257-F256)/F256 -> 0.015916151
B258: 45621 | C258: 635.21 | D258: =(C258-C257)/C257 -> 0.07644467 | F258: 24131.1 | G258: =(F258-F257)/F257 -> 0.0093632685
...

Sheet Intrinsic Growth
B2: Calculation for ROIC | G2: 44256 | H2: 44621 | I2: 44986 | J2: 45352 | K2: 45717
B4: Current Assets
B5: ='Raw FS'!B33 -> Inventories | G5: ='Raw FS'!C33 -> 2248 | H5: ='Raw FS'!D33 -> 2743 | I5: ='Raw FS'!E33 -> 3243 | J5: ='Raw FS'!F33 -> 3927 | K5: ='Raw FS'!G33 -> 5044
B6: ='Raw FS'!B34 -> Trade receivables | G6: ='Raw FS'!C34 -> 44 | H6: ='Raw FS'!D34 -> 67 | I6: ='Raw FS'!E34 -> 62 | J6: ='Raw FS'!F34 -> 166 | K6: ='Raw FS'!G34 -> 154
B7: {='Raw FS'!B36:B37} -> Loans n Advances | G7: ='Raw FS'!C36 -> 81 | H7: ='Raw FS'!D36 -> 109 | I7: ='Raw FS'!E36 -> 97 | J7: ='Raw FS'!F36 -> 105 | K7: ='Raw FS'!G36 -> 126
B8: Other asset items | G8: ='Raw FS'!C37 -> 1806 | H8: ='Raw FS'!D37 -> 1859 | I8: ='Raw FS'!E37 -> 922 | J8: ='Raw FS'!F37 -> 1879 | K8: ='Raw FS'!G37 -> 1321
B9: Total Current Assets | G9: =SUM(G5:G8) -> 4179 | H9: =SUM(H5:H8) -> 4778 | I9: =SUM(I5:I8) -> 4324 | J9: =SUM(J5:J8) -> 6077 | K9: =SUM(K5:K8) -> 6645
B11: Current Liabilities
B12: ='Raw FS'!B13 -> Trade Payables | G12: ='Raw FS'!C13 -> 578 | H12: ='Raw FS'!D13 -> 589 | I12: ='Raw FS'!E13 -> 754 | J12: ='Raw FS'!F13 -> 985 | K12: ='Raw FS'!G13 -> 1071
B13: ='Raw FS'!B14 -> Other liability items | G13: ='Raw FS'!C14 -> 500 | H13: ='Raw FS'!D14 -> 557 | I13: ='Raw FS'!E14 -> 629 | J13: ='Raw FS'!F14 -> 898 | K13: ='Raw FS'!G14 -> 996
B14: Total Current Liabilities | G14: =SUM(G12:G13) -> 1078 | H14: =SUM(H12:H13) -> 1146 | I14: =SUM(I12:I13) -> 1383 | J14: =SUM(J12:J13) -> 1883 | K14: =SUM(K12:K13) -> 2067
A16: # | B16: Net Working Capital | G16: =G9-G14 -> 3101 | H16: =H9-H14 -> 3632 | I16: =I9-I14 -> 2941 | J16: =J9-J14 -> 4194 | K16: =K9-K14 -> 4578
B18: Non - Current Assets
B19: ='Raw FS'!B19 -> Land | G19: ='Raw FS'!C19 -> 3483 | H19: ='Raw FS'!D19 -> 4527 | I19: ='Raw FS'!E19 -> 5519 | J19: ='Raw FS'!F19 -> 6904 | K19: ='Raw FS'!G19 -> 8595
B20: ='Raw FS'!B20 -> Building | G20: ='Raw FS'!C20 -> 3649 | H20: ='Raw FS'!D20 -> 4938 | I20: ='Raw FS'!E20 -> 6201 | J20: ='Raw FS'!F20 -> 7062 | K20: ='Raw FS'!G20 -> 8256
B21: ='Raw FS'!B21 -> Plant Machinery | G21: ='Raw FS'!C21 -> 352 | H21: ='Raw FS'!D21 -> 491 | I21: ='Raw FS'!E21 -> 656 | J21: ='Raw FS'!F21 -> 870 | K21: ='Raw FS'!G21 -> 1141
B22: ='Raw FS'!B22 -> Equipments | G22: ='Raw FS'!C22 -> 50 | H22: ='Raw FS'!D22 -> 73 | I22: ='Raw FS'!E22 -> 85 | J22: ='Raw FS'!F22 -> 97 | K22: ='Raw FS'!G22 -> 115
B23: ='Raw FS'!B23 -> Computers | G23: ='Raw FS'!C23 -> 119 | H23: ='Raw FS'!D23 -> 153 | I23: ='Raw FS'!E23 -> 190 | J23: ='Raw FS'!F23 -> 219 | K23: ='Raw FS'!G23 -> 276
B24: ='Raw FS'!B24 -> Furniture n fittings | G24: ='Raw FS'!C24 -> 581 | H24: ='Raw FS'!D24 -> 772 | I24: ='Raw FS'!E24 -> 968 | J24: ='Raw FS'!F24 -> 1205 | K24: ='Raw FS'!G24 -> 1515
B25: ='Raw FS'!B25 -> Vehicles | G25: ='Raw FS'!C25 -> 4 | H25: ='Raw FS'!D25 -> 3 | I25: ='Raw FS'!E25 -> 15 | J25: ='Raw FS'!F25 -> 17 | K25: ='Raw FS'!G25 -> 6
B26: ='Raw FS'!B26 -> Intangible Assets | G26: ='Raw FS'!C26 -> 78 | H26: ='Raw FS'!D26 -> 78 | I26: ='Raw FS'!E26 -> 78 | J26: ='Raw FS'!F26 -> 78 | K26: ='Raw FS'!G26 -> 78
B27: ='Raw FS'!B27 -> Other fixed assets | G27: ='Raw FS'!C27 -> 81 | H27: ='Raw FS'!D27 -> 91 | I27: ='Raw FS'!E27 -> 105 | J27: ='Raw FS'!F27 -> 119 | K27: ='Raw FS'!G27 -> 124
B28: ='Raw FS'!B28 -> Gross Block | G28: =SUM(G19:G27) -> 8397 | H28: =SUM(H19:H27) -> 11126 | I28: =SUM(I19:I27) -> 13817 | J28: =SUM(J19:J27) -> 16571 | K28: =SUM(K19:K27) -> 20106
B29: CWIP | G29: ='Raw FS'!C30 -> 1020 | H29: ='Raw FS'!D30 -> 1129 | I29: ='Raw FS'!E30 -> 829 | J29: ='Raw FS'!F30 -> 935 | K29: ='Raw FS'!G30 -> 1099
B30: ='Raw FS'!B29 -> Accumulated Depreciation | G30: ='Raw FS'!C29 -> 1387 | H30: ='Raw FS'!D29 -> 1867 | I30: ='Raw FS'!E29 -> 2476 | J30: ='Raw FS'!F29 -> 3156 | K30: ='Raw FS'!G29 -> 3900
A31: # | B31: Net Non - Current Assets | G31: =G28+G29-G30 -> 8030 | H31: =H28+H29-H30 -> 10388 | I31: =I28+I29-I30 -> 12170 | J31: =J28+J29-J30 -> 14350 | K31: =K28+K29-K30 -> 17305
A33: # | B33: Invested Capital | G33: =G31+G16 -> 11131 | H33: =H31+H16 -> 14020 | I33: =I31+I16 -> 15111 | J33: =J31+J16 -> 18544 | K33: =K31+K16 -> 21883
B34: EBIT | G34: =HistoricalFS!G24 -> 10552 | H34: =HistoricalFS!H24 -> 11766 | I34: =HistoricalFS!I24 -> 13010 | J34: =HistoricalFS!J24 -> 13443 | K34: =HistoricalFS!K24 -> 13488
A36: # | B36: ROIC | G36: =G34/G33 -> 0.94798311 | H36: =H34/H33 -> 0.83922967 | I36: =I34/I33 -> 0.86096221 | J36: =J34/J33 -> 0.7249245 | K36: =K34/K33 -> 0.61636887
A39: # | B39: Calculation for Reinvestment Rate | G39: 44621 | H39: 44986 | I39: 45352 | J39: 45717 | K39: 46082
B41: Net Capex | G41: =-SUM(HistoricalFS!G83:G84) -> 2027 | H41: =-SUM(HistoricalFS!H83:H84) -> 2389 | I41: =-SUM(HistoricalFS!I83:I84) -> 2207 | J41: =-SUM(HistoricalFS!J83:J84) -> 2722 | K41: =-SUM(HistoricalFS!K83:K84) -> 3417
B42: Change in Working Capital | G42: - | H42: =H16-G16 -> 531 | I42: =I16-H16 -> -691 | J42: =J16-I16 -> 1253 | K42: =K16-J16 -> 384
B44: EBIT | G44: =G34 -> 10552 | H44: =H34 -> 11766 | I44: =I34 -> 13010 | J44: =J34 -> 13443 | K44: =K34 -> 13488
B45: Marginal Tax Rate | G45: 0.26 | H45: 0.26 | I45: 0.26 | J45: 0.26 | K45: 0.26
B46: EBIT(1-T) | G46: =G44*(1-G45) -> 7808.48 | H46: =H44*(1-H45) -> 8706.84 | I46: =I44*(1-I45) -> 9627.4 | J46: =J44*(1-J45) -> 9947.82 | K46: =K44*(1-K45) -> 9981.12
B48: Reinvestment | G48: - | H48: =SUM(H41:H42) -> 2920 | I48: =SUM(I41:I42) -> 1516 | J48: =SUM(J41:J42) -> 3975 | K48: =SUM(K41:K42) -> 3801
A49: # | B49: Reinvestment Rate | H49: =H48/H46 -> 0.33536851 | I49: =I48/I46 -> 0.15746723 | J49: =J48/J46 -> 0.39958503 | K49: =K48/K46 -> 0.38081899
I50: 4 Year Average | K50: =AVERAGE(H49:K49) -> 0.31830994
I51: 4 Year Median | K51: =MEDIAN(H49:K49) -> 0.35809375
A54: # | B54: Calculation for Growth Rate | G54: 44621 | H54: 44986 | I54: 45352 | J54: 45717 | K54: 46082
B56: Reinvestment Rate | G56: =G48 -> - | H56: =H49 -> 0.33536851 | I56: =I49 -> 0.15746723 | J56: =J49 -> 0.39958503 | K56: =K49 -> 0.38081899
B57: ROIC | G57: =G36 -> 0.94798311 | H57: =H36 -> 0.83922967 | I57: =I36 -> 0.86096221 | J57: =J36 -> 0.7249245 | K57: =K36 -> 0.61636887
A59: # | B59: Intrinsic Growth | G59: - | H59: =H57*H56 -> 0.28145121 | I59: =I57*I56 -> 0.13557333 | J59: =J57*J56 -> 0.28966898 | K59: =K57*K56 -> 0.23472497
I60: 3 Year Average | K60: =AVERAGE(H59:K59) -> 0.23535462
I61: 3 Year Median | K61: =MEDIAN(H59:K59) -> 0.25808809
B336: 46146

Sheet RM
B2: Return on Markets (NIFTY)
B4: Date | C4: Annualized
B5: 2000 | C5: -0.1465 | E5: Average Return | F5: =AVERAGE(C5:C30) -> 0.15149231
B6: 2001 | C6: -0.1618 | E6: Equity Risk Premium | F6: =F5-WACC!J22 -> 0.081652308
B7: 2002 | C7: 0.0325
B8: 2003 | C8: 0.719
B9: 2004 | C9: 0.1068
B10: 2005 | C10: 0.3634
B11: 2006 | C11: 0.3983
B12: 2007 | C12: 0.5477
B13: 2008 | C13: -0.5179
B14: 2009 | C14: 0.7576
B15: 2010 | C15: 0.1795
B16: 2011 | C16: -0.2462
B17: 2012 | C17: 0.277
B18: 2013 | C18: 0.0676
... B30: 2025 | C30: 0.1051
B335: 46146

Sheet Football Field
M2: Football Field Analysis
N3: OpenLow | O3: Low | P3: OpenHigh | Q3: High
M4: Comps | N4: ='Comps Val'!O27 -> 2065.95 | O4: 2065.95 | P4: ='Comps Val'!Q27 -> 11537.205 | Q4: 11537.205
M5: DCF Bear | N5: =DCF!J22 -> 741.13878 | O5: 741.13878 | P5: =DCF!J25 -> 849.88411 | Q5: 849.88411
M6: DCF Base | N6: =DCF!I22 -> 815.2555 | O6: 815.2555 | P6: =DCF!I25 -> 952.30926 | Q6: 952.30926
M7: DCF Bull | N7: =DCF!G22 -> 1132.4401 | O7: 1132.4401 | P7: =DCF!G25 -> 1438.9674 | Q7: 1438.9674
M8: 52W H/L | N8: 2022.5 | O8: 2022.5 | P8: 2750 | Q8: 2750

Sheet Comps Val
B2: Comparable Company Valuation
D4: Market Data | K4: Financials | O4: Valuation
B5: Company | C5: Ticker | D5: Share Price | E5: Shares Outstanding | F5: Equity Value | G5: Net Debt | H5: Enterprise Value | K5: Revenue | L5: EBITDA | M5: Net Income | O5: EV/Revenue | P5: EV/EBITDA | Q5: P/E
B7: Hindustan Unilever | C7: ='Data Sheet Relative Valuation'!D3 -> HINDUNILVR | D7: ='Data Sheet Relative Valuation'!E3 -> 2256.3 | E7: ='Data Sheet Relative Valuation'!F3 -> 234.96 | F7: ='Data Sheet Relative Valuation'!G3 -> 530138.31 | G7: ='Data Sheet Relative Valuation'!H3 -> 1478 | H7: ='Data Sheet Relative Valuation'!J3 -> 528368.31 | K7: ='Data Sheet Relative Valuation'!L3 -> 64468 | L7: ='Data Sheet Relative Valuation'!M3 -> 15790 | M7: ='Data Sheet Relative Valuation'!N3 -> 15059 | O7: =$H7/K7 -> 8.1958229 | P7: =$H7/L7 -> 33.462211 | Q7: =F7/M7 -> 35.204085
B8: Nestle India | C8: ='Data Sheet Relative Valuation'!D4 -> NESTLEIND | D8: ='Data Sheet Relative Valuation'!E4 -> 1466 | E8: ='Data Sheet Relative Valuation'!F4 -> 192.83 | F8: ='Data Sheet Relative Valuation'!G4 -> 282690.9 | G8: ='Data Sheet Relative Valuation'!H4 -> 444.16 | H8: ='Data Sheet Relative Valuation'!J4 -> 281794.19 | K8: ='Data Sheet Relative Valuation'!L4 -> 23154.6 | L8: ='Data Sheet Relative Valuation'!M4 -> 5346.41 | M8: ='Data Sheet Relative Valuation'!N4 -> 3544.6 | O8: =H8/K8 -> 12.170117 | P8: =$H8/L8 -> 52.707179 | Q8: =F8/M8 -> 79.752553
B9: Marico | C9: ='Data Sheet Relative Valuation'!D5 -> MARICO | D9: ='Data Sheet Relative Valuation'!E5 -> 838.35 | E9: ='Data Sheet Relative Valuation'!F5 -> 129.81 | F9: ='Data Sheet Relative Valuation'!G5 -> 108830.28 | G9: ='Data Sheet Relative Valuation'!H5 -> 557 | H9: ='Data Sheet Relative Valuation'!J5 -> 108894.28 | K9: ='Data Sheet Relative Valuation'!L5 -> 13611 | L9: ='Data Sheet Relative Valuation'!M5 -> 2532 | M9: ='Data Sheet Relative Valuation'!N5 -> 1813 | O9: =H9/K9 -> 8.0004614 | P9: =$H9/L9 -> 43.00722 | Q9: =F9/M9 -> 60.027733
B10: Godrej Consumer Products | C10: ='Data Sheet Relative Valuation'!D6 -> GODREJCP | D10: ='Data Sheet Relative Valuation'!E6 -> 1023.45 | E10: ='Data Sheet Relative Valuation'!F6 -> 102.32 | F10: ='Data Sheet Relative Valuation'!G6 -> 104723.99 | G10: ='Data Sheet Relative Valuation'!H6 -> 4415.81 | H10: ='Data Sheet Relative Valuation'!J6 -> 108134.39 | K10: ='Data Sheet Relative Valuation'!L6 -> 15177.9 | L10: ='Data Sheet Relative Valuation'!M6 -> 3422.41 | M10: ='Data Sheet Relative Valuation'!N6 -> 1861.47 | O10: =H10/K10 -> 7.1244632 | P10: =$H10/L10 -> 31.595978 | Q10: =F10/M10 -> 56.258758
B11: Dabur India | C11: ='Data Sheet Relative Valuation'!D7 -> DABUR | D11: ='Data Sheet Relative Valuation'!E7 -> 460.15 | E11: ='Data Sheet Relative Valuation'!F7 -> 177.37 | F11: ='Data Sheet Relative Valuation'!G7 -> 81616.35 | G11: ='Data Sheet Relative Valuation'!H7 -> 1287.32 | H11: ='Data Sheet Relative Valuation'!J7 -> 82341.6 | K11: ='Data Sheet Relative Valuation'!L7 -> 13192.57 | L11: ='Data Sheet Relative Valuation'!M7 -> 3049.81 | M11: ='Data Sheet Relative Valuation'!N7 -> 1868.69 | O11: =H11/K11 -> 6.2415132 | P11: =$H11/L11 -> 26.998928 | Q11: =F11/M11 -> 43.675703
B12: Emami | C12: ='Data Sheet Relative Valuation'!D8 -> EMAMILTD | D12: ='Data Sheet Relative Valuation'!E8 -> 426.85 | E12: ='Data Sheet Relative Valuation'!F8 -> 43.65 | F12: ='Data Sheet Relative Valuation'!G8 -> 18632.01 | G12: ='Data Sheet Relative Valuation'!H8 -> 71.96 | H12: ='Data Sheet Relative Valuation'!J8 -> 18431.07 | K12: ='Data Sheet Relative Valuation'!L8 -> 3817.46 | L12: ='Data Sheet Relative Valuation'!M8 -> 1043.04 | M12: ='Data Sheet Relative Valuation'!N8 -> 802.75 | O12: =H12/K12 -> 4.8280977 | P12: =$H12/L12 -> 17.67053 | Q12: =F12/M12 -> 23.210227
B14: High | O14: =MAX(O7:O12) -> 12.170117 | P14: =MAX(P7:P12) -> 52.707179 | Q14: =MAX(Q7:Q12) -> 79.752553
B15: 75th Percentile | O15: =QUARTILE(O7:O12,3) -> 8.1469825 | P15: =QUARTILE(P7:P12,3) -> 40.620967 | Q15: =QUARTILE(Q7:Q12,3) -> 59.085489
B16: Average | O16: =AVERAGE(O7:O12) -> 7.7600792 | P16: =AVERAGE(P7:P12) -> 34.240341 | Q16: =AVERAGE(Q7:Q12) -> 49.688177
B17: Median | O17: =MEDIAN(O7:O12) -> 7.5624623 | P17: =MEDIAN(P7:P12) -> 32.529094 | Q17: =MEDIAN(Q7:Q12) -> 49.967231
B18: 25th Percentile | O18: =QUARTILE(O7:O12,1) -> 6.4622507 | P18: =QUARTILE(P7:P12,1) -> 28.14819 | Q18: =QUARTILE(Q7:Q12,1) -> 37.321989
B19: Low | O19: =MIN(O7:O12) -> 4.8280977 | P19: =MIN(P7:P12) -> 17.67053 | Q19: =MIN(Q7:Q12) -> 23.210227
B21: Hindustan Unilever Comparable Valuation | O21: EV/Revenue | P21: EV/EBITDA | Q21: P/E
B23: Implied Enteprise Value | O23: =O17*K7 -> 487536.82 | P23: =P17*L7 -> 513634.4 | Q23: =Q24+Q25 -> 754577.74
B24: Net Debt | O24: 2121.21 | P24: 2121.21 | Q24: 2121.21
B25: Implied Market Value | O25: =O23-O24 -> 485415.61 | P25: =P23-P24 -> 511513.19 | Q25: =Q17*M7 -> 752456.53
B26: Shares Outstanding | O26: =E7 -> 234.96 | P26: 65.22 | Q26: 65.22
B27: Implied Value Per Share | O27: =O25/O26 -> 2065.95 | P27: =P25/P26 -> 7842.8885 | Q27: =Q25/Q26 -> 11537.205
B29: Source :- The Valuation School, Screener.in, Yahoo Finance
B335: 46146

Sheet Data>
B335: 46146

Sheet Data Sheet
A1: COMPANY NAME | B1: HINDUSTAN UNILEVER LTD | E1: =IF(B2<>B3, "A NEW VERSION OF THE WORKSHEET IS AVAILABLE", "")
A2: LATEST VERSION | B2: 2.1 | E2: PLEASE DO NOT MAKE ANY CHANGES TO THIS SHEET
A3: CURRENT VERSION | B3: 2.1
A5: META
A6: Number of shares | B6: =IF(B9>0, B9/B8, 0) -> 234.94894
A7: Face Value | B7: 1
A8: Current Price | B8: 2262
A9: Market Capitalization | B9: 531454.51
A15: PROFIT & LOSS
A16: Report Date | B16: 42825 | C16: 43190 | D16: 43555 | E16: 43921 | F16: 44286 | G16: 44651 | H16: 45016 | I16: 45382 | J16: 45747
A17: Sales | B17: 33162 | C17: 35545 | D17: 39310 | E17: 39783 | F17: 47028 | G17: 52446 | H17: 60580 | I17: 61896 | J17: 63121
A18: Raw Material Cost | B18: 13606 | C18: 14233 | D18: 15845 | E18: 15697 | F18: 20141 | G18: 22871 | H18: 28427 | I18: 26822 | J18: 27344
A19: Change in Inventory | B19: -144 | C19: 72 | D19: -12 | E19: 108 | F19: 405 | G19: 22 | H19: 75 | I19: 11 | J19: 153
A20: Power and Fuel | B20: 295 | C20: 295 | D20: 308 | E20: 299 | F20: 339 | G20: 318 | H20: 384 | I20: 446 | J20: 427
A21: Other Mfr. Exp | B21: 2887 | C21: 2998 | D21: 3041 | E21: 2906 | F21: 2868 | G21: 3354 | H21: 3791 | I21: 3385 | J21: 3834
A22: Employee Cost | B22: 1743 | C22: 1860 | D22: 1875 | E22: 1820 | F22: 2358 | G22: 2545 | H22: 2854 | I22: 3009 | J22: 3077
A23: Selling and admin | B23: 6689 | C23: 7252 | D23: 7796 | E23: 7620 | F23: 7906 | G23: 8164 | H23: 8785 | I23: 10780 | J23: 10693
A24: Other Expenses | B24: 1470 | C24: 1480 | D24: 1553 | E24: 1688 | F24: 2195 | G24: 2359 | H24: 2267 | I24: 2806 | J24: 3056
A25: Other Income | B25: 606 | C25: 353 | D25: 322 | E25: 424 | F25: 170 | G25: 219 | H25: 448 | I25: 817 | J25: 1322
A26: Depreciation | B26: 432 | C26: 520 | D26: 565 | E26: 1002 | F26: 1074 | G26: 1091 | H26: 1137 | I26: 1216 | J26: 1355
A27: Interest | B27: 35 | C27: 26 | D27: 33 | E27: 118 | F27: 117 | G27: 106 | H27: 114 | I27: 334 | J27: 395
... A31: Dividend Amount | B31: 3672 | C31: 4320 | D31: 4752 | E31: 5400 | F31: 9517.5 | G31: 7990 | H31: 9165 | I31: 9870 | J31: 12455
A40: Quarters
A41: Report Date | B41: 45291 | C41: 45382 | D41: 45473 | E41: 45565 | F41: 45657 | G41: 45747 | H41: 45838 | I41: 45930 | J41: 46022
A42: Sales | B42: 15567 | C42: 15210 | D42: 15707 | E42: 15926 | F42: 15556 | G42: 15190 | H42: 16514 | I42: 15919 | J42: 16441
A43: Expenses | B43: 11902 | C43: 11675 | D43: 11965 | E43: 12139 | F43: 11867 | G43: 11572 | H43: 12797 | I43: 12137 | J43: 12660
A44: Other Income | B44: 184 | C44: 309 | D44: 209 | E44: 203 | F44: 733 | G44: 149 | H44: 74 | I44: 269 | J44: 4048
A45: Depreciation | B45: 313 | C45: 320 | D45: 329 | E45: 338 | F45: 318 | G45: 318 | H45: 361 | I45: 322 | J45: 337
A46: Interest | B46: 91 | C46: 105 | D46: 93 | E46: 110 | F46: 109 | G46: 77 | H46: 127 | I46: 124 | J46: 88
A47: Profit before tax | B47: 3445 | C47: 3419 | D47: 3529 | E47: 3542 | F47: 3995 | G47: 3372 | H47: 3303 | I47: 3605 | J47: 7404
A48: Tax | B48: 937 | C48: 858 | D48: 917 | E48: 947 | F48: 1006 | G48: 897 | H48: 535 | I48: 911 | J48: 801
A49: Net profit | B49: 2509 | C49: 2558 | D49: 2610 | E49: 2591 | F49: 2984 | G49: 2464 | H49: 2756 | I49: 2685 | J49: 6607
A50: Operating Profit | B50: 3665 | C50: 3535 | D50: 3742 | E50: 3787 | F50: 3689 | G50: 3618 | H50: 3717 | I50: 3782 | J50: 3781
A55: BALANCE SHEET
A56: Report Date | B56: 42825 | C56: 43190 | D56: 43555 | E56: 43921 | F56: 44286 | G56: 44651 | H56: 45016 | I56: 45382 | J56: 45747
A57: Equity Share Capital | B57: 216 | C57: 216 | D57: 216 | E57: 216 | F57: 235 | G57: 235 | H57: 235 | I57: 235 | J57: 235
A58: Reserves | B58: 6528 | C58: 7065 | D58: 7651 | E58: 8013 | F58: 47439 | G58: 48826 | H58: 50069 | I58: 50983 | J58: 49167
A59: Borrowings | B59: 277 | D59: 99 | G59: 1043 | H59: 1219 | I59: 1484 | J59: 1648
A60: Other Liabilities | B60: 8685 | C60: 10581 | D60: 10663 | E60: 11924 | F60: 21066 | G60: 20402 | H60: 21554 | I60: 25787 | J60: 28813
A61: Total | B61: 15706 | C61: 17862 | D61: 18629 | E61: 20153 | F61: 68740 | G61: 70506 | H61: 73077 | I61: 78489 | J61: 79863
A62: Net Block | B62: 4419 | C62: 4528 | D62: 4715 | E62: 5479 | F62: 51443 | G62: 51473 | H62: 52678 | I62: 53744 | J62: 54335
A63: Capital Work in Progress | B63: 229 | C63: 461 | D63: 406 | E63: 597 | F63: 745 | G63: 1313 | H63: 1132 | I63: 1025 | J63: 1009
A64: Investments | B64: 3794 | C64: 2873 | D64: 2716 | E64: 1255 | F64: 2709 | G64: 3521 | H64: 2882 | I64: 4625 | J64: 3810
A65: Other Assets | B65: 7264 | C65: 10000 | D65: 10792 | E65: 12822 | F65: 13843 | G65: 14199 | H65: 16385 | I65: 19095 | J65: 20709
A66: Total | B66: 15706 | C66: 17862 | D66: 18629 | E66: 20153 | F66: 68740 | G66: 70506 | H66: 73077 | I66: 78489 | J66: 79863
A67: Receivables | B67: 1085 | C67: 1310 | D67: 1816 | E67: 1149 | F67: 1758 | G67: 2236 | H67: 3079 | I67: 2997 | J67: 3819
A68: Inventory | B68: 2541 | C68: 2513 | D68: 2574 | E68: 2767 | F68: 3579 | G68: 4096 | H68: 4251 | I68: 4022 | J68: 4415
A69: Cash & Bank | B69: 1828 | C69: 3485 | D69: 3757 | E69: 5113 | F69: 4471 | G69: 3846 | H69: 4678 | I69: 7559 | J69: 7554
A70: No. of Equity Shares | B70: 2164349639 | C70: 2164528777 | D70: 2164704405 | E70: 2164704405 | F70: 2349567819 | G70: 2349591262 | H70: 2349591262 | I70: 2349591262 | J70: 2349591262
A71: New Bonus Shares
A72: Face value | B72: 1 | C72: 1 | D72: 1 | E72: 1 | F72: 1 | G72: 1 | H72: 1 | I72: 1 | J72: 1
A80: CASH FLOW:
A81: Report Date | B81: 42825 | C81: 43190 | D81: 43555 | E81: 43921 | F81: 44286 | G81: 44651 | H81: 45016 | I81: 45382 | J81: 45747
A82: Cash from Operating Activity | B82: 5185 | C82: 6059 | D82: 5800 | E82: 7623 | F82: 9163 | G82: 9048 | H82: 9991 | I82: 15469 | J82: 11886
A83: Cash from Investing Activity | B83: -1173 | C83: -1063 | D83: -438 | E83: 1791 | F83: -1228 | G83: -1728 | H83: -1484 | I83: -5324 | J83: 6473
A84: Cash from Financing Activity | B84: -4214 | C84: -4975 | D84: -5390 | E84: -6819 | F84: -9309 | G84: -8015 | H84: -8953 | I84: -10034 | J84: -13101
A85: Net Cash Flow | B85: -202 | C85: 21 | D85: -28 | E85: 2595 | F85: -1374 | G85: -695 | H85: -446 | I85: 111 | J85: 5258
A90: PRICE: | B90: 872.61 | C90: 1276.11 | D90: 1633.53 | E90: 2199.83 | F90: 2327.12 | G90: 1960.7 | H90: 2450.44 | I90: 2167.14 | J90: 2161.88
A92: DERIVED:
A93: Adjusted Equity Shares in Cr | B93: 216.43 | C93: 216.45 | D93: 216.47 | E93: 216.48 | F93: 234.96 | G93: 234.96 | H93: 234.96 | I93: 234.96 | J93: 234.96
B335: 46146

Sheet Raw FS
B2: Particulars | C2: 44256 | D2: 44621 | E2: 44986 | F2: 45352 | G2: 45717
B4: Equity Capital | C4: 648 | D4: 648 | E4: 648 | F4: 651 | G4: 651
B5: Reserves | C5: 11536 | D5: 13030 | E5: 15430 | F5: 18047 | G5: 20777
B6: Borrowings -
B7: Long term Borrowings | C7: 0 | D7: 0 | E7: 0 | F7: 0 | G7: 0
B8: Short term Borrowings | C8: 0 | D8: 0 | E8: 0 | F8: 0 | G8: 0
B9: Lease Liabilities | C9: 393 | D9: 647 | E9: 643 | F9: 592 | G9: 820
B10: Other Borrowings | C10: 0 | D10: 0 | E10: 0 | F10: 0 | G10: 0
B11: Other Liabilities -
B12: Non controlling int | C12: 0 | D12: 0 | E12: 0 | F12: 0 | G12: -1
B13: Trade Payables | C13: 578 | D13: 589 | E13: 754 | F13: 985 | G13: 1071
B14: Other liability items | C14: 500 | D14: 557 | E14: 629 | F14: 898 | G14: 996
B16: Total Liabilities | C16: 13655 | D16: 15471 | E16: 18105 | F16: 21172 | G16: 24313
B18: Fixed Assets -
B19: Land | C19: 3483 | D19: 4527 | E19: 5519 | F19: 6904 | G19: 8595
B20: Building | C20: 3649 | D20: 4938 | E20: 6201 | F20: 7062 | G20: 8256
B21: Plant Machinery | C21: 352 | D21: 491 | E21: 656 | F21: 870 | G21: 1141
B22: Equipments | C22: 50 | D22: 73 | E22: 85 | F22: 97 | G22: 115
B23: Computers | C23: 119 | D23: 153 | E23: 190 | F23: 219 | G23: 276
B24: Furniture n fittings | C24: 581 | D24: 772 | E24: 968 | F24: 1205 | G24: 1515
B25: Vehicles | C25: 4 | D25: 3 | E25: 15 | F25: 17 | G25: 6
B26: Intangible Assets | C26: 78 | D26: 78 | E26: 78 | F26: 78 | G26: 78
B27: Other fixed assets | C27: 81 | D27: 91 | E27: 105 | F27: 119 | G27: 124
B28: Gross Block | C28: 8396 | D28: 11127 | E28: 13816 | F28: 16571 | G28: 20106
B29: Accumulated Depreciation | C29: 1387 | D29: 1867 | E29: 2476 | F29: 3156 | G29: 3900
B30: CWIP | C30: 1020 | D30: 1129 | E30: 829 | F30: 935 | G30: 1099
B31: Investments | C31: 3 | D31: 6 | E31: 202 | F31: 107 | G31: 3
B32: Other Assets -
B33: Inventories | C33: 2248 | D33: 2743 | E33: 3243 | F33: 3927 | G33: 5044
B34: Trade receivables | C34: 44 | D34: 67 | E34: 62 | F34: 166 | G34: 154
B35: Cash Equivalents | C35: 1446 | D35: 299 | E35: 1408 | F35: 638 | G35: 358
B36: Loans n Advances | C36: 81 | D36: 109 | E36: 97 | F36: 105 | G36: 126
B37: Other asset items | C37: 1806 | D37: 1859 | E37: 922 | F37: 1879 | G37: 1321
B39: Total Assets | C39: 13655 | D39: 15471 | E39: 18105 | F39: 21172 | G39: 24313
B335: 46146

Sheet Cash Flow Data
C2: 42064 | D2: 42430 | E2: 42795 | F2: 43160 | G2: 43525 | H2: 43891 | I2: 44256 | J2: 44621 | K2: 44986 | L2: 45352 | M2: 45717 | N2: 46082
B3: Cash from Operating Activity - | C3: 222 | D3: 433 | E3: 455 | F3: 730 | G3: 807 | H3: 1280 | I3: 1375 | J3: 1372 | K3: 2630 | L3: 2746 | M3: 2463 | N3: 3467
B4: Profit from operations | C4: 474 | D4: 666 | E4: 984 | F4: 1375 | G4: 1659 | H4: 2149 | I4: 1764 | J4: 2515 | K4: 3659 | L4: 4131 | M4: 4535 | N4: 5233
B5: Receivables | C5: 2 | D5: -1 | E5: 54 | F5: -13 | G5: -31 | H5: 45 | I5: -24 | J5: -23 | K5: 5 | L5: -104 | M5: 13 | N5: 4
B6: Inventory | C6: -161 | D6: -132 | E6: -276 | F6: -212 | G6: -445 | H6: -339 | I6: -301 | J6: -494 | K6: -501 | L6: -684 | M6: -1117 | N6: -856
B7: Payables | C7: -4 | D7: 72 | E7: 0 | F7: 55 | G7: 146 | H7: -30 | I7: 145 | J7: 11 | K7: 165 | L7: 231 | M7: 86 | N7: 267
B8: Loans Advances | C8: -5 | D8: 0 | E8: 0 | F8: 0 | G8: 0 | H8: 0 | I8: 0 | J8: 0 | K8: 0 | L8: 0 | M8: 0 | N8: 0
B9: Operating investments | C9: 0 | D9: 0 | E9: -2 | F9: -62 | G9: 52 | H9: 2 | I9: 12 | J9: -3 | K9: 0 | L9: 0 | M9: 0 | N9: 0
B10: Other WC items | C10: 16 | D10: -7 | E10: -46 | F10: -11 | G10: -72 | H10: -54 | I10: 41 | J10: -73 | K10: 12 | L10: -87 | M10: -94 | N10: -114
B11: Working capital changes | C11: -152 | D11: -69 | E11: -270 | F11: -243 | G11: -351 | H11: -376 | I11: -127 | J11: -582 | K11: -320 | L11: -644 | M11: -1113 | N11: -699
B12: Direct taxes | C12: -100 | D12: -164 | E12: -258 | F12: -403 | G12: -502 | H12: -492 | I12: -262 | J12: -560 | K12: -709 | L12: -742 | M12: -959 | N12: -1068
B13: Cash from Investing Activity - | C13: -474 | D13: -633 | E13: -2482 | F13: 464 | G13: -958 | H13: -4657 | I13: -1110 | J13: -1289 | K13: -2313 | L13: -2468 | M13: -2185 | N13: -4207
B14: Fixed assets purchased | C14: -477 | D14: 0 | E14: -645 | F14: -916 | G14: -1417 | H14: -1712 | I14: -2029 | J14: -2410 | K14: -2212 | L14: -2731 | M14: -3423 | N14: -4113
... B36: CFO/OP | C36: 0.71 | D36: 0.9 | E36: 0.74 | F36: 0.84 | G36: 0.8 | H36: 0.83 | I36: 0.94 | J36: 0.77 | K36: 0.92 | L36: 0.85 | M36: 0.76 | N36: 0.87
B335: 46146

Sheet Data Sheet Beta
B1: Hindustan Unilver | E1: Nifty | H1: Nestle India | K1: Marico India | N1: GCPL | R1: Emami | V1: Dabur
B2: Date | C2: Adj Close | E2: Date | F2: Adj Close | H2: Date | I2: Adj Close | K2: Date | L2: Adj Close | N2: Date | O2: Adj Close | P2: Date | R2: Date | S2: Adj Close | V2: Date | W2: Adj Close
B3: 45425 | C3: 2236.9 | E3: 45425 | F3: 22466.1 | H3: 45425 | I3: 1227.05 | K3: 45425 | L3: 585.57 | N3: May 13, 2026 | O3: 1030.5 | P3: =DATE(RIGHT(N3,4),MATCH(LEFT(N3,3),{"Jan","Feb","Mar","Apr","May","Jun","Jul","Aug","Sep","Oct","Nov","Dec"},0),MID(N3,5,2)) -> 46155 | R3: May 13, 2026 | S3: 428.9 | T3: =DATE(RIGHT(R3,4),MATCH(LEFT(R3,3),{"Jan","Feb","Mar","Apr","May","Jun","Jul","Aug","Sep","Oct","Nov","Dec"},0),MID(R3,5,2)) -> 46155 | V3: May 13, 2026 | W3: 463.1 | X3: =DATE(RIGHT(V3,4),MATCH(LEFT(V3,3),{"Jan","Feb","Mar","Apr","May","Jun","Jul","Aug","Sep","Oct","Nov","Dec"},0),MID(V3,5,2)) -> 46155
B4: 45432 | C4: 2277.17 | E4: 45432 | F4: 22957.1 | H4: 45432 | I4: 1209.09 | K4: 45432 | L4: 594.88 | N4: May 11, 2026 | O4: 1025.1 | P4: =DATE(RIGHT(N4,4),MATCH(LEFT(N4,3),{"Jan","Feb","Mar","Apr","May","Jun","Jul","Aug","Sep","Oct","Nov","Dec"},0),MID(N4,5,2)) -> 46153 | R4: May 11, 2026 | S4: 432.4 | T4: =DATE(RIGHT(R4,4),MATCH(LEFT(R4,3),{"Jan","Feb","Mar","Apr","May","Jun","Jul","Aug","Sep","Oct","Nov","Dec"},0),MID(R4,5,2)) -> 46153 | V4: May 11, 2026 | W4: 473.25 | X4: =DATE(RIGHT(V4,4),MATCH(LEFT(V4,3),{"Jan","Feb","Mar","Apr","May","Jun","Jul","Aug","Sep","Oct","Nov","Dec"},0),MID(V4,5,2)) -> 46153
B5: 45439 | C5: 2238.72 | E5: 45439 | F5: 22530.7 | H5: 45439 | I5: 1153.8 | K5: 45439 | L5: 586.56 | N5: May 4, 2026 | O5: 1037.24 | P5: 46146 | R5: May 4, 2026 | S5: 456.95 | T5: 46146 | V5: May 4, 2026 | W5: 487.7 | X5: 46146
B6: 45446 | C6: 2477.82 | E6: 45446 | F6: 23290.15 | H6: 45446 | I6: 1226.09 | K6: 45446 | L6: 643.14 | N6: Apr 27, 2026 | O6: 1061.82 | P6: =DATE(RIGHT(N6,4),MATCH(LEFT(N6,3),{"Jan","Feb","Mar","Apr","May","Jun","Jul","Aug","Sep","Oct","Nov","Dec"},0),MID(N6,5,2)) -> 46139 | R6: Apr 27, 2026 | S6: 444.5 | T6: =DATE(RIGHT(R6,4),MATCH(LEFT(R6,3),{"Jan","Feb","Mar","Apr","May","Jun","Jul","Aug","Sep","Oct","Nov","Dec"},0),MID(R6,5,2)) -> 46139 | V6: Apr 27, 2026 | W6: 441.5 | X6: =DATE(RIGHT(V6,4),MATCH(LEFT(V6,3),{"Jan","Feb","Mar","Apr","May","Jun","Jul","Aug","Sep","Oct","Nov","Dec"},0),MID(V6,5,2)) -> 46139
B7: 45453 | C7: 2383.58 | E7: 45453 | F7: 23465.6 | H7: 45453 | I7: 1245.71 | K7: 45453 | L7: 610 | N7: Apr 20, 2026 | O7: 1084.51 | P7: =DATE(RIGHT(N7,4),MATCH(LEFT(N7,3),{"Jan","Feb","Mar","Apr","May","Jun","Jul","Aug","Sep","Oct","Nov","Dec"},0),MID(N7,5,2)) -> 46132 | R7: Apr 20, 2026 | S7: 460.15 | T7: =DATE(RIGHT(R7,4),MATCH(LEFT(R7,3),{"Jan","Feb","Mar","Apr","May","Jun","Jul","Aug","Sep","Oct","Nov","Dec"},0),MID(R7,5,2)) -> 46132 | V7: Apr 20, 2026 | W7: 451.1 | X7: =DATE(RIGHT(V7,4),MATCH(LEFT(V7,3),{"Jan","Feb","Mar","Apr","May","Jun","Jul","Aug","Sep","Oct","Nov","Dec"},0),MID(V7,5,2)) -> 46132
B8: 45460 | C8: 2369.48 | E8: 45460 | F8: 23501.1 | H8: 45460 | I8: 1224.11 | K8: 45460 | L8: 600.59 | N8: Apr 13, 2026 | O8: 1103.91 | P8: =DATE(RIGHT(N8,4),MATCH(LEFT(N8,3),{"Jan","Feb","Mar","Apr","May","Jun","Jul","Aug","Sep","Oct","Nov","Dec"},0),MID(N8,5,2)) -> 46125 | R8: Apr 13, 2026 | S8: 452.1 | T8: =DATE(RIGHT(R8,4),MATCH(LEFT(R8,3),{"Jan","Feb","Mar","Apr","May","Jun","Jul","Aug","Sep","Oct","Nov","Dec"},0),MID(R8,5,2)) -> 46125 | V8: Apr 13, 2026 | W8: 442.85 | X8: =DATE(RIGHT(V8,4),MATCH(LEFT(V8,3),{"Jan","Feb","Mar","Apr","May","Jun","Jul","Aug","Sep","Oct","Nov","Dec"},0),MID(V8,5,2)) -> 46125
B9: 45467 | C9: 2400.3 | E9: 45467 | F9: 24010.6 | H9: 45467 | I9: 1250.2 | K9: 45467 | L9: 603.74 | N9: Apr 6, 2026 | O9: 1072.77 | P9: 46118 | R9: Apr 6, 2026 | S9: 424.15 | T9: 46118 | V9: Apr 6, 2026 | W9: 435.7 | X9: 46118
B10: 45474 | C10: 2472.07 | E10: 45474 | F10: 24323.85 | H10: 45474 | I10: 1261.22 | K10: 45474 | L10: 606.06 | N10: Mar 30, 2026 | O10: 989.88 | P10: =DATE(RIGHT(N10,4),MATCH(LEFT(N10,3),{"Jan","Feb","Mar","Apr","May","Jun","Jul","Aug","Sep","Oct","Nov","Dec"},0),MID(N10,5,2)) -> 46111 | R10: Mar 30, 2026 | S10: 398.3 | T10: =DATE(RIGHT(R10,4),MATCH(LEFT(R10,3),{"Jan","Feb","Mar","Apr","May","Jun","Jul","Aug","Sep","Oct","Nov","Dec"},0),MID(R10,5,2)) -> 46111 | V10: Mar 30, 2026 | W10: 417.25 | X10: =DATE(RIGHT(V10,4),MATCH(LEFT(V10,3),{"Jan","Feb","Mar","Apr","May","Jun","Jul","Aug","Sep","Oct","Nov","Dec"},0),MID(V10,5,2)) -> 46111
B11: 45481 | C11: 2545.11 | E11: 45481 | F11: 24502.15 | H11: 45481 | I11: 1278.3 | K11: 45481 | L11: 640.28 | N11: Mar 23, 2026 | O11: 1003.71 | P11: =DATE(RIGHT(N11,4),MATCH(LEFT(N11,3),{"Jan","Feb","Mar","Apr","May","Jun","Jul","Aug","Sep","Oct","Nov","Dec"},0),MID(N11,5,2)) -> 46104 | R11: Mar 23, 2026 | S11: 393.1 | T11: =DATE(RIGHT(R11,4),MATCH(LEFT(R11,3),{"Jan","Feb","Mar","Apr","May","Jun","Jul","Aug","Sep","Oct","Nov","Dec"},0),MID(R11,5,2)) -> 46104 | V11: Mar 23, 2026 | W11: 419.6 | X11: =DATE(RIGHT(V11,4),MATCH(LEFT(V11,3),{"Jan","Feb","Mar","Apr","May","Jun","Jul","Aug","Sep","Oct","Nov","Dec"},0),MID(V11,5,2)) -> 46104
B12: 45488 | C12: 2646.78 | E12: 45488 | F12: 24530.9 | H12: 45488 | I12: 1272.83 | K12: 45488 | L12: 658.55 | N12: Mar 16, 2026 | O12: 1012.57 | P12: =DATE(RIGHT(N12,4),MATCH(LEFT(N12,3),{"Jan","Feb","Mar","Apr","May","Jun","Jul","Aug","Sep","Oct","Nov","Dec"},0),MID(N12,5,2)) -> 46097 | R12: Mar 16, 2026 | S12: 402.75 | T12: =DATE(RIGHT(R12,4),MATCH(LEFT(R12,3),{"Jan","Feb","Mar","Apr","May","Jun","Jul","Aug","Sep","Oct","Nov","Dec"},0),MID(R12,5,2)) -> 46097 | V12: Mar 16, 2026 | W12: 430.7 | X12: =DATE(RIGHT(V12,4),MATCH(LEFT(V12,3),{"Jan","Feb","Mar","Apr","May","Jun","Jul","Aug","Sep","Oct","Nov","Dec"},0),MID(V12,5,2)) -> 46097
B13: 45495 | C13: 2631.29 | E13: 45495 | F13: 24834.85 | H13: 45495 | I13: 1218.84 | K13: 45495 | L13: 669.49 | N13: Mar 9, 2026 | O13: 1022.82 | P13: 46090 | R13: Mar 9, 2026 | S13: 416.05 | T13: 46090 | V13: Mar 9, 2026 | W13: 453.5 | X13: 46090
B14: 45502 | C14: 2613.34 | E14: 45502 | F14: 24717.7 | H14: 45502 | I14: 1227.79 | K14: 45509 | L14: 643.14 | N14: Mar 2, 2026 | O14: 1111.08 | P14: 46083 | R14: Mar 2, 2026 | S14: 458.45 | T14: 46083 | V14: Mar 2, 2026 | W14: 478.6 | X14: 46083
B15: 45509 | C15: 2666.38 | E15: 45509 | F15: 24367.5 | H15: 45509 | I15: 1232.52 | K15: 45509 | L15: 652.4 | N15: Feb 23, 2026 | O15: 1211.48 | P15: =DATE(RIGHT(N15,4),MATCH(LEFT(N15,3),{"Jan","Feb","Mar","Apr","May","Jun","Jul","Aug","Sep","Oct","Nov","Dec"},0),MID(N15,5,2)) -> 46076 | R15: Feb 23, 2026 | S15: 462.6 | T15: =DATE(RIGHT(R15,4),MATCH(LEFT(R15,3),{"Jan","Feb","Mar","Apr","May","Jun","Jul","Aug","Sep","Oct","Nov","Dec"},0),MID(R15,5,2)) -> 46076 | V15: Feb 23, 2026 | W15: 518.5 | X15: =DATE(RIGHT(V15,4),MATCH(LEFT(V15,3),{"Jan","Feb","Mar","Apr","May","Jun","Jul","Aug","Sep","Oct","Nov","Dec"},0),MID(V15,5,2)) -> 46076
B16: 45516 | C16: 2667.4 | E16: 45516 | F16: 24541.15 | H16: 45516 | I16: 1242.73 | K16: 45516 | L16: 651.07 | N16: Feb 16, 2026 | O16: 1199.94 | P16: =DATE(RIGHT(N16,4),MATCH(LEFT(N16,3),{"Jan","Feb","Mar","Apr","May","Jun","Jul","Aug","Sep","Oct","Nov","Dec"},0),MID(N16,5,2)) -> 46069 | R16: Feb 16, 2026 | S16: 479.6 | T16: =DATE(RIGHT(R16,4),MATCH(LEFT(R16,3),{"Jan","Feb","Mar","Apr","May","Jun","Jul","Aug","Sep","Oct","Nov","Dec"},0),MID(R16,5,2)) -> 46069 | V16: Feb 16, 2026 | W16: 509.7 | X16: =DATE(RIGHT(V16,4),MATCH(LEFT(V16,3),{"Jan","Feb","Mar","Apr","May","Jun","Jul","Aug","Sep","Oct","Nov","Dec"},0),MID(V16,5,2)) -> 46069
B17: 45523 | C17: 2732.77 | E17: 45523 | F17: 24823.15 | H17: 45523 | I17: 1244.57 | K17: 45523 | L17: 667.96 | N17: Feb 9, 2026 | O17: 1189.49 | P17: 46062 | R17: Feb 9, 2026 | S17: 483.8 | T17: 46062 | V17: Feb 9, 2026 | W17: 512.45 | X17: 46062
B18: 45530 | C18: 2696.28 | E18: 45530 | F18: 25235.9 | H18: 45530 | I18: 1230.57 | K18: 45530 | L18: 637.38 | N18: Feb 2, 2026 | O18: 1175.95 | P18: 46055 | R18: Feb 2, 2026 | S18: 498.38 | T18: 46055 | V18: Feb 2, 2026 | W18: 508.3 | X18: 46055
B19: 45537 | C19: 2755.43 | E19: 45537 | F19: 24852.15 | H19: 45537 | I19: 1231.78 | K19: 45537 | L19: 655.2 | N19: Jan 26, 2026 | O19: 1150.36 | P19: =DATE(RIGHT(N19,4),MATCH(LEFT(N19,3),{"Jan","Feb","Mar","Apr","May","Jun","Jul","Aug","Sep","Oct","Nov","Dec"},0),MID(N19,5,2)) -> 46048 | R19: Jan 26, 2026 | S19: 469.43 | T19: =DATE(RIGHT(R19,4),MATCH(LEFT(R19,3),{"Jan","Feb","Mar","Apr","May","Jun","Jul","Aug","Sep","Oct","Nov","Dec"},0),MID(R19,5,2)) -> 46048 | V19: Jan 26, 2026 | W19: 502.1 | X19: =DATE(RIGHT(V19,4),MATCH(LEFT(V19,3),{"Jan","Feb","Mar","Apr","May","Jun","Jul","Aug","Sep","Oct","Nov","Dec"},0),MID(V19,5,2)) -> 46048
B20: 45544 | C20: 2846.67 | E20: 45544 | F20: 25356.5 | H20: 45544 | I20: 1245.65 | K20: 45544 | L20: 671.65 | N20: Jan 19, 2026 | O20: 1228.92 | P20: =DATE(RIGHT(N20,4),MATCH(LEFT(N20,3),{"Jan","Feb","Mar","Apr","May","Jun","Jul","Aug","Sep","Oct","Nov","Dec"},0),MID(N20,5,2)) -> 46041 | R20: Jan 19, 2026 | S20: 498.48 | T20: =DATE(RIGHT(R20,4),MATCH(LEFT(R20,3),{"Jan","Feb","Mar","Apr","May","Jun","Jul","Aug","Sep","Oct","Nov","Dec"},0),MID(R20,5,2)) -> 46041 | V20: Jan 19, 2026 | W20: 519 | X20: =DATE(RIGHT(V20,4),MATCH(LEFT(V20,3),{"Jan","Feb","Mar","Apr","May","Jun","Jul","Aug","Sep","Oct","Nov","Dec"},0),MID(V20,5,2)) -> 46041
B21: 45551 | C21: 2890 | E21: 45551 | F21: 25790.95 | H21: 45551 | I21: 1328.4 | K21: 45551 | L21: 698.29 | N21: Jan 12, 2026 | O21: 1225.46 | P21: =DATE(RIGHT(N21,4),MATCH(LEFT(N21,3),{"Jan","Feb","Mar","Apr","May","Jun","Jul","Aug","Sep","Oct","Nov","Dec"},0),MID(N21,5,2)) -> 46034 | R21: Jan 12, 2026 | S21: 499.52 | T21: =DATE(RIGHT(R21,4),MATCH(LEFT(R21,3),{"Jan","Feb","Mar","Apr","May","Jun","Jul","Aug","Sep","Oct","Nov","Dec"},0),MID(R21,5,2)) -> 46034 | V21: Jan 12, 2026 | W21: 514.55 | X21: =DATE(RIGHT(V21,4),MATCH(LEFT(V21,3),{"Jan","Feb","Mar","Apr","May","Jun","Jul","Aug","Sep","Oct","Nov","Dec"},0),MID(V21,5,2)) -> 46034
B22: 45558 | C22: 2878.99 | E22: 45558 | F22: 26178.95 | H22: 45558 | I22: 1351.11 | K22: 45558 | L22: 681.99 | N22: Jan 5, 2026 | O22: 1218.22 | P22: 46027 | R22: Jan 5, 2026 | S22: 501.99 | T22: 46027 | V22: Jan 5, 2026 | W22: 522.4 | X22: 46027
B23: 45565 | C23: 2764.94 | E23: 45565 | F23: 25014.6 | H23: 45565 | I23: 1278.5 | K23: 45565 | L23: 679.78 | N23: Dec 29, 2025 | O23: 1223.77 | P23: =DATE(RIGHT(N23,4),MATCH(LEFT(N23,3),{"Jan","Feb","Mar","Apr","May","Jun","Jul","Aug","Sep","Oct","Nov","Dec"},0),MID(N23,5,2)) -> 46020 | R23: Dec 29, 2025 | S23: 516.36 | T23: =DATE(RIGHT(R23,4),MATCH(LEFT(R23,3),{"Jan","Feb","Mar","Apr","May","Jun","Jul","Aug","Sep","Oct","Nov","Dec"},0),MID(R23,5,2)) -> 46020 | V23: Dec 29, 2025 | W23: 522.6 | X23: =DATE(RIGHT(V23,4),MATCH(LEFT(V23,3),{"Jan","Feb","Mar","Apr","May","Jun","Jul","Aug","Sep","Oct","Nov","Dec"},0),MID(V23,5,2)) -> 46020
B24: 45572 | C24: 2701.32 | E24: 45572 | F24: 24964.25 | H24: 45572 | I24: 1236.01 | K24: 45572 | L24: 675.15 | N24: Dec 22, 2025 | O24: 1195.04 | P24: =DATE(RIGHT(N24,4),MATCH(LEFT(N24,3),{"Jan","Feb","Mar","Apr","May","Jun","Jul","Aug","Sep","Oct","Nov","Dec"},0),MID(N24,5,2)) -> 46013 | R24: Dec 22, 2025 | S24: 508.61 | T24: =DATE(RIGHT(R24,4),MATCH(LEFT(R24,3),{"Jan","Feb","Mar","Apr","May","Jun","Jul","Aug","Sep","Oct","Nov","Dec"},0),MID(R24,5,2)) -> 46013 | V24: Dec 22, 2025 | W24: 488.2 | X24: =DATE(RIGHT(V24,4),MATCH(LEFT(V24,3),{"Jan","Feb","Mar","Apr","May","Jun","Jul","Aug","Sep","Oct","Nov","Dec"},0),MID(V24,5,2)) -> 46013
B25: 45579 | C25: 2637.17 | E25: 45579 | F25: 24854.05 | H25: 45579 | I25: 1156.51 | K25: 45579 | L25: 659.19 | N25: Dec 15, 2025 | O25: 1175.22 | P25: =DATE(RIGHT(N25,4),MATCH(LEFT(N25,3),{"Jan","Feb","Mar","Apr","May","Jun","Jul","Aug","Sep","Oct","Nov","Dec"},0),MID(N25,5,2)) -> 46006 | R25: Dec 15, 2025 | S25: 513.1 | T25: =DATE(RIGHT(R25,4),MATCH(LEFT(R25,3),{"Jan","Feb","Mar","Apr","May","Jun","Jul","Aug","Sep","Oct","Nov","Dec"},0),MID(R25,5,2)) -> 46006 | V25: Dec 15, 2025 | W25: 493.95 | X25: =DATE(RIGHT(V25,4),MATCH(LEFT(V25,3),{"Jan","Feb","Mar","Apr","May","Jun","Jul","Aug","Sep","Oct","Nov","Dec"},0),MID(V25,5,2)) -> 46006
B26: 45586 | C26: 2453.68 | E26: 45586 | F26: 24180.8 | H26: 45586 | I26: 1112.45 | K26: 45586 | L26: 630.43 | N26: Dec 8, 2025 | O26: 1143.12 | P26: 45999 | R26: Dec 8, 2025 | S26: 533.16 | T26: 45999 | V26: Dec 8, 2025 | W26: 495 | X26: 46364
B27: 45593 | C27: 2462.85 | E27: 45593 | F27: 24304.35 | H27: 45593 | I27: 1123.08 | K27: 45593 | L27: 636.2 | N27: Dec 1, 2025 | O27: 1125.49 | P27: 45992 | R27: Dec 1, 2025 | S27: 519.08 | T27: 45992 | V27: Dec 1, 2025 | W27: 510.1 | X27: 46357
B28: 45600 | C28: 2433.93 | E28: 45600 | F28: 24148.2 | H28: 45600 | I28: 1129.65 | K28: 45600 | L28: 620.34 | N28: Nov 24, 2025 | O28: 1135 | P28: =DATE(RIGHT(N28,4),MATCH(LEFT(N28,3),{"Jan","Feb","Mar","Apr","May","Jun","Jul","Aug","Sep","Oct","Nov","Dec"},0),MID(N28,5,2)) -> 45985 | R28: Nov 24, 2025 | S28: 524.22 | T28: =DATE(RIGHT(R28,4),MATCH(LEFT(R28,3),{"Jan","Feb","Mar","Apr","May","Jun","Jul","Aug","Sep","Oct","Nov","Dec"},0),MID(R28,5,2)) -> 45985 | V28: Nov 24, 2025 | W28: 517.4 | X28: =DATE(RIGHT(V28,4),MATCH(LEFT(V28,3),{"Jan","Feb","Mar","Apr","May","Jun","Jul","Aug","Sep","Oct","Nov","Dec"},0),MID(V28,5,2)) -> 45985
B29: 45607 | C29: 2345.9 | E29: 45607 | F29: 23532.7 | H29: 45607 | I29: 1074.12 | K29: 45607 | L29: 583.31 | N29: Nov 17, 2025 | O29: 1114.79 | P29: =DATE(RIGHT(N29,4),MATCH(LEFT(N29,3),{"Jan","Feb","Mar","Apr","May","Jun","Jul","Aug","Sep","Oct","Nov","Dec"},0),MID(N29,5,2)) -> 45978 | R29: Nov 17, 2025 | S29: 507.22 | T29: =DATE(RIGHT(R29,4),MATCH(LEFT(R29,3),{"Jan","Feb","Mar","Apr","May","Jun","Jul","Aug","Sep","Oct","Nov","Dec"},0),MID(R29,5,2)) -> 45978 | V29: Nov 17, 2025 | W29: 515.65 | X29: =DATE(RIGHT(V29,4),MATCH(LEFT(V29,3),{"Jan","Feb","Mar","Apr","May","Jun","Jul","Aug","Sep","Oct","Nov","Dec"},0),MID(V29,5,2)) -> 45978
B30: 45614 | C30: 2400.93 | E30: 45614 | F30: 23907.25 | H30: 45614 | I30: 1105.85 | K30: 45614 | L30: 590.1 | N30: Nov 10, 2025 | O30: 1135.89 | P30: =DATE(RIGHT(N30,4),MATCH(LEFT(N30,3),{"Jan","Feb","Mar","Apr","May","Jun","Jul","Aug","Sep","Oct","Nov","Dec"},0),MID(N30,5,2)) -> 45971 | R30: Nov 10, 2025 | S30: 510.25 | T30: =DATE(RIGHT(R30,4),MATCH(LEFT(R30,3),{"Jan","Feb","Mar","Apr","May","Jun","Jul","Aug","Sep","Oct","Nov","Dec"},0),MID(R30,5,2)) -> 45971 | V30: Nov 10, 2025 | W30: 525 | X30: =DATE(RIGHT(V30,4),MATCH(LEFT(V30,3),{"Jan","Feb","Mar","Apr","May","Jun","Jul","Aug","Sep","Oct","Nov","Dec"},0),MID(V30,5,2)) -> 45971
B31: 45621 | C31: 2450.91 | E31: 45621 | F31: 24131.1 | H31: 45621 | I31: 1099.63 | K31: 45621 | L31: 635.21 | N31: Nov 3, 2025 | O31: 1106.57 | P31: 45964 | R31: Nov 3, 2025 | S31: 504.12 | T31: 45964 | V31: Nov 3, 2025 | W31: 515.93 | X31: 45964
B32: 45628 | C32: 2438.78 | E32: 45628 | F32: 24677.8 | H32: 45628 | I32: 1115.94 | K32: 45628 | L32: 624.08 | N32: Oct 27, 2025 | O32: 1103.41 | P32: =DATE(RIGHT(N32,4),MATCH(LEFT(N32,3),{"Jan","Feb","Mar","Apr","May","Jun","Jul","Aug","Sep","Oct","Nov","Dec"},0),MID(N32,5,2)) -> 45957 | R32: Oct 27, 2025 | S32: 524.03 | T32: =DATE(RIGHT(R32,4),MATCH(LEFT(R32,3),{"Jan","Feb","Mar","Apr","May","Jun","Jul","Aug","Sep","Oct","Nov","Dec"},0),MID(R32,5,2)) -> 45957 | V32: Oct 27, 2025 | W32: 484.99 | X32: =DATE(RIGHT(V32,4),MATCH(LEFT(V32,3),{"Jan","Feb","Mar","Apr","May","Jun","Jul","Aug","Sep","Oct","Nov","Dec"},0),MID(V32,5,2)) -> 45957
B33: 45635 | C33: 2346.78 | E33: 45635 | F33: 24768.3 | H33: 45635 | I33: 1108.91 | K33: 45635 | L33: 630.14 | N33: Oct 20, 2025 | O33: 1115.05 | P33: =DATE(RIGHT(N33,4),MATCH(LEFT(N33,3),{"Jan","Feb","Mar","Apr","May","Jun","Jul","Aug","Sep","Oct","Nov","Dec"},0),MID(N33,5,2)) -> 45950 | R33: Oct 20, 2025 | S33: 534.08 | T33: =DATE(RIGHT(R33,4),MATCH(LEFT(R33,3),{"Jan","Feb","Mar","Apr","May","Jun","Jul","Aug","Sep","Oct","Nov","Dec"},0),MID(R33,5,2)) -> 45950 | V33: Oct 20, 2025 | W33: 505.78 | X33: =DATE(RIGHT(V33,4),MATCH(LEFT(V33,3),{"Jan","Feb","Mar","Apr","May","Jun","Jul","Aug","Sep","Oct","Nov","Dec"},0),MID(V33,5,2)) -> 45950
B34: 45642 | C34: 2291.6 | E34: 45642 | F34: 23587.5 | H34: 45642 | I34: 1064.62 | K34: 45642 | L34: 618.47 | N34: Oct 13, 2025 | O34: 1116.83 | P34: =DATE(RIGHT(N34,4),MATCH(LEFT(N34,3),{"Jan","Feb","Mar","Apr","May","Jun","Jul","Aug","Sep","Oct","Nov","Dec"},0),MID(N34,5,2)) -> 45943 | R34: Oct 13, 2025 | S34: 540.8 | T34: =DATE(RIGHT(R34,4),MATCH(LEFT(R34,3),{"Jan","Feb","Mar","Apr","May","Jun","Jul","Aug","Sep","Oct","Nov","Dec"},0),MID(R34,5,2)) -> 45943 | V34: Oct 13, 2025 | W34: 505.68 | X34: =DATE(RIGHT(V34,4),MATCH(LEFT(V34,3),{"Jan","Feb","Mar","Apr","May","Jun","Jul","Aug","Sep","Oct","Nov","Dec"},0),MID(V34,5,2)) -> 45943
B35: 45649 | C35: 2298.81 | E35: 45649 | F35: 23813.4 | H35: 45649 | I35: 1065.65 | K35: 45649 | L35: 623.05 | N35: Oct 6, 2025 | O35: 1114.46 | P35: 45936 | R35: Oct 6, 2025 | S35: 531.87 | T35: 45936 | V35: Oct 6, 2025 | W35: 487.13 | X35: 45936
B36: 45656 | C36: 2362.64 | E36: 45656 | F36: 24004.75 | H36: 45656 | I36: 1098.67 | K36: 45656 | L36: 650.97 | N36: Sep 29, 2025 | O36: 1133.4 | P36: =DATE(RIGHT(N36,4),MATCH(LEFT(N36,3),{"Jan","Feb","Mar","Apr","May","Jun","Jul","Aug","Sep","Oct","Nov","Dec"},0),MID(N36,5,2)) -> 45929 | R36: Sep 29, 2025 | S36: 539.87 | T36: =DATE(RIGHT(R36,4),MATCH(LEFT(R36,3),{"Jan","Feb","Mar","Apr","May","Jun","Jul","Aug","Sep","Oct","Nov","Dec"},0),MID(R36,5,2)) -> 45929 | V36: Sep 29, 2025 | W36: 493.54 | X36: =DATE(RIGHT(V36,4),MATCH(LEFT(V36,3),{"Jan","Feb","Mar","Apr","May","Jun","Jul","Aug","Sep","Oct","Nov","Dec"},0),MID(V36,5,2)) -> 45929
B37: 45663 | C37: 2397.79 | E37: 45663 | F37: 23431.5 | H37: 45663 | I37: 1106.15 | K37: 45663 | L37: 663.72 | N37: Sep 22, 2025 | O37: 1148.1 | P37: =DATE(RIGHT(N37,4),MATCH(LEFT(N37,3),{"Jan","Feb","Mar","Apr","May","Jun","Jul","Aug","Sep","Oct","Nov","Dec"},0),MID(N37,5,2)) -> 45922 | R37: Sep 22, 2025 | S37: 547.02 | T37: =DATE(RIGHT(R37,4),MATCH(LEFT(R37,3),{"Jan","Feb","Mar","Apr","May","Jun","Jul","Aug","Sep","Oct","Nov","Dec"},0),MID(R37,5,2)) -> 45922 | V37: Sep 22, 2025 | W37: 497.13 | X37: =DATE(RIGHT(V37,4),MATCH(LEFT(V37,3),{"Jan","Feb","Mar","Apr","May","Jun","Jul","Aug","Sep","Oct","Nov","Dec"},0),MID(V37,5,2)) -> 45922
B38: 45670 | C38: 2311.33 | E38: 45670 | F38: 23203.2 | H38: 45670 | I38: 1091.04 | K38: 45670 | L38: 654.37 | N38: Sep 15, 2025 | O38: 1222.08 | P38: =DATE(RIGHT(N38,4),MATCH(LEFT(N38,3),{"Jan","Feb","Mar","Apr","May","Jun","Jul","Aug","Sep","Oct","Nov","Dec"},0),MID(N38,5,2)) -> 45915 | R38: Sep 15, 2025 | S38: 568.35 | T38: =DATE(RIGHT(R38,4),MATCH(LEFT(R38,3),{"Jan","Feb","Mar","Apr","May","Jun","Jul","Aug","Sep","Oct","Nov","Dec"},0),MID(R38,5,2)) -> 45915 | V38: Sep 15, 2025 | W38: 532.64 | X38: =DATE(RIGHT(V38,4),MATCH(LEFT(V38,3),{"Jan","Feb","Mar","Apr","May","Jun","Jul","Aug","Sep","Oct","Nov","Dec"},0),MID(V38,5,2)) -> 45915
B39: 45677 | C39: 2325.18 | E39: 45677 | F39: 23092.2 | H39: 45677 | I39: 1086.47 | K39: 45677 | L39: 656.14 | N39: Sep 8, 2025 | O39: 1232.73 | P39: 45908 | R39: Sep 8, 2025 | S39: 590.27 | T39: 45908 | V39: Sep 8, 2025 | W39: 536.02 | X39: 45908
B40: 45684 | C40: 2460.63 | E40: 45684 | F40: 23482.15 | H40: 45684 | I40: 1145.17 | K40: 45684 | L40: 683.72 | N40: Sep 1, 2025 | O40: 1214.78 | P40: 45901 | R40: Sep 1, 2025 | S40: 593.21 | T40: 45901 | V40: Sep 1, 2025 | W40: 543.83 | X40: 45901
B41: 45691 | C41: 2321 | E41: 45691 | F41: 23559.95 | H41: 45691 | I41: 1094.93 | K41: 45691 | L41: 639.45 | N41: Aug 25, 2025 | O41: 1225.73 | P41: =DATE(RIGHT(N41,4),MATCH(LEFT(N41,3),{"Jan","Feb","Mar","Apr","May","Jun","Jul","Aug","Sep","Oct","Nov","Dec"},0),MID(N41,5,2)) -> 45894 | R41: Aug 25, 2025 | S41: 562.47 | T41: =DATE(RIGHT(R41,4),MATCH(LEFT(R41,3),{"Jan","Feb","Mar","Apr","May","Jun","Jul","Aug","Sep","Oct","Nov","Dec"},0),MID(R41,5,2)) -> 45894 | V41: Aug 25, 2025 | W41: 518.36 | X41: =DATE(RIGHT(V41,4),MATCH(LEFT(V41,3),{"Jan","Feb","Mar","Apr","May","Jun","Jul","Aug","Sep","Oct","Nov","Dec"},0),MID(V41,5,2)) -> 45894
B42: 45698 | C42: 2276.33 | E42: 45698 | F42: 22929.25 | H42: 45698 | I42: 1087.46 | K42: 45698 | L42: 627.5 | N42: Aug 18, 2025 | O42: 1240.13 | P42: =DATE(RIGHT(N42,4),MATCH(LEFT(N42,3),{"Jan","Feb","Mar","Apr","May","Jun","Jul","Aug","Sep","Oct","Nov","Dec"},0),MID(N42,5,2)) -> 45887 | R42: Aug 18, 2025 | S42: 600.07 | T42: =DATE(RIGHT(R42,4),MATCH(LEFT(R42,3),{"Jan","Feb","Mar","Apr","May","Jun","Jul","Aug","Sep","Oct","Nov","Dec"},0),MID(R42,5,2)) -> 45887 | V42: Aug 18, 2025 | W42: 513.24 | X42: =DATE(RIGHT(V42,4),MATCH(LEFT(V42,3),{"Jan","Feb","Mar","Apr","May","Jun","Jul","Aug","Sep","Oct","Nov","Dec"},0),MID(V42,5,2)) -> 45887
B43: 45705 | C43: 2201.02 | E43: 45705 | F43: 22795.9 | H43: 45705 | I43: 1096.92 | K43: 45705 | L43: 618.64 | N43: Aug 11, 2025 | O43: 1163.95 | P43: =DATE(RIGHT(N43,4),MATCH(LEFT(N43,3),{"Jan","Feb","Mar","Apr","May","Jun","Jul","Aug","Sep","Oct","Nov","Dec"},0),MID(N43,5,2)) -> 45880 | R43: Aug 11, 2025 | S43: 571.05 | T43: =DATE(RIGHT(R43,4),MATCH(LEFT(R43,3),{"Jan","Feb","Mar","Apr","May","Jun","Jul","Aug","Sep","Oct","Nov","Dec"},0),MID(R43,5,2)) -> 45880 | V43: Aug 11, 2025 | W43: 498.27 | X43: =DATE(RIGHT(V43,4),MATCH(LEFT(V43,3),{"Jan","Feb","Mar","Apr","May","Jun","Jul","Aug","Sep","Oct","Nov","Dec"},0),MID(V43,5,2)) -> 45880
B44: 45712 | C44: 2150.55 | E44: 45712 | F44: 22124.7 | H44: 45712 | I44: 1084.39 | K44: 45712 | L44: 594.68 | N44: Aug 4, 2025 | O44: 1165.13 | P44: 45873 | R44: Aug 4, 2025 | S44: 564.92 | T44: 45873 | V44: Aug 4, 2025 | W44: 504.59 | X44: 45873
B45: 45719 | C45: 2164.59 | E45: 45719 | F45: 22552.5 | H45: 45719 | I45: 1108.55 | K45: 45719 | L45: 603.64 | N45: Jul 28, 2025 | O45: 1244.1 | P45: =DATE(RIGHT(N45,4),MATCH(LEFT(N45,3),{"Jan","Feb","Mar","Apr","May","Jun","Jul","Aug","Sep","Oct","Nov","Dec"},0),MID(N45,5,2)) -> 45866 | R45: Jul 28, 2025 | S45: 607.28 | T45: =DATE(RIGHT(R45,4),MATCH(LEFT(R45,3),{"Jan","Feb","Mar","Apr","May","Jun","Jul","Aug","Sep","Oct","Nov","Dec"},0),MID(R45,5,2)) -> 45866 | V45: Jul 28, 2025 | W45: 531.54 | X45: =DATE(RIGHT(V45,4),MATCH(LEFT(V45,3),{"Jan","Feb","Mar","Apr","May","Jun","Jul","Aug","Sep","Oct","Nov","Dec"},0),MID(V45,5,2)) -> 45866
B46: 45726 | C46: 2135.38 | E46: 45726 | F46: 22397.2 | H46: 45726 | I46: 1085.53 | K46: 45726 | L46: 600.32 | N46: Jul 21, 2025 | O46: 1195.58 | P46: =DATE(RIGHT(N46,4),MATCH(LEFT(N46,3),{"Jan","Feb","Mar","Apr","May","Jun","Jul","Aug","Sep","Oct","Nov","Dec"},0),MID(N46,5,2)) -> 45859 | R46: Jul 21, 2025 | S46: 564.04 | T46: =DATE(RIGHT(R46,4),MATCH(LEFT(R46,3),{"Jan","Feb","Mar","Apr","May","Jun","Jul","Aug","Sep","Oct","Nov","Dec"},0),MID(R46,5,2)) -> 45859 | V46: Jul 21, 2025 | W46: 508.66 | X46: =DATE(RIGHT(V46,4),MATCH(LEFT(V46,3),{"Jan","Feb","Mar","Apr","May","Jun","Jul","Aug","Sep","Oct","Nov","Dec"},0),MID(V46,5,2)) -> 45859
B47: 45733 | C47: 2205.49 | E47: 45733 | F47: 23350.4 | H47: 45733 | I47: 1123.61 | K47: 45733 | L47: 624.58 | N47: Jul 14, 2025 | O47: 1229.17 | P47: =DATE(RIGHT(N47,4),MATCH(LEFT(N47,3),{"Jan","Feb","Mar","Apr","May","Jun","Jul","Aug","Sep","Oct","Nov","Dec"},0),MID(N47,5,2)) -> 45852 | R47: Jul 14, 2025 | S47: 580.17 | T47: =DATE(RIGHT(R47,4),MATCH(LEFT(R47,3),{"Jan","Feb","Mar","Apr","May","Jun","Jul","Aug","Sep","Oct","Nov","Dec"},0),MID(R47,5,2)) -> 45852 | V47: Jul 14, 2025 | W47: 514.69 | X47: =DATE(RIGHT(V47,4),MATCH(LEFT(V47,3),{"Jan","Feb","Mar","Apr","May","Jun","Jul","Aug","Sep","Oct","Nov","Dec"},0),MID(V47,5,2)) -> 45852
B48: 45740 | C48: 2217.91 | E48: 45740 | F48: 23519.35 | H48: 45740 | I48: 1114.65 | K48: 45740 | L48: 645.22 | N48: Jul 7, 2025 | O48: 1262.28 | P48: 45845 | R48: Jul 7, 2025 | S48: 575.61 | T48: 45845 | V48: Jul 7, 2025 | W48: 522.82 | X48: 45845
B49: 45747 | C49: 2203.87 | E49: 45747 | F49: 22904.45 | H49: 45747 | I49: 1120.29 | K49: 45747 | L49: 670.62 | N49: Jun 30, 2025 | O49: 1171.81 | P49: =DATE(RIGHT(N49,4),MATCH(LEFT(N49,3),{"Jan","Feb","Mar","Apr","May","Jun","Jul","Aug","Sep","Oct","Nov","Dec"},0),MID(N49,5,2)) -> 45838 | R49: Jun 30, 2025 | S49: 551.63 | T49: =DATE(RIGHT(R49,4),MATCH(LEFT(R49,3),{"Jan","Feb","Mar","Apr","May","Jun","Jul","Aug","Sep","Oct","Nov","Dec"},0),MID(R49,5,2)) -> 45838 | V49: Jun 30, 2025 | W49: 487.61 | X49: =DATE(RIGHT(V49,4),MATCH(LEFT(V49,3),{"Jan","Feb","Mar","Apr","May","Jun","Jul","Aug","Sep","Oct","Nov","Dec"},0),MID(V49,5,2)) -> 45838
B50: 45754 | C50: 2323.26 | E50: 45754 | F50: 22828.55 | H50: 45754 | I50: 1169.44 | K50: 45754 | L50: 702.95 | N50: Jun 23, 2025 | O50: 1155.6 | P50: =DATE(RIGHT(N50,4),MATCH(LEFT(N50,3),{"Jan","Feb","Mar","Apr","May","Jun","Jul","Aug","Sep","Oct","Nov","Dec"},0),MID(N50,5,2)) -> 45831 | R50: Jun 23, 2025 | S50: 556.19 | T50: =DATE(RIGHT(R50,4),MATCH(LEFT(R50,3),{"Jan","Feb","Mar","Apr","May","Jun","Jul","Aug","Sep","Oct","Nov","Dec"},0),MID(R50,5,2)) -> 45831 | V50: Jun 23, 2025 | W50: 478.99 | X50: =DATE(RIGHT(V50,4),MATCH(LEFT(V50,3),{"Jan","Feb","Mar","Apr","May","Jun","Jul","Aug","Sep","Oct","Nov","Dec"},0),MID(V50,5,2)) -> 45831
B51: 45761 | C51: 2331.95 | E51: 45761 | F51: 23851.65 | H51: 45761 | I51: 1196.78 | K51: 45761 | L51: 707.75 | N51: Jun 16, 2025 | O51: 1168.37 | P51: =DATE(RIGHT(N51,4),MATCH(LEFT(N51,3),{"Jan","Feb","Mar","Apr","May","Jun","Jul","Aug","Sep","Oct","Nov","Dec"},0),MID(N51,5,2)) -> 45824 | R51: Jun 16, 2025 | S51: 542.32 | T51: =DATE(RIGHT(R51,4),MATCH(LEFT(R51,3),{"Jan","Feb","Mar","Apr","May","Jun","Jul","Aug","Sep","Oct","Nov","Dec"},0),MID(R51,5,2)) -> 45824 | V51: Jun 16, 2025 | W51: 459.84 | X51: =DATE(RIGHT(V51,4),MATCH(LEFT(V51,3),{"Jan","Feb","Mar","Apr","May","Jun","Jul","Aug","Sep","Oct","Nov","Dec"},0),MID(V51,5,2)) -> 45824
B52: 45768 | C52: 2289.93 | E52: 45768 | F52: 24039.35 | H52: 45768 | I52: 1195.24 | K52: 45768 | L52: 703.39 | N52: Jun 9, 2025 | O52: 1167.78 | P52: 45817 | R52: Jun 9, 2025 | S52: 561.44 | T52: 45817 | V52: Jun 9, 2025 | W52: 459.44 | X52: 45817
B53: 45775 | C53: 2276.57 | E53: 45775 | F53: 24346.7 | H53: 45775 | I53: 1154.78 | K53: 45775 | L53: 691.91 | N53: Jun 2, 2025 | O53: 1188.7 | P53: 45810 | R53: Jun 2, 2025 | S53: 572.03 | T53: 45810 | V53: Jun 2, 2025 | W53: 473.97 | X53: 45810
B54: 45782 | C54: 2290.62 | E54: 45782 | F54: 24008 | H54: 45782 | I54: 1151.61 | K54: 45782 | L54: 716.17 | N54: May 26, 2025 | O54: 1209.62 | P54: =DATE(RIGHT(N54,4),MATCH(LEFT(N54,3),{"Jan","Feb","Mar","Apr","May","Jun","Jul","Aug","Sep","Oct","Nov","Dec"},0),MID(N54,5,2)) -> 45803 | R54: May 26, 2025 | S54: 572.86 | T54: =DATE(RIGHT(R54,4),MATCH(LEFT(R54,3),{"Jan","Feb","Mar","Apr","May","Jun","Jul","Aug","Sep","Oct","Nov","Dec"},0),MID(R54,5,2)) -> 45803 | V54: May 26, 2025 | W54: 475.64 | X54: =DATE(RIGHT(V54,4),MATCH(LEFT(V54,3),{"Jan","Feb","Mar","Apr","May","Jun","Jul","Aug","Sep","Oct","Nov","Dec"},0),MID(V54,5,2)) -> 45803
B55: 45789 | C55: 2338.24 | E55: 45789 | F55: 25019.8 | H55: 45789 | I55: 1192.92 | K55: 45789 | L55: 717.26 | N55: May 19, 2025 | O55: 1254.81 | P55: =DATE(RIGHT(N55,4),MATCH(LEFT(N55,3),{"Jan","Feb","Mar","Apr","May","Jun","Jul","Aug","Sep","Oct","Nov","Dec"},0),MID(N55,5,2)) -> 45796 | R55: May 19, 2025 | S55: 580.29 | T55: =DATE(RIGHT(R55,4),MATCH(LEFT(R55,3),{"Jan","Feb","Mar","Apr","May","Jun","Jul","Aug","Sep","Oct","Nov","Dec"},0),MID(R55,5,2)) -> 45796 | V55: May 19, 2025 | W55: 474.66 | X55: =DATE(RIGHT(V55,4),MATCH(LEFT(V55,3),{"Jan","Feb","Mar","Apr","May","Jun","Jul","Aug","Sep","Oct","Nov","Dec"},0),MID(V55,5,2)) -> 45796
B56: 45796 | C56: 2316.44 | E56: 45796 | F56: 24853.15 | H56: 45796 | I56: 1195.69 | K56: 45796 | L56: 693.94 | N56: May 12, 2025 | O56: 1271.57 | P56: =DATE(RIGHT(N56,4),MATCH(LEFT(N56,3),{"Jan","Feb","Mar","Apr","May","Jun","Jul","Aug","Sep","Oct","Nov","Dec"},0),MID(N56,5,2)) -> 45789 | R56: May 12, 2025 | S56: 619.84 | T56: =DATE(RIGHT(R56,4),MATCH(LEFT(R56,3),{"Jan","Feb","Mar","Apr","May","Jun","Jul","Aug","Sep","Oct","Nov","Dec"},0),MID(R56,5,2)) -> 45789 | V56: May 12, 2025 | W56: 469.44 | X56: =DATE(RIGHT(V56,4),MATCH(LEFT(V56,3),{"Jan","Feb","Mar","Apr","May","Jun","Jul","Aug","Sep","Oct","Nov","Dec"},0),MID(V56,5,2)) -> 45789
B57: 45803 | C57: 2305.74 | E57: 45803 | F57: 24750.7 | H57: 45803 | I57: 1186.68 | K57: 45803 | L57: 709.38 | N57: May 5, 2025 | O57: 1215.4 | P57: 45782 | R57: May 5, 2025 | S57: 614.1 | T57: 45782 | V57: May 5, 2025 | W57: 455.75 | X57: 45782
B58: 45810 | C58: 2346.48 | E58: 45810 | F58: 25003.05 | H58: 45810 | I58: 1197.08 | K58: 45810 | L58: 691.76 | N58: Apr 28, 2025 | O58: 1231.45 | P58: =DATE(RIGHT(N58,4),MATCH(LEFT(N58,3),{"Jan","Feb","Mar","Apr","May","Jun","Jul","Aug","Sep","Oct","Nov","Dec"},0),MID(N58,5,2)) -> 45775 | R58: Apr 28, 2025 | S58: 614.29 | T58: =DATE(RIGHT(R58,4),MATCH(LEFT(R58,3),{"Jan","Feb","Mar","Apr","May","Jun","Jul","Aug","Sep","Oct","Nov","Dec"},0),MID(R58,5,2)) -> 45775 | V58: Apr 28, 2025 | W58: 472.15 | X58: =DATE(RIGHT(V58,4),MATCH(LEFT(V58,3),{"Jan","Feb","Mar","Apr","May","Jun","Jul","Aug","Sep","Oct","Nov","Dec"},0),MID(V58,5,2)) -> 45775
B59: 45817 | C59: 2276.97 | E59: 45817 | F59: 24718.6 | H59: 45817 | I59: 1177.07 | K59: 45817 | L59: 684.38 | N59: Apr 21, 2025 | O59: 1239.28 | P59: =DATE(RIGHT(N59,4),MATCH(LEFT(N59,3),{"Jan","Feb","Mar","Apr","May","Jun","Jul","Aug","Sep","Oct","Nov","Dec"},0),MID(N59,5,2)) -> 45768 | R59: Apr 21, 2025 | S59: 603.77 | T59: =DATE(RIGHT(R59,4),MATCH(LEFT(R59,3),{"Jan","Feb","Mar","Apr","May","Jun","Jul","Aug","Sep","Oct","Nov","Dec"},0),MID(R59,5,2)) -> 45768 | V59: Apr 21, 2025 | W59: 477.27 | X59: =DATE(RIGHT(V59,4),MATCH(LEFT(V59,3),{"Jan","Feb","Mar","Apr","May","Jun","Jul","Aug","Sep","Oct","Nov","Dec"},0),MID(V59,5,2)) -> 45768
B60: 45824 | C60: 2264.4 | E60: 45824 | F60: 25112.4 | H60: 45824 | I60: 1168.95 | K60: 45824 | L60: 686.46 | N60: Apr 14, 2025 | O60: 1212.66 | P60: =DATE(RIGHT(N60,4),MATCH(LEFT(N60,3),{"Jan","Feb","Mar","Apr","May","Jun","Jul","Aug","Sep","Oct","Nov","Dec"},0),MID(N60,5,2)) -> 45761 | R60: Apr 14, 2025 | S60: 599.1 | T60: =DATE(RIGHT(R60,4),MATCH(LEFT(R60,3),{"Jan","Feb","Mar","Apr","May","Jun","Jul","Aug","Sep","Oct","Nov","Dec"},0),MID(R60,5,2)) -> 45761 | V60: Apr 14, 2025 | W60: 472.05 | X60: =DATE(RIGHT(V60,4),MATCH(LEFT(V60,3),{"Jan","Feb","Mar","Apr","May","Jun","Jul","Aug","Sep","Oct","Nov","Dec"},0),MID(V60,5,2)) -> 45761
B61: 45831 | C61: 2265.09 | E61: 45831 | F61: 25637.8 | H61: 45831 | I61: 1217.63 | K61: 45831 | L61: 724.43 | N61: Apr 7, 2025 | O61: 1197.3 | P61: 45754 | R61: Apr 7, 2025 | S61: 592.76 | T61: 45754 | V61: Apr 7, 2025 | W61: 454.32 | X61: 45754
B62: 45838 | C62: 2321.05 | E62: 45838 | F62: 25461 | H62: 45838 | I62: 1184.99 | K62: 45838 | L62: 721.41 | N62: Mar 31, 2025 | O62: 1131.74 | P62: =DATE(RIGHT(N62,4),MATCH(LEFT(N62,3),{"Jan","Feb","Mar","Apr","May","Jun","Jul","Aug","Sep","Oct","Nov","Dec"},0),MID(N62,5,2)) -> 45747 | R62: Mar 31, 2025 | S62: 577.47 | T62: =DATE(RIGHT(R62,4),MATCH(LEFT(R62,3),{"Jan","Feb","Mar","Apr","May","Jun","Jul","Aug","Sep","Oct","Nov","Dec"},0),MID(R62,5,2)) -> 45747 | V62: Mar 31, 2025 | W62: 454.76 | X62: =DATE(RIGHT(V62,4),MATCH(LEFT(V62,3),{"Jan","Feb","Mar","Apr","May","Jun","Jul","Aug","Sep","Oct","Nov","Dec"},0),MID(V62,5,2)) -> 45747
B63: 45845 | C63: 2499.95 | E63: 45845 | F63: 25149.85 | H63: 45845 | I63: 1195.3 | K63: 45845 | L63: 718.49 | N63: Mar 24, 2025 | O63: 1134.33 | P63: =DATE(RIGHT(N63,4),MATCH(LEFT(N63,3),{"Jan","Feb","Mar","Apr","May","Jun","Jul","Aug","Sep","Oct","Nov","Dec"},0),MID(N63,5,2)) -> 45740 | R63: Mar 24, 2025 | S63: 564.9 | T63: =DATE(RIGHT(R63,4),MATCH(LEFT(R63,3),{"Jan","Feb","Mar","Apr","May","Jun","Jul","Aug","Sep","Oct","Nov","Dec"},0),MID(R63,5,2)) -> 45740 | V63: Mar 24, 2025 | W63: 498.84 | X63: =DATE(RIGHT(V63,4),MATCH(LEFT(V63,3),{"Jan","Feb","Mar","Apr","May","Jun","Jul","Aug","Sep","Oct","Nov","Dec"},0),MID(V63,5,2)) -> 45740
B64: 45852 | C64: 2470.18 | E64: 45852 | F64: 24968.4 | H64: 45852 | I64: 1229.46 | K64: 45852 | L64: 713.1 | N64: Mar 17, 2025 | O64: 1088.05 | P64: =DATE(RIGHT(N64,4),MATCH(LEFT(N64,3),{"Jan","Feb","Mar","Apr","May","Jun","Jul","Aug","Sep","Oct","Nov","Dec"},0),MID(N64,5,2)) -> 45733 | R64: Mar 17, 2025 | S64: 561.1 | T64: =DATE(RIGHT(R64,4),MATCH(LEFT(R64,3),{"Jan","Feb","Mar","Apr","May","Jun","Jul","Aug","Sep","Oct","Nov","Dec"},0),MID(R64,5,2)) -> 45733 | V64: Mar 17, 2025 | W64: 499.13 | X64: =DATE(RIGHT(V64,4),MATCH(LEFT(V64,3),{"Jan","Feb","Mar","Apr","May","Jun","Jul","Aug","Sep","Oct","Nov","Dec"},0),MID(V64,5,2)) -> 45733
B65: 45859 | C65: 2396.56 | E65: 45859 | F65: 24837 | H65: 45859 | I65: 1131.19 | K65: 45859 | L65: 687.11 | N65: Mar 10, 2025 | O65: 1003.75 | P65: =DATE(RIGHT(N65,4),MATCH(LEFT(N65,3),{"Jan","Feb","Mar","Apr","May","Jun","Jul","Aug","Sep","Oct","Nov","Dec"},0),MID(N65,5,2)) -> 45726 | R65: Mar 10, 2025 | S65: 547.61 | T65: =DATE(RIGHT(R65,4),MATCH(LEFT(R65,3),{"Jan","Feb","Mar","Apr","May","Jun","Jul","Aug","Sep","Oct","Nov","Dec"},0),MID(R65,5,2)) -> 45726 | V65: Mar 10, 2025 | W65: 493.37 | X65: =DATE(RIGHT(V65,4),MATCH(LEFT(V65,3),{"Jan","Feb","Mar","Apr","May","Jun","Jul","Aug","Sep","Oct","Nov","Dec"},0),MID(V65,5,2)) -> 45726
B66: 45866 | C66: 2533.78 | E66: 45866 | F66: 24565.35 | H66: 45866 | I66: 1132.14 | K66: 45866 | L66: 704.19 | N66: Mar 3, 2025 | O66: 1022.83 | P66: 45719 | R66: Mar 3, 2025 | S66: 537.48 | T66: 45719 | V66: Mar 3, 2025 | W66: 488.3 | X66: 45719
B67: 45873 | C67: 2479.11 | E67: 45873 | F67: 24363.3 | H67: 45873 | I67: 1090.61 | K67: 45873 | L67: 703.95 | N67: Feb 24, 2025 | O67: 983.55 | P67: =DATE(RIGHT(N67,4),MATCH(LEFT(N67,3),{"Jan","Feb","Mar","Apr","May","Jun","Jul","Aug","Sep","Oct","Nov","Dec"},0),MID(N67,5,2)) -> 45712 | R67: Feb 24, 2025 | S67: 516.24 | T67: =DATE(RIGHT(R67,4),MATCH(LEFT(R67,3),{"Jan","Feb","Mar","Apr","May","Jun","Jul","Aug","Sep","Oct","Nov","Dec"},0),MID(R67,5,2)) -> 45712 | V67: Feb 24, 2025 | W67: 485.84 | X67: =DATE(RIGHT(V67,4),MATCH(LEFT(V67,3),{"Jan","Feb","Mar","Apr","May","Jun","Jul","Aug","Sep","Oct","Nov","Dec"},0),MID(V67,5,2)) -> 45712
B68: 45880 | C68: 2461.25 | E68: 45880 | F68: 24631.3 | H68: 45880 | I68: 1083.55 | K68: 45880 | L68: 710.55 | N68: Feb 17, 2025 | O68: 1029.59 | P68: =DATE(RIGHT(N68,4),MATCH(LEFT(N68,3),{"Jan","Feb","Mar","Apr","May","Jun","Jul","Aug","Sep","Oct","Nov","Dec"},0),MID(N68,5,2)) -> 45705 | R68: Feb 17, 2025 | S68: 542.25 | T68: =DATE(RIGHT(R68,4),MATCH(LEFT(R68,3),{"Jan","Feb","Mar","Apr","May","Jun","Jul","Aug","Sep","Oct","Nov","Dec"},0),MID(R68,5,2)) -> 45705 | V68: Feb 17, 2025 | W68: 500.95 | X68: =DATE(RIGHT(V68,4),MATCH(LEFT(V68,3),{"Jan","Feb","Mar","Apr","May","Jun","Jul","Aug","Sep","Oct","Nov","Dec"},0),MID(V68,5,2)) -> 45705
B69: 45887 | C69: 2609.39 | E69: 45887 | F69: 24870.1 | H69: 45887 | I69: 1156.66 | K69: 45887 | L69: 730.7 | N69: Feb 10, 2025 | O69: 1036.14 | P69: =DATE(RIGHT(N69,4),MATCH(LEFT(N69,3),{"Jan","Feb","Mar","Apr","May","Jun","Jul","Aug","Sep","Oct","Nov","Dec"},0),MID(N69,5,2)) -> 45698 | R69: Feb 10, 2025 | S69: 510.94 | T69: =DATE(RIGHT(R69,4),MATCH(LEFT(R69,3),{"Jan","Feb","Mar","Apr","May","Jun","Jul","Aug","Sep","Oct","Nov","Dec"},0),MID(R69,5,2)) -> 45698 | V69: Feb 10, 2025 | W69: 512.03 | X69: =DATE(RIGHT(V69,4),MATCH(LEFT(V69,3),{"Jan","Feb","Mar","Apr","May","Jun","Jul","Aug","Sep","Oct","Nov","Dec"},0),MID(V69,5,2)) -> 45698
B70: 45894 | C70: 2639.05 | E70: 45894 | F70: 24426.85 | H70: 45894 | I70: 1149.99 | K70: 45894 | L70: 725.85 | N70: Feb 3, 2025 | O70: 1078.42 | P70: 45691 | R70: Feb 3, 2025 | S70: 554.4 | T70: 45691 | V70: Feb 3, 2025 | W70: 519.13 | X70: 45691
B71: 45901 | C71: 2612.86 | E71: 45901 | F71: 24741 | H71: 45901 | I71: 1202.01 | K71: 45901 | L71: 731.7 | N71: Jan 27, 2025 | O71: 1161.19 | P71: =DATE(RIGHT(N71,4),MATCH(LEFT(N71,3),{"Jan","Feb","Mar","Apr","May","Jun","Jul","Aug","Sep","Oct","Nov","Dec"},0),MID(N71,5,2)) -> 45684 | R71: Jan 27, 2025 | S71: 605.65 | T71: =DATE(RIGHT(R71,4),MATCH(LEFT(R71,3),{"Jan","Feb","Mar","Apr","May","Jun","Jul","Aug","Sep","Oct","Nov","Dec"},0),MID(R71,5,2)) -> 45684 | V71: Jan 27, 2025 | W71: 530.94 | X71: =DATE(RIGHT(V71,4),MATCH(LEFT(V71,3),{"Jan","Feb","Mar","Apr","May","Jun","Jul","Aug","Sep","Oct","Nov","Dec"},0),MID(V71,5,2)) -> 45684
B72: 45908 | C72: 2560.37 | E72: 45908 | F72: 25114 | H72: 45908 | I72: 1211.06 | K72: 45908 | L72: 734.55 | N72: Jan 20, 2025 | O72: 1101.42 | P72: =DATE(RIGHT(N72,4),MATCH(LEFT(N72,3),{"Jan","Feb","Mar","Apr","May","Jun","Jul","Aug","Sep","Oct","Nov","Dec"},0),MID(N72,5,2)) -> 45677 | R72: Jan 20, 2025 | S72: 533.55 | T72: =DATE(RIGHT(R72,4),MATCH(LEFT(R72,3),{"Jan","Feb","Mar","Apr","May","Jun","Jul","Aug","Sep","Oct","Nov","Dec"},0),MID(R72,5,2)) -> 45677 | V72: Jan 20, 2025 | W72: 513.76 | X72: =DATE(RIGHT(V72,4),MATCH(LEFT(V72,3),{"Jan","Feb","Mar","Apr","May","Jun","Jul","Aug","Sep","Oct","Nov","Dec"},0),MID(V72,5,2)) -> 45677
B73: 45915 | C73: 2539.64 | E73: 45915 | F73: 25327.05 | H73: 45915 | I73: 1188.09 | K73: 45915 | L73: 720.15 | N73: Jan 13, 2025 | O73: 1157.35 | P73: =DATE(RIGHT(N73,4),MATCH(LEFT(N73,3),{"Jan","Feb","Mar","Apr","May","Jun","Jul","Aug","Sep","Oct","Nov","Dec"},0),MID(N73,5,2)) -> 45670 | R73: Jan 13, 2025 | S73: 546.66 | T73: =DATE(RIGHT(R73,4),MATCH(LEFT(R73,3),{"Jan","Feb","Mar","Apr","May","Jun","Jul","Aug","Sep","Oct","Nov","Dec"},0),MID(R73,5,2)) -> 45670 | V73: Jan 13, 2025 | W73: 518.09 | X73: =DATE(RIGHT(V73,4),MATCH(LEFT(V73,3),{"Jan","Feb","Mar","Apr","May","Jun","Jul","Aug","Sep","Oct","Nov","Dec"},0),MID(V73,5,2)) -> 45670
B74: 45922 | C74: 2492.21 | E74: 45922 | F74: 24654.7 | H74: 45922 | I74: 1156.36 | K74: 45922 | L74: 698.35 | N74: Jan 6, 2025 | O74: 1144.24 | P74: 45663 | R74: Jan 6, 2025 | S74: 570.42 | T74: 45663 | V74: Jan 6, 2025 | W74: 510.06 | X74: 45663
B75: 45929 | C75: 2525.05 | E75: 45929 | F75: 24894.25 | H75: 45929 | I75: 1163.62 | K75: 45929 | L75: 710.95 | N75: Dec 30, 2024 | O75: 1088.07 | P75: =DATE(RIGHT(N75,4),MATCH(LEFT(N75,3),{"Jan","Feb","Mar","Apr","May","Jun","Jul","Aug","Sep","Oct","Nov","Dec"},0),MID(N75,5,2)) -> 45656 | R75: Dec 30, 2024 | S75: 594.66 | T75: =DATE(RIGHT(R75,4),MATCH(LEFT(R75,3),{"Jan","Feb","Mar","Apr","May","Jun","Jul","Aug","Sep","Oct","Nov","Dec"},0),MID(R75,5,2)) -> 45656 | V75: Dec 30, 2024 | W75: 516.96 | X75: =DATE(RIGHT(V75,4),MATCH(LEFT(V75,3),{"Jan","Feb","Mar","Apr","May","Jun","Jul","Aug","Sep","Oct","Nov","Dec"},0),MID(V75,5,2)) -> 45656
B76: 45936 | C76: 2509.18 | E76: 45936 | F76: 25285.35 | H76: 45936 | I76: 1193.06 | K76: 45936 | L76: 714.3 | N76: Dec 23, 2024 | O76: 1040.47 | P76: =DATE(RIGHT(N76,4),MATCH(LEFT(N76,3),{"Jan","Feb","Mar","Apr","May","Jun","Jul","Aug","Sep","Oct","Nov","Dec"},0),MID(N76,5,2)) -> 45649 | R76: Dec 23, 2024 | S76: 571.24 | T76: =DATE(RIGHT(R76,4),MATCH(LEFT(R76,3),{"Jan","Feb","Mar","Apr","May","Jun","Jul","Aug","Sep","Oct","Nov","Dec"},0),MID(R76,5,2)) -> 45649 | V76: Dec 23, 2024 | W76: 499.48 | X76: =DATE(RIGHT(V76,4),MATCH(LEFT(V76,3),{"Jan","Feb","Mar","Apr","May","Jun","Jul","Aug","Sep","Oct","Nov","Dec"},0),MID(V76,5,2)) -> 45649
B77: 45943 | C77: 2583.39 | E77: 45943 | F77: 25709.85 | H77: 45943 | I77: 1282.58 | K77: 45943 | L77: 735.15 | N77: Dec 16, 2024 | O77: 1042.22 | P77: =DATE(RIGHT(N77,4),MATCH(LEFT(N77,3),{"Jan","Feb","Mar","Apr","May","Jun","Jul","Aug","Sep","Oct","Nov","Dec"},0),MID(N77,5,2)) -> 45642 | R77: Dec 16, 2024 | S77: 571.82 | T77: =DATE(RIGHT(R77,4),MATCH(LEFT(R77,3),{"Jan","Feb","Mar","Apr","May","Jun","Jul","Aug","Sep","Oct","Nov","Dec"},0),MID(R77,5,2)) -> 45642 | V77: Dec 16, 2024 | W77: 494.95 | X77: =DATE(RIGHT(V77,4),MATCH(LEFT(V77,3),{"Jan","Feb","Mar","Apr","May","Jun","Jul","Aug","Sep","Oct","Nov","Dec"},0),MID(V77,5,2)) -> 45642
B78: 45950 | C78: 2496.77 | E78: 45950 | F78: 25795.15 | H78: 45950 | I78: 1275.12 | K78: 45950 | L78: 725.85 | N78: Dec 9, 2024 | O78: 1083 | P78: 45635 | R78: Dec 9, 2024 | S78: 572.98 | T78: 45635 | V78: Dec 9, 2024 | W78: 505.04 | X78: 45635
B79: 45957 | C79: 2446.27 | E79: 45957 | F79: 25722.1 | H79: 45957 | I79: 1264.77 | K79: 45957 | L79: 719.95 | N79: Dec 2, 2024 | O79: 1203.82 | P79: 45628 | R79: Dec 2, 2024 | S79: 621.81 | T79: 45628 | V79: Dec 2, 2024 | W79: 515.88 | X79: 45628
B80: 45964 | C80: 2395.17 | E80: 45964 | F80: 25492.3 | H80: 45964 | I80: 1255.92 | K80: 45964 | L80: 711.6 | N80: Nov 25, 2024 | O80: 1212.79 | P80: =DATE(RIGHT(N80,4),MATCH(LEFT(N80,3),{"Jan","Feb","Mar","Apr","May","Jun","Jul","Aug","Sep","Oct","Nov","Dec"},0),MID(N80,5,2)) -> 45621 | R80: Nov 25, 2024 | S80: 661.97 | T80: =DATE(RIGHT(R80,4),MATCH(LEFT(R80,3),{"Jan","Feb","Mar","Apr","May","Jun","Jul","Aug","Sep","Oct","Nov","Dec"},0),MID(R80,5,2)) -> 45621 | V80: Nov 25, 2024 | W80: 519.17 | X80: =DATE(RIGHT(V80,4),MATCH(LEFT(V80,3),{"Jan","Feb","Mar","Apr","May","Jun","Jul","Aug","Sep","Oct","Nov","Dec"},0),MID(V80,5,2)) -> 45621
B81: 45971 | C81: 2427.7 | E81: 45971 | F81: 25910.05 | H81: 45971 | I81: 1264.77 | K81: 45971 | L81: 738.7 | N81: Nov 18, 2024 | O81: 1161.78 | P81: =DATE(RIGHT(N81,4),MATCH(LEFT(N81,3),{"Jan","Feb","Mar","Apr","May","Jun","Jul","Aug","Sep","Oct","Nov","Dec"},0),MID(N81,5,2)) -> 45614 | R81: Nov 18, 2024 | S81: 614.43 | T81: =DATE(RIGHT(R81,4),MATCH(LEFT(R81,3),{"Jan","Feb","Mar","Apr","May","Jun","Jul","Aug","Sep","Oct","Nov","Dec"},0),MID(R81,5,2)) -> 45614 | V81: Nov 18, 2024 | W81: 505.24 | X81: =DATE(RIGHT(V81,4),MATCH(LEFT(V81,3),{"Jan","Feb","Mar","Apr","May","Jun","Jul","Aug","Sep","Oct","Nov","Dec"},0),MID(V81,5,2)) -> 45614
B82: 45978 | C82: 2433.7 | E82: 45978 | F82: 26068.15 | H82: 45978 | I82: 1273.82 | K82: 45978 | L82: 739.9 | N82: Nov 11, 2024 | O82: 1145.02 | P82: =DATE(RIGHT(N82,4),MATCH(LEFT(N82,3),{"Jan","Feb","Mar","Apr","May","Jun","Jul","Aug","Sep","Oct","Nov","Dec"},0),MID(N82,5,2)) -> 45607 | R82: Nov 11, 2024 | S82: 618.28 | T82: =DATE(RIGHT(R82,4),MATCH(LEFT(R82,3),{"Jan","Feb","Mar","Apr","May","Jun","Jul","Aug","Sep","Oct","Nov","Dec"},0),MID(R82,5,2)) -> 45607 | V82: Nov 11, 2024 | W82: 500.41 | X82: =DATE(RIGHT(V82,4),MATCH(LEFT(V82,3),{"Jan","Feb","Mar","Apr","May","Jun","Jul","Aug","Sep","Oct","Nov","Dec"},0),MID(V82,5,2)) -> 45607
B83: 45985 | C83: 2466.6 | E83: 45985 | F83: 26202.95 | H83: 45985 | I83: 1254.33 | K83: 45985 | L83: 717.4 | N83: Nov 4, 2024 | O83: 1219.03 | P83: 45600 | R83: Nov 4, 2024 | S83: 644.24 | T83: 45600 | V83: Nov 4, 2024 | W83: 520.77 | X83: 45600
B84: 45992 | C84: 2338.6 | E84: 45992 | F84: 26186.45 | H84: 45992 | I84: 1240.2 | K84: 45992 | L84: 736.65 | N84: Oct 28, 2024 | O84: 1237.68 | P84: =DATE(RIGHT(N84,4),MATCH(LEFT(N84,3),{"Jan","Feb","Mar","Apr","May","Jun","Jul","Aug","Sep","Oct","Nov","Dec"},0),MID(N84,5,2)) -> 45593 | R84: Oct 28, 2024 | S84: 689.06 | T84: =DATE(RIGHT(R84,4),MATCH(LEFT(R84,3),{"Jan","Feb","Mar","Apr","May","Jun","Jul","Aug","Sep","Oct","Nov","Dec"},0),MID(R84,5,2)) -> 45593 | V84: Oct 28, 2024 | W84: 531.59 | X84: =DATE(RIGHT(V84,4),MATCH(LEFT(V84,3),{"Jan","Feb","Mar","Apr","May","Jun","Jul","Aug","Sep","Oct","Nov","Dec"},0),MID(V84,5,2)) -> 45593
B85: 45999 | C85: 2260.6 | E85: 45999 | F85: 26046.95 | H85: 45999 | I85: 1231.65 | K85: 45999 | L85: 727.05 | N85: Oct 21, 2024 | O85: 1253.36 | P85: =DATE(RIGHT(N85,4),MATCH(LEFT(N85,3),{"Jan","Feb","Mar","Apr","May","Jun","Jul","Aug","Sep","Oct","Nov","Dec"},0),MID(N85,5,2)) -> 45586 | R85: Oct 21, 2024 | S85: 620.82 | T85: =DATE(RIGHT(R85,4),MATCH(LEFT(R85,3),{"Jan","Feb","Mar","Apr","May","Jun","Jul","Aug","Sep","Oct","Nov","Dec"},0),MID(R85,5,2)) -> 45586 | V85: Oct 21, 2024 | W85: 527.82 | X85: =DATE(RIGHT(V85,4),MATCH(LEFT(V85,3),{"Jan","Feb","Mar","Apr","May","Jun","Jul","Aug","Sep","Oct","Nov","Dec"},0),MID(V85,5,2)) -> 45586
B86: 46006 | C86: 2280 | E86: 46006 | F86: 25966.4 | H86: 46006 | I86: 1237.72 | K86: 46006 | L86: 741.2 | N86: Oct 14, 2024 | O86: 1296.94 | P86: =DATE(RIGHT(N86,4),MATCH(LEFT(N86,3),{"Jan","Feb","Mar","Apr","May","Jun","Jul","Aug","Sep","Oct","Nov","Dec"},0),MID(N86,5,2)) -> 45579 | R86: Oct 14, 2024 | S86: 674.06 | T86: =DATE(RIGHT(R86,4),MATCH(LEFT(R86,3),{"Jan","Feb","Mar","Apr","May","Jun","Jul","Aug","Sep","Oct","Nov","Dec"},0),MID(R86,5,2)) -> 45579 | V86: Oct 14, 2024 | W86: 559.86 | X86: =DATE(RIGHT(V86,4),MATCH(LEFT(V86,3),{"Jan","Feb","Mar","Apr","May","Jun","Jul","Aug","Sep","Oct","Nov","Dec"},0),MID(V86,5,2)) -> 45579
B87: 46013 | C87: 2285.4 | E87: 46013 | F87: 26042.3 | H87: 46013 | I87: 1265.77 | K87: 46013 | L87: 743.3 | N87: Oct 7, 2024 | O87: 1277.09 | P87: 45572 | R87: Oct 7, 2024 | S87: 702.34 | T87: 45572 | V87: Oct 7, 2024 | W87: 559.32 | X87: 45572
B88: 46020 | C88: 2348 | E88: 46020 | F88: 26328.55 | H88: 46020 | I88: 1272.83 | K88: 46020 | L88: 757.75 | N88: Sep 30, 2024 | O88: 1303.83 | P88: =DATE(RIGHT(N88,4),MATCH(LEFT(N88,3),{"Jan","Feb","Mar","Apr","May","Jun","Jul","Aug","Sep","Oct","Nov","Dec"},0),MID(N88,5,2)) -> 45565 | R88: Sep 30, 2024 | S88: 714.45 | T88: =DATE(RIGHT(R88,4),MATCH(LEFT(R88,3),{"Jan","Feb","Mar","Apr","May","Jun","Jul","Aug","Sep","Oct","Nov","Dec"},0),MID(R88,5,2)) -> 45565 | V88: Sep 30, 2024 | W88: 560.89 | X88: =DATE(RIGHT(V88,4),MATCH(LEFT(V88,3),{"Jan","Feb","Mar","Apr","May","Jun","Jul","Aug","Sep","Oct","Nov","Dec"},0),MID(V88,5,2)) -> 45565
B89: 46027 | C89: 2372.6 | E89: 46027 | F89: 25683.3 | H89: 46027 | I89: 1292.12 | K89: 46027 | L89: 753.45 | N89: Sep 23, 2024 | O89: 1347.9 | P89: =DATE(RIGHT(N89,4),MATCH(LEFT(N89,3),{"Jan","Feb","Mar","Apr","May","Jun","Jul","Aug","Sep","Oct","Nov","Dec"},0),MID(N89,5,2)) -> 45558 | R89: Sep 23, 2024 | S89: 722.92 | T89: =DATE(RIGHT(R89,4),MATCH(LEFT(R89,3),{"Jan","Feb","Mar","Apr","May","Jun","Jul","Aug","Sep","Oct","Nov","Dec"},0),MID(R89,5,2)) -> 45558 | V89: Sep 23, 2024 | W89: 620.22 | X89: =DATE(RIGHT(V89,4),MATCH(LEFT(V89,3),{"Jan","Feb","Mar","Apr","May","Jun","Jul","Aug","Sep","Oct","Nov","Dec"},0),MID(V89,5,2)) -> 45558
B90: 46034 | C90: 2360.4 | E90: 46034 | F90: 25694.35 | H90: 46034 | I90: 1308.83 | K90: 46034 | L90: 760.15 | N90: Sep 16, 2024 | O90: 1413.86 | P90: =DATE(RIGHT(N90,4),MATCH(LEFT(N90,3),{"Jan","Feb","Mar","Apr","May","Jun","Jul","Aug","Sep","Oct","Nov","Dec"},0),MID(N90,5,2)) -> 45551 | R90: Sep 16, 2024 | S90: 718.97 | T90: =DATE(RIGHT(R90,4),MATCH(LEFT(R90,3),{"Jan","Feb","Mar","Apr","May","Jun","Jul","Aug","Sep","Oct","Nov","Dec"},0),MID(R90,5,2)) -> 45551 | V90: Sep 16, 2024 | W90: 654.07 | X90: =DATE(RIGHT(V90,4),MATCH(LEFT(V90,3),{"Jan","Feb","Mar","Apr","May","Jun","Jul","Aug","Sep","Oct","Nov","Dec"},0),MID(V90,5,2)) -> 45551
B91: 46041 | C91: 2409.5 | E91: 46041 | F91: 25048.65 | H91: 46041 | I91: 1286.85 | K91: 46041 | L91: 740.95 | N91: Sep 9, 2024 | O91: 1447.54 | P91: 45544 | R91: Sep 9, 2024 | S91: 757.93 | T91: 45544 | V91: Sep 9, 2024 | W91: 647.55 | X91: 45544
B92: 46048 | C92: 2350.7 | E92: 46048 | F92: 24825.45 | H92: 46048 | I92: 1275.61 | K92: 46048 | L92: 720.65 | N92: Sep 2, 2024 | O92: 1401.09 | P92: 45537 | R92: Sep 2, 2024 | S92: 800.87 | T92: 45537 | V92: Sep 2, 2024 | W92: 631.39 | X92: 45537
B93: 46055 | C93: 2424.2 | E93: 46055 | F93: 25693.7 | H93: 46055 | I93: 1296.3 | K93: 46055 | L93: 752.75 | N93: Aug 26, 2024 | O93: 1437.73 | P93: =DATE(RIGHT(N93,4),MATCH(LEFT(N93,3),{"Jan","Feb","Mar","Apr","May","Jun","Jul","Aug","Sep","Oct","Nov","Dec"},0),MID(N93,5,2)) -> 45530 | R93: Aug 26, 2024 | S93: 782.11 | T93: =DATE(RIGHT(R93,4),MATCH(LEFT(R93,3),{"Jan","Feb","Mar","Apr","May","Jun","Jul","Aug","Sep","Oct","Nov","Dec"},0),MID(R93,5,2)) -> 45530 | V93: Aug 26, 2024 | W93: 624.28 | X93: =DATE(RIGHT(V93,4),MATCH(LEFT(V93,3),{"Jan","Feb","Mar","Apr","May","Jun","Jul","Aug","Sep","Oct","Nov","Dec"},0),MID(V93,5,2)) -> 45530
B94: 46062 | C94: 2305.2 | E94: 46062 | F94: 25471.1 | H94: 46062 | I94: 1282.6 | K94: 46062 | L94: 760.15 | N94: Aug 19, 2024 | O94: 1386.43 | P94: =DATE(RIGHT(N94,4),MATCH(LEFT(N94,3),{"Jan","Feb","Mar","Apr","May","Jun","Jul","Aug","Sep","Oct","Nov","Dec"},0),MID(N94,5,2)) -> 45523 | R94: Aug 19, 2024 | S94: 778.17 | T94: =DATE(RIGHT(R94,4),MATCH(LEFT(R94,3),{"Jan","Feb","Mar","Apr","May","Jun","Jul","Aug","Sep","Oct","Nov","Dec"},0),MID(R94,5,2)) -> 45523 | V94: Aug 19, 2024 | W94: 630.26 | X94: =DATE(RIGHT(V94,4),MATCH(LEFT(V94,3),{"Jan","Feb","Mar","Apr","May","Jun","Jul","Aug","Sep","Oct","Nov","Dec"},0),MID(V94,5,2)) -> 45523
B95: 46069 | C95: 2314.5 | E95: 46069 | F95: 25571.25 | H95: 46069 | I95: 1293.8 | K95: 46069 | L95: 788.2 | N95: Aug 12, 2024 | O95: 1358.84 | P95: =DATE(RIGHT(N95,4),MATCH(LEFT(N95,3),{"Jan","Feb","Mar","Apr","May","Jun","Jul","Aug","Sep","Oct","Nov","Dec"},0),MID(N95,5,2)) -> 45516 | R95: Aug 12, 2024 | S95: 792.84 | T95: =DATE(RIGHT(R95,4),MATCH(LEFT(R95,3),{"Jan","Feb","Mar","Apr","May","Jun","Jul","Aug","Sep","Oct","Nov","Dec"},0),MID(R95,5,2)) -> 45516 | V95: Aug 12, 2024 | W95: 605.13 | X95: =DATE(RIGHT(V95,4),MATCH(LEFT(V95,3),{"Jan","Feb","Mar","Apr","May","Jun","Jul","Aug","Sep","Oct","Nov","Dec"},0),MID(V95,5,2)) -> 45516
B96: 46076 | C96: 2338.1 | E96: 46076 | F96: 25178.65 | H96: 46076 | I96: 1291.7 | K96: 46076 | L96: 788.65 | N96: Aug 5, 2024 | O96: 1397.29 | P96: 45509 | R96: Aug 5, 2024 | S96: 767.01 | T96: 45509 | V96: Aug 5, 2024 | W96: 611.35 | X96: 45509
B97: 46083 | C97: 2225.7 | E97: 46083 | F97: 24450.45 | H97: 46083 | I97: 1252.4 | K97: 46083 | L97: 785.25 | N97: Jul 29, 2024 | O97: 1411.17 | P97: =DATE(RIGHT(N97,4),MATCH(LEFT(N97,3),{"Jan","Feb","Mar","Apr","May","Jun","Jul","Aug","Sep","Oct","Nov","Dec"},0),MID(N97,5,2)) -> 45502 | R97: Jul 29, 2024 | S97: 749.46 | T97: =DATE(RIGHT(R97,4),MATCH(LEFT(R97,3),{"Jan","Feb","Mar","Apr","May","Jun","Jul","Aug","Sep","Oct","Nov","Dec"},0),MID(R97,5,2)) -> 45502 | V97: Jul 29, 2024 | W97: 614.88 | X97: =DATE(RIGHT(V97,4),MATCH(LEFT(V97,3),{"Jan","Feb","Mar","Apr","May","Jun","Jul","Aug","Sep","Oct","Nov","Dec"},0),MID(V97,5,2)) -> 45502
B98: 46090 | C98: 2160 | E98: 46090 | F98: 23151.1 | H98: 46090 | I98: 1202.2 | K98: 46090 | L98: 752.4 | N98: Jul 22, 2024 | O98: 1419.24 | P98: =DATE(RIGHT(N98,4),MATCH(LEFT(N98,3),{"Jan","Feb","Mar","Apr","May","Jun","Jul","Aug","Sep","Oct","Nov","Dec"},0),MID(N98,5,2)) -> 45495 | R98: Jul 22, 2024 | S98: 766.63 | T98: =DATE(RIGHT(R98,4),MATCH(LEFT(R98,3),{"Jan","Feb","Mar","Apr","May","Jun","Jul","Aug","Sep","Oct","Nov","Dec"},0),MID(R98,5,2)) -> 45495 | V98: Jul 22, 2024 | W98: 619.68 | X98: =DATE(RIGHT(V98,4),MATCH(LEFT(V98,3),{"Jan","Feb","Mar","Apr","May","Jun","Jul","Aug","Sep","Oct","Nov","Dec"},0),MID(V98,5,2)) -> 45495
B99: 46097 | C99: 2082.7 | E99: 46097 | F99: 23114.5 | H99: 46097 | I99: 1193.6 | K99: 46097 | L99: 744.3 | N99: Jul 15, 2024 | O99: 1404.15 | P99: =DATE(RIGHT(N99,4),MATCH(LEFT(N99,3),{"Jan","Feb","Mar","Apr","May","Jun","Jul","Aug","Sep","Oct","Nov","Dec"},0),MID(N99,5,2)) -> 45488 | R99: Jul 15, 2024 | S99: 769.23 | T99: =DATE(RIGHT(R99,4),MATCH(LEFT(R99,3),{"Jan","Feb","Mar","Apr","May","Jun","Jul","Aug","Sep","Oct","Nov","Dec"},0),MID(R99,5,2)) -> 45488 | V99: Jul 15, 2024 | W99: 617.47 | X99: =DATE(RIGHT(V99,4),MATCH(LEFT(V99,3),{"Jan","Feb","Mar","Apr","May","Jun","Jul","Aug","Sep","Oct","Nov","Dec"},0),MID(V99,5,2)) -> 45488
B100: 46104 | C100: 2074.4 | E100: 46104 | F100: 22819.6 | H100: 46104 | I100: 1193.2 | K100: 46104 | L100: 742.45 | N100: Jul 8, 2024 | O100: 1396.42 | P100: 45481 | R100: Jul 8, 2024 | S100: 734.36 | T100: 45481 | V100: Jul 8, 2024 | W100: 614.64 | X100: 45481
...

Sheet Beta - Comps
B2: S.No. | C2: Name | D2: CMP Rs. | E2: Mar Cap Rs.Cr. | F2: Debt Rs.Cr. | G2: Debt / Eq
B3: 1 | C3: Hindustan Unilever | D3: 2256.65 | E3: 530220.51 | F3: 1478 | G3: 0.03
B4: 2 | C4: Nestle India | D4: 1471 | E4: 283655.02 | F4: 444.16 | G4: 0.08
B5: 3 | C5: Marico | D5: 828.1 | E5: 107499.72 | F5: 557 | G5: 0.13
B6: 4 | C6: Godrej Consumer | D6: 1023 | E6: 104677.93 | F6: 4415.81 | G6: 0.35
B7: 5 | C7: Dabur India | D7: 473.55 | E7: 83993.12 | F7: 1287.32 | G7: 0.11
B8: 6 | C8: Emami | D8: 432.25 | E8: 18867.72 | F8: 71.96 | G8: 0.02
B335: 46146

Sheet Data Sheet Relative Valuation
B2: S.No. | C2: Name | D2: Ticker | E2: CMP Rs. | F2: No. Eq. Shares Cr. | G2: Mar Cap Rs.Cr. | H2: Debt Rs.Cr. | I2: Cash End Rs.Cr. | J2: EV | K2: EV Rs.Cr. | L2: Sales Rs.Cr. | M2: EBIDT Ann Rs.Cr. | N2: NP Ann Rs.Cr.
B3: 1 | C3: Hind. Unilever | D3: HINDUNILVR | E3: 2256.3 | F3: 234.96 | G3: 530138.31 | H3: 1478 | I3: 3248 | J3: =G3+H3-I3 -> 528368.31 | K3: 528368.31 | L3: 64468 | M3: 15790 | N3: 15059
B4: 2 | C4: Nestle India | D4: NESTLEIND | E4: 1466 | F4: 192.83 | G4: 282690.9 | H4: 444.16 | I4: 1340.87 | J4: =G4+H4-I4 -> 281794.19 | K4: 281794.19 | L4: 23154.6 | M4: 5346.41 | N4: 3544.6
B5: 3 | C5: Marico | D5: MARICO | E5: 838.35 | F5: 129.81 | G5: 108830.28 | H5: 557 | I5: 493 | J5: =G5+H5-I5 -> 108894.28 | K5: 108894.28 | L5: 13611 | M5: 2532 | N5: 1813
B6: 4 | C6: Godrej Consumer | D6: GODREJCP | E6: 1023.45 | F6: 102.32 | G6: 104723.99 | H6: 4415.81 | I6: 1005.41 | J6: =G6+H6-I6 -> 108134.39 | K6: 108134.39 | L6: 15177.9 | M6: 3422.41 | N6: 1861.47
B7: 5 | C7: Dabur India | D7: DABUR | E7: 460.15 | F7: 177.37 | G7: 81616.35 | H7: 1287.32 | I7: 562.07 | J7: =G7+H7-I7 -> 82341.6 | K7: 82341.6 | L7: 13192.57 | M7: 3049.81 | N7: 1868.69
B8: 6 | C8: Emami | D8: EMAMILTD | E8: 426.85 | F8: 43.65 | G8: 18632.01 | H8: 71.96 | I8: 272.9 | J8: =G8+H8-I8 -> 18431.07 | K8: 18475.62 | L8: 3817.46 | M8: 1043.04 | N8: 802.75
